Workbook
Name const_start: Inputs!$D$25
Name Constr_Finish_Date: Inputs!$E$27
Name Constr_Finish_Mo: Inputs!$D$27
Name Construction_Start_Date: Inputs!$E$25
Name Diligence_Begin_Date: Inputs!$E$20
Name Greenlight_Date: Inputs!$E$21
Name Greenlight_Mo: Inputs!$D$21
Name Land_Closing_Mo: Inputs!$D$22
Name lease_up_period: Inputs!$E$31
Name logistics_cost: '(Z+) Monthly CF'!$D$65
Name mod_costs: '(Z+) Monthly CF'!$D$64
Name perm_fees: '(Z+) Financing'!$H$22
Name perm_proceeds: '(Z+) Financing'!$H$19
Name refinance_date: Inputs!$E$34
Name sale_month: Inputs!$E$38

Sheet Inputs
C3: Inputs
C5: Location | F5: Budget Summary | G5: Budget | H5: $/Unit | J5: Underwriting Assumptions | N5: Massing Information
C6: Address | D6: 2828 STANFORD AVE | F6: Acquisition Costs | G6: =IFERROR('(Z+) Dev Budget'!G10,0) -> 1601600 | H6: =IFERROR(G6/$H$14,0) -> 7150 | J6: Vacancy & Credit Loss | L6: 0.03 | N6: Number of Buildings | O6: 1
C7: City | D7: Los Angeles | F7: Hard Costs | G7: =IFERROR('(Z+) Dev Budget'!G30,0) -> 44063340 | H7: =IFERROR(G7/$H$14,0) -> 196711.34 | J7: Rent Growth | L7: =Dashboard!W21 -> 0.025 | N7: Podium SF | O7: 14289
C8: State | D8: California | F8: Soft Costs | G8: ='(Z+) Dev Budget'!G109 -> 3635373 | H8: =+IFERROR(G8/$H$14,0) -> 16229.344 | J8: OpEx Ratio | L8: ='(Z+) OpEx'!D27 -> 0.31681548 | N8: Podium Levels | O8: 1
C9: Zip Code | D9: 90011-2018 | F9: Admin Costs | G9: ='(Z+) Dev Budget'!G115 -> 2608935.6 | H9: =+IFERROR(G9/$H$14,0) -> 11647.034 | J9: Construction Cost Escalation | L9: 0.04 | N9: # of Parking Stalls - Surface | O9: 38
F10: Financing Costs | G10: ='(Z+) Dev Budget'!G124 -> 8268359.9 | H10: =IFERROR(G10/$H$14,0) -> 36912.321 | J10: Rent Trending Begin Mo. | L10: =1 -> 1 | N10: # of Dwelling Units (Total) | O10: =SUM(O11:O13) -> 224
C11: Parcel Info | F11: Total | G11: =SUM(G6:G10) -> 60177608 | H11: =G11/$H$14 -> 268650.04 | J11: Precon Soft Cost Expenditure | L11: =60/100 -> 0.6 | N11: 1-BR 1-BA | O11: 224
C12: Zoning | D12: R3-1 | N12: 2-BR 1-BA | O12: 0
C13: Gross Lot Size (SF) | D13: 29482 | F13: Effective Development Potential | J13: Capital Stack | N13: 3-BR 2-BA | O13: 0
C14: Lot Length (ft) | D14: 216 | F14: Dwelling Units | H14: =O10 -> 224 | J14: Acquisition | N14: Service Modules (Total) | O14: =SUM(O15:O20) -> 17
C15: Lot Width (ft) | D15: 135 | F15: Moduler Units | H15: =(O11*1)+(O12*2)+(O13*2) -> 224 | J15: Equity | K15: =L15/SUM($L$15:$L$16) -> 1 | L15: ='(Z+) Dev Budget'!G118*(1-'(Z+) Financing'!D18) -> 15572775 | N15: Staircase Unit | O15: 17
C16: Gross Building SF | D16: 13582.5 | F16: Parking Stalls | H16: =O9 -> 38 | J16: Debt | K16: =L16/SUM($L$15:$L$16) -> 0 | L16: ='(Z+) Financing'!D10 -> 0 | N16: Bike Parking Units | O16: 0
C17: Net Rentable SF | D17: 101416 | J17: Total Acquisition Capitalization | L17: =+SUM(L15:L16) -> 15572775 | N17: Laundry Rooms | O17: 0
J18: Development | N18: Lobbies | O18: 0
C19: Timing Assumptions | D19: Month | E19: Date | F19: Rent Growth | G19: Exp Growth | J19: Equity | K19: =L19/SUM($L$19,$L$20) -> 0.39618737 | L19: ='(Z+) Dev Budget'!G126-L20 -> 23841608 | N19: Mechanical Rooms | O19: 0
C20: Diligence Begin Date | D20: 1 | E20: 46357 | F20: =+IFERROR(INDEX('(Z+) Monthly CF'!$F$9:$HB$9,1,MATCH(Inputs!$D20,'(Z+) Monthly CF'!$F$5:$HB$5,0)),0) -> 1 | G20: =+IFERROR(INDEX('(Z+) Monthly CF'!$F$10:$HB$10,1,MATCH(Inputs!D20,'(Z+) Monthly CF'!$F$5:$HB$5,0)),0) -> 1 | J20: Senior Debt | K20: =L20/SUM($L$19,$L$20) -> 0.60381263 | L20: ='(Z+) Financing'!D38 -> 36336000 | N20: Other Service Mods | O20: 0
C21: Greenlight Date | D21: 4 | E21: =+IFERROR(EOMONTH(E20,D21-1),0) -> 46477 | F21: =+IFERROR(INDEX('(Z+) Monthly CF'!$F$9:$HB$9,1,MATCH(Inputs!$D21,'(Z+) Monthly CF'!$F$5:$HB$5,0)),0) -> 1.0061922 | G21: =+IFERROR(INDEX('(Z+) Monthly CF'!$F$10:$HB$10,1,MATCH(Inputs!D21,'(Z+) Monthly CF'!$F$5:$HB$5,0)),0) -> 1.0074171 | J21: Total Development Capitalization | L21: =+SUM(L19,L20) -> 60177608 | N21: Total # of Modules | O21: =(O11*1)+(O12*2)+(O13*2)+O14 -> 241
C22: Land Closing Date | D22: =Greenlight_Mo -> 4 | E22: =+IFERROR(EOMONTH(E20,D21-1),0) -> 46477 | F22: =+IFERROR(INDEX('(Z+) Monthly CF'!$F$9:$HB$9,1,MATCH(Inputs!$D22,'(Z+) Monthly CF'!$F$5:$HB$5,0)),0) -> 1.0061922 | G22: =+IFERROR(INDEX('(Z+) Monthly CF'!$F$10:$HB$10,1,MATCH(Inputs!D22,'(Z+) Monthly CF'!$F$5:$HB$5,0)),0) -> 1.0074171 | J22: Stabilization
C23: Preconstruction Period (Months) | E23: 6 | J23: Equity | K23: =(L23/SUM($L$23:$L$24)) -> 0.19206922 | L23: ='(Z+) Dev Budget'!G126-L24-'(Z+) Dev Budget'!G129+'(Z+) Financing'!H22*'(Z+) Financing'!H19 -> 11444788 | N23: Affordability/Set-Aside Detail
C24: RTI Date | D24: =+IFERROR(D21+E23,0) -> 10 | E24: =EOMONTH(E21,E23) -> 46660 | J24: Debt | K24: =(L24/SUM($L$23:$L$24)) -> 0.80793078 | L24: ='(Z+) Financing'!H19 -> 48142000 | N24: Set Aside Options | O24: # of Units
C25: Construction Start | D25: =+D24 -> 10 | E25: =+EOMONTH(E21,E23) -> 46660 | F25: =+INDEX('(Z+) Monthly CF'!$F$9:$HB$9,1,MATCH(Inputs!$D25,'(Z+) Monthly CF'!$F$5:$HB$5,0)) -> 1.018692 | G25: =+INDEX('(Z+) Monthly CF'!$F$10:$HB$10,1,MATCH(Inputs!D25,'(Z+) Monthly CF'!$F$5:$HB$5,0)) -> 1.0224167 | J25: Total Stabilized Capitalization | L25: =+SUM(L23:L24) -> 59586788 | N25: Required ELI Units | O25: 0
C26: Construction Timeline (Months) | E26: =Dashboard!W19 -> 11 | N26: Required VLI Units | O26: 0
C27: Construction Finishing Date | D27: =+IFERROR(E26+D25,0) -> 21 | E27: =EOMONTH(E25,E26) -> 46996 | F27: =+INDEX('(Z+) Monthly CF'!$F$9:$HB$9,1,MATCH(Inputs!$D27,'(Z+) Monthly CF'!$F$5:$HB$5,0)) -> 1.0420129 | G27: =+INDEX('(Z+) Monthly CF'!$F$10:$HB$10,1,MATCH(Inputs!D27,'(Z+) Monthly CF'!$F$5:$HB$5,0)) -> 1.0504983 | J27: Model Z Schedule | K27: Duration (Months) | L27: Date | N27: Required LI Units | O27: =ROUNDUP((H14-1)*0.8,0) -> 179
C28: Total Development Timeline | E28: =SUM(E26,E23) -> 17 | J28: Site Acquisition and Planning | K28: 3 | L28: =Greenlight_Date-27 -> 46450 | N28: Required Mod Units | O28: =H14-1-O27 -> 44
C29: Occupancy Date | D29: =+IFERROR(D27+1,0) -> 22 | E29: =+EOMONTH(E27,1) -> 47026 | F29: =+INDEX('(Z+) Monthly CF'!$F$9:$HB$9,1,MATCH(Inputs!$D29,'(Z+) Monthly CF'!$F$5:$HB$5,0)) -> 1.0441593 | G29: =+INDEX('(Z+) Monthly CF'!$F$10:$HB$10,1,MATCH(Inputs!D29,'(Z+) Monthly CF'!$F$5:$HB$5,0)) -> 1.0530344 | J29: Z/Suite Design | K29: 3 | L29: =+L28 -> 46450 | N29: ED1/100% Affordable? | O29: No
C30: Leased Units/Month | E30: 30 | J30: Permits and Entitlement | K30: 6 | L30: =+EOMONTH(L28,K28-1) -> 46538 | N30: HUD/TCAC AMI | O30: 1
C31: Lease-Up Period | E31: =+ROUNDUP('(Z+) Rent Roll'!E20/E30,0) -> 8 | J31: Site Prep and Preconstruction | K31: 6 | L31: =+EOMONTH(L30,K30) -> 46721 | N31: HCD AMI | O31: 1
C32: Refinancing Period | E32: =3 -> 3 | J32: Modular Manufacturing | K32: 2 | L32: =+EOMONTH(L30,K30+4) -> 46843 | N32: Set Aside Restricted Units (HCD) | O32: =SUM(O25:O28) -> 223
C33: Stabilization Period (Months) | E33: =+E32+E31 -> 11 | J33: Construction | K33: 12 | L33: =+EOMONTH(L31,K31) -> 46904
C34: Stabilization/Refinance Date | D34: =33 -> 33 | E34: =EOMONTH(E29,E33) -> 47361 | F34: =+INDEX('(Z+) Monthly CF'!$F$9:$HB$9,1,MATCH(Inputs!$D34,'(Z+) Monthly CF'!$F$5:$HB$5,0)) -> 1.0680633 | G34: =+INDEX('(Z+) Monthly CF'!$F$10:$HB$10,1,MATCH(Inputs!D34,'(Z+) Monthly CF'!$F$5:$HB$5,0)) -> 1.0813379 | N34: Legend
C35: Time to Stabilization | E35: =ROUND(DAYS360(E21,E34)/30,0) -> 29 | N35: Inputs (Z/Suite) | O35: Light Blue
C36: Total Hold Period (Months) | E36: =IFERROR(Dashboard!W20,0) -> 84 | N36: Editable Variables | O36: Blue
C37: Total Hold Period (Fiscal Years) | E37: =ROUNDUP((E36)/12,1) -> 7 | N37: Formulas | O37: Black
C38: Sale Month | D38: =+E36+D22 -> 88 | E38: =EOMONTH(E22,E36) -> 49034 | F38: =+IFERROR(INDEX('(Z+) Monthly CF'!$F$9:$HB$9,1,MATCH(Inputs!$D38,'(Z+) Monthly CF'!$F$5:$HB$5,0)),0) -> 1.1960464 | G38: =+IFERROR(INDEX('(Z+) Monthly CF'!$F$10:$HB$10,1,MATCH(Inputs!D38,'(Z+) Monthly CF'!$F$5:$HB$5,0)),0) -> 1.2346843

Sheet Dashboard
A1: Project Overview
A3: Project Info | D3: Total Uses | F3: /Unit | G3: Percentage | I3: Assumed Exit Cap Rate | K3: IRR | M3: Year | O3: =IFERROR(1,0) -> 1 | P3: =IFERROR(O3+1,0) -> 2 | Q3: =IFERROR(P3+1,0) -> 3 | R3: =IFERROR(Q3+1,0) -> 4 | S3: =IFERROR(R3+1,0) -> 5 | T3: =IFERROR(S3+1,0) -> 6 | U3: =IFERROR(T3+1,0) -> 7 | V3: =IFERROR(U3+1,0) -> 8
A4: Address | B4: =Inputs!D6 -> 2828 STANFORD AVE | D4: Land Acquistions | E4: =IFERROR(Inputs!G6,0) -> 1601600 | F4: =IFERROR(E4/$B$10,0) -> 7150 | G4: =IFERROR(E4/$E$10,0) -> 0.026614551 | I4: Best case | J4: =IFERROR(J5-0.005,0) -> 0.0625 | K4: =IFERROR(22.1/100,0) -> 0.221 | M4: Date | O4: =IFERROR(TEXT(Inputs!E22, "yyyy"),0) -> 2027 | P4: =IFERROR(TEXT(Inputs!E22+365, "yyyy"),0) -> 2028 | Q4: =IFERROR(TEXT(Inputs!E22+(365*2), "yyyy"),0) -> 2029 | R4: =IFERROR(TEXT(Inputs!E22+(365*3), "yyyy"),0) -> 2030 | S4: =IFERROR(TEXT(Inputs!E22+(365*4),"yyyy"),0) -> 2031 | T4: =IFERROR(TEXT(Inputs!E22+(365*5), "yyyy"),0) -> 2032 | U4: =IFERROR(TEXT(Inputs!E22+(365*6), "yyyy"),0) -> 2033 | V4: =IFERROR(TEXT(Inputs!E22+(365*7), "yyyy"),0) -> 2034
A5: Levered IRR | B5: ='(Z+) Financing'!K7 -> 0.15538478 | D5: Modular Cost | E5: =IFERROR('(Z+) Dev Budget'!G14,0) -> 20160000 | F5: =IFERROR(E5/$B$10,0) -> 90000 | G5: =IFERROR(E5/$E$10,0) -> 0.33500833 | I5: Base Case | J5: 0.0675 | K5: =IFERROR(B5,0) -> 0.15538478 | M5: Project Costs | O5: =IFERROR(SUMIF('(Z+) Monthly CF'!F6:EU6,"=1",'(Z+) Monthly CF'!F70:EU70),0) -> -27147049 | P5: =IFERROR(SUMIF('(Z+) Monthly CF'!F6:EU6,"=2",'(Z+) Monthly CF'!F70:EU70),0) -> -24769287 | Q5: =IFERROR(SUMIF('(Z+) Monthly CF'!F6:EU6,"=3",'(Z+) Monthly CF'!F70:EU70),0) -> 0 | R5: =IFERROR(SUMIF('(Z+) Monthly CF'!F6:EU6,"=4",'(Z+) Monthly CF'!F70:EU70),0) -> 0 | S5: =IFERROR(SUMIF('(Z+) Monthly CF'!F6:EU6,"=5",'(Z+) Monthly CF'!F70:EU70),0) -> 0 | T5: =IFERROR(SUMIF('(Z+) Monthly CF'!F6:EU6,"=6",'(Z+) Monthly CF'!F70:EU70),0) -> 0 | U5: =IFERROR(SUMIF('(Z+) Monthly CF'!F6:EU6,"=8",'(Z+) Monthly CF'!F70:EU70),0) -> 0 | V5: =IFERROR(SUMIF('(Z+) Monthly CF'!G6:EV6,"=7",'(Z+) Monthly CF'!G70:EV70),0) -> 0
A6: Equity Multiple | B6: ='(Z+) Financing'!K12 -> 1.7201935 | D6: On-Site Hard Costs | E6: =IFERROR(Inputs!G7-'(Z+) Dev Budget'!G14,0) -> 23903340 | F6: =IFERROR(E6/$B$10,0) -> 106711.34 | G6: =IFERROR(E6/$E$10,0) -> 0.39721319 | I6: Worst Case | J6: =IFERROR(J5+0.005,0) -> 0.0725 | K6: =IFERROR(12.6/100,0) -> 0.126 | M6: Constr. Loan Proceeds | O6: =IFERROR(SUMIF('(Z+) Monthly CF'!F6:EU6,"=1",'(Z+) Monthly CF'!F89:EU89),0) -> 3305440.6 | P6: =IFERROR(SUMIF('(Z+) Monthly CF'!F6:EU6,"=2",'(Z+) Monthly CF'!F89:EU89),0) -> 24769287 | Q6: =IFERROR(SUMIF('(Z+) Monthly CF'!F6:EU6,"=3",'(Z+) Monthly CF'!F89:EU89),0) -> 0 | R6: =IFERROR(SUMIF('(Z+) Monthly CF'!F6:EU6,"=4",'(Z+) Monthly CF'!F89:EU89),0) -> 0 | S6: =IFERROR(SUMIF('(Z+) Monthly CF'!F6:EV6,"=5",'(Z+) Monthly CF'!F89:EV89),0) -> 0 | T6: =IFERROR(SUMIF('(Z+) Monthly CF'!F6:EW6,"=6",'(Z+) Monthly CF'!F89:EW89),0) -> 0 | U6: =IFERROR(SUMIF('(Z+) Monthly CF'!F6:EX6,"=7",'(Z+) Monthly CF'!F89:EX89),0) -> 0 | V6: =IFERROR(SUMIF('(Z+) Monthly CF'!G6:EY6,"=8",'(Z+) Monthly CF'!G89:EY89),0) -> 0
A7: Cash-on-Cash Return | B7: ='(Z+) Financing'!K9 -> 0.17628922 | D7: Soft Costs | E7: =IFERROR(Inputs!G8,0) -> 3635373 | F7: =IFERROR(E7/$B$10,0) -> 16229.344 | G7: =IFERROR(E7/$E$10,0) -> 0.060410726 | M7: Constr. Loan Re-Payment | O7: =IFERROR(SUMIF('(Z+) Monthly CF'!F6:EU6,"=1",'(Z+) Monthly CF'!F92:EU92)+SUMIF('(Z+) Monthly CF'!F6:EU6,"=1",'(Z+) Monthly CF'!F77:EU77),0) -> 5578.6791 | P7: =IFERROR(SUMIF('(Z+) Monthly CF'!G6:EV6,"=2",'(Z+) Monthly CF'!G92:EV92)-SUMIF('(Z+) Monthly CF'!G6:EV6,"=2",'(Z+) Monthly CF'!G77:EV77),0) -> -1895624.3 | Q7: =IFERROR(SUMIF('(Z+) Monthly CF'!H6:EW6,"=3",'(Z+) Monthly CF'!H92:EW92)-SUMIF('(Z+) Monthly CF'!H6:EW6,"=3",'(Z+) Monthly CF'!H77:EW77),0) -> -34312336 | R7: =IFERROR(SUMIF('(Z+) Monthly CF'!I6:EX6,"=4",'(Z+) Monthly CF'!I92:EX92)-SUMIF('(Z+) Monthly CF'!I6:EX6,"=4",'(Z+) Monthly CF'!I77:EX77),0) -> 0 | S7: =IFERROR(SUMIF('(Z+) Monthly CF'!G6:EV6,"=5",'(Z+) Monthly CF'!G92:EV92)-SUMIF('(Z+) Monthly CF'!I6:EX6,"=5",'(Z+) Monthly CF'!I77:EX77),0) -> 0 | T7: =IFERROR(SUMIF('(Z+) Monthly CF'!H6:EW6,"=6",'(Z+) Monthly CF'!H92:EW92)-SUMIF('(Z+) Monthly CF'!I6:EX6,"=6",'(Z+) Monthly CF'!I77:EX77),0) -> 0 | U7: =IFERROR(SUMIF('(Z+) Monthly CF'!I6:EX6,"=7",'(Z+) Monthly CF'!I92:EX92)-SUMIF('(Z+) Monthly CF'!I6:EX6,"=7",'(Z+) Monthly CF'!I77:EX77),0) -> 0 | V7: =IFERROR(SUMIF('(Z+) Monthly CF'!J6:EY6,"=8",'(Z+) Monthly CF'!J92:EY92)-SUMIF('(Z+) Monthly CF'!I6:EX6,"=8",'(Z+) Monthly CF'!I77:EX77),0) -> 0
A8: Untrended Return-on-Cost | B8: ='(Z+) Financing'!K11 -> 0.080198049 | D8: Admin Costs | E8: =IFERROR(Inputs!G9,0) -> 2608935.6 | F8: =IFERROR(E8/$B$10,0) -> 11647.034 | G8: =IFERROR(E8/$E$10,0) -> 0.043353927 | I8: Financing | J8: Constr. | K8: Perm. | M8: Gross Rental Income | O8: =IFERROR(SUMIF('(Z+) Monthly CF'!F6:EU6, "=1",'(Z+) Monthly CF'!F19:EU19),0) -> 0 | P8: =IFERROR(SUMIF('(Z+) Monthly CF'!G6:EV6, "=2",'(Z+) Monthly CF'!G19:EV19),0) -> 356945.09 | Q8: =IFERROR(SUMIF('(Z+) Monthly CF'!H6:EW6, "=3",'(Z+) Monthly CF'!H19:EW19),0) -> 5618733.6 | R8: =IFERROR(SUMIF('(Z+) Monthly CF'!I6:EX6, "=4",'(Z+) Monthly CF'!I19:EX19),0) -> 6683635.6 | S8: =IFERROR(SUMIF('(Z+) Monthly CF'!J6:EY6, "=5",'(Z+) Monthly CF'!J19:EY19),0) -> 6850726.5 | T8: =IFERROR(SUMIF('(Z+) Monthly CF'!K6:EZ6, "=6",'(Z+) Monthly CF'!K19:EZ19),0) -> 7021994.7 | U8: =IFERROR(SUMIF('(Z+) Monthly CF'!L6:FA6, "=7",'(Z+) Monthly CF'!L19:FA19),0) -> 7197544.5 | V8: =IFERROR(SUMIF('(Z+) Monthly CF'!M6:FB6, "=8",'(Z+) Monthly CF'!M19:FB19),0) -> 7377483.1
A9: Total Profit | B9: ='(Z+) Financing'!K14 -> 17170572 | D9: Financing Costs | E9: =IFERROR(Inputs!G10,0) -> 8268359.9 | F9: =IFERROR(E9/$B$10,0) -> 36912.321 | G9: =IFERROR(E4/$E$10,0) -> 0.026614551 | I9: Loan Proceeds | J9: =IFERROR('(Z+) Financing'!D38,0) -> 36336000 | K9: =IFERROR(perm_proceeds,0) -> 48142000 | M9: Operating Expenses | O9: =IFERROR(SUMIF('(Z+) Monthly CF'!F6:EU6,"=1",'(Z+) Monthly CF'!F47:EU47),0) -> 0 | P9: =IFERROR(SUMIF('(Z+) Monthly CF'!G6:EV6,"=2",'(Z+) Monthly CF'!G47:EV47),0) -> -322257.24 | Q9: =IFERROR(SUMIF('(Z+) Monthly CF'!H6:EW6,"=3",'(Z+) Monthly CF'!H47:EW47),0) -> -1645829.5 | R9: =IFERROR(SUMIF('(Z+) Monthly CF'!I6:EX6,"=4",'(Z+) Monthly CF'!I47:EX47),0) -> -1766930.5 | S9: =IFERROR(SUMIF('(Z+) Monthly CF'!J6:EY6,"=5",'(Z+) Monthly CF'!J47:EY47),0) -> -1817346.4 | T9: =IFERROR(SUMIF('(Z+) Monthly CF'!K6:EZ6,"=6",'(Z+) Monthly CF'!K47:EZ47),0) -> -1869206 | U9: =IFERROR(SUMIF('(Z+) Monthly CF'!L6:FA6,"=7",'(Z+) Monthly CF'!L47:FA47),0) -> -1922550.7 | V9: =IFERROR(SUMIF('(Z+) Monthly CF'!M6:FB6,"=8",'(Z+) Monthly CF'!M47:FB47),0) -> -1977423.2
A10: Unit Count | B10: =Inputs!O10 -> 224 | D10: Total | E10: =IFERROR(SUM(E4:E9),0) -> 60177608 | F10: =IFERROR(SUM(F4:F9),0) -> 268650.04 | G10: =IFERROR(SUM(G4:G9),0) -> 0.88921527 | I10: LTV | J10: =IFERROR('(Z+) Financing'!D34,0) -> 0.75 | K10: =IFERROR('(Z+) Financing'!H14,0) -> 0.75 | M10: NOI | O10: =IFERROR(Dashboard!O8+Dashboard!O9,0) -> 0 | P10: =IFERROR(Dashboard!P8+Dashboard!P9,0) -> 34687.856 | Q10: =IFERROR(Dashboard!Q8+Dashboard!Q9,0) -> 3972904.1 | R10: =IFERROR(Dashboard!R8+Dashboard!R9,0) -> 4916705.1 | S10: =IFERROR(Dashboard!S8+Dashboard!S9,0) -> 5033380.1 | T10: =IFERROR(Dashboard!T8+Dashboard!T9,0) -> 5152788.7 | U10: =IFERROR(Dashboard!U8+Dashboard!U9,0) -> 5274993.8 | V10: =IFERROR(SUM(V8:V9),0) -> 5400059.9
A11: Parking | B11: =Inputs!H16 -> 38 | I11: LTC | J11: 0.7 | K11: =IFERROR('(Z+) Financing'!H16,0) -> 0.8 | M11: Perm. Loan Proceeds | O11: =IFERROR(SUMIF('(Z+) Monthly CF'!F6:EU6,"=1",'(Z+) Monthly CF'!F95:EU95),0) -> 0 | P11: =IFERROR(SUMIF('(Z+) Monthly CF'!G6:EV6,"=2",'(Z+) Monthly CF'!G95:EV95),0) -> 0 | Q11: =IFERROR(SUMIF('(Z+) Monthly CF'!H6:EW6,"=3",'(Z+) Monthly CF'!H95:EW95),0) -> 48137186 | R11: =IFERROR(SUMIF('(Z+) Monthly CF'!I6:EX6,"=4",'(Z+) Monthly CF'!I95:EX95),0) -> 0 | S11: =IFERROR(SUMIF('(Z+) Monthly CF'!J6:EY6,"=5",'(Z+) Monthly CF'!J95:EY95),0) -> 0 | T11: =IFERROR(SUMIF('(Z+) Monthly CF'!K6:EZ6,"=6",'(Z+) Monthly CF'!K95:EZ95),0) -> 0 | U11: =IFERROR(SUMIF('(Z+) Monthly CF'!L6:FA6,"=7",'(Z+) Monthly CF'!L95:FA95),0) -> 0 | V11: =IFERROR(SUMIF('(Z+) Monthly CF'!M6:FB6,"=8",'(Z+) Monthly CF'!M95:FB95),0) -> 0
A12: NRSF | B12: =Inputs!D17 -> 101416 | D12: Total Sources | F12: /Unit | G12: Percentage | I12: Int. Rate | J12: 0.09 | K12: 0.0575 | M12: Debt Service | O12: =IFERROR((SUMIF('(Z+) Monthly CF'!F6:EU6,"=1",'(Z+) Monthly CF'!F96:EU96))+SUMIF('(Z+) Monthly CF'!F6:EU6,"=1",'(Z+) Monthly CF'!F97:EU97),0) -> 0 | P12: =IFERROR((SUMIF('(Z+) Monthly CF'!G6:EV6,"=2",'(Z+) Monthly CF'!G96:EV96))+SUMIF('(Z+) Monthly CF'!G6:EV6,"=2",'(Z+) Monthly CF'!G97:EV97),0) -> 0 | Q12: =IFERROR((SUMIF('(Z+) Monthly CF'!H6:EW6,"=3",'(Z+) Monthly CF'!H96:EW96))+SUMIF('(Z+) Monthly CF'!H6:EW6,"=3",'(Z+) Monthly CF'!H97:EW97),0) -> -807451.15 | R12: =IFERROR((SUMIF('(Z+) Monthly CF'!I6:EX6,"=4",'(Z+) Monthly CF'!I96:EX96))+SUMIF('(Z+) Monthly CF'!I6:EX6,"=4",'(Z+) Monthly CF'!I97:EX97),0) -> -3229804.6 | S12: =IFERROR((SUMIF('(Z+) Monthly CF'!J6:EY6,"=5",'(Z+) Monthly CF'!J96:EY96))+SUMIF('(Z+) Monthly CF'!J6:EY6,"=5",'(Z+) Monthly CF'!J97:EY97),0) -> -3229804.6 | T12: =IFERROR((SUMIF('(Z+) Monthly CF'!K6:EZ6,"=6",'(Z+) Monthly CF'!K96:EZ96))+SUMIF('(Z+) Monthly CF'!K6:EZ6,"=6",'(Z+) Monthly CF'!K97:EZ97),0) -> -3229804.6 | U12: =IFERROR((SUMIF('(Z+) Monthly CF'!L6:FA6,"=7",'(Z+) Monthly CF'!L96:FA96))+SUMIF('(Z+) Monthly CF'!L6:FA6,"=7",'(Z+) Monthly CF'!L97:FA97),0) -> -3229804.6 | V12: =IFERROR((SUMIF('(Z+) Monthly CF'!M6:FB6,"=8",'(Z+) Monthly CF'!M96:FB96))+SUMIF('(Z+) Monthly CF'!M6:FB6,"=8",'(Z+) Monthly CF'!M97:FB97),0) -> -1076601.5
A13: Total Development Cost | B13: =Inputs!G11 -> 60177608 | D13: Equity | E13: =IFERROR(Inputs!L19,0) -> 23841608 | F13: =IFERROR(E13/B10,0) -> 106435.75 | G13: =IFERROR(E13/$E$15,0) -> 0.39618737 | I13: DSCR | J13: N/A | K13: =IFERROR('(Z+) Financing'!H11,0) -> 1.2 | M13: Perm. Loan Re-Payment | O13: =IFERROR(SUMIF('(Z+) Monthly CF'!I6:EX6,"=1",'(Z+) Monthly CF'!F98:EX98),0) -> 0 | P13: =IFERROR(SUMIF('(Z+) Monthly CF'!G6:EY6,"=2",'(Z+) Monthly CF'!G98:EY98),0) -> 0 | Q13: =IFERROR(SUMIF('(Z+) Monthly CF'!H6:EZ6,"=3",'(Z+) Monthly CF'!H98:EZ98),0) -> 0 | R13: =IFERROR(SUMIF('(Z+) Monthly CF'!I6:FA6,"=4",'(Z+) Monthly CF'!I98:FA98),0) -> 0 | S13: =IFERROR(SUMIF('(Z+) Monthly CF'!J6:FB6,"=5",'(Z+) Monthly CF'!J98:FB98),0) -> 0 | T13: =IFERROR(SUMIF('(Z+) Monthly CF'!K6:FC6,"=6",'(Z+) Monthly CF'!K98:FC98),0) -> 0 | U13: =IFERROR(SUMIF('(Z+) Monthly CF'!L6:FD6,"=7",'(Z+) Monthly CF'!L98:FD98),0) -> 0 | V13: =IFERROR(SUMIF('(Z+) Monthly CF'!F6:FE6,"=8",'(Z+) Monthly CF'!F98:FE98),0) -> -45934519
A14: Price per Unit | B14: =Inputs!H11 -> 268650.04 | D14: Debt | E14: =IFERROR(SUM(Inputs!L20),0) -> 36336000 | F14: =IFERROR(E14/B10,0) -> 162214.29 | G14: =IFERROR(E14/$E$15,0) -> 0.60381263 | M14: Sale Proceeds | O14: =IFERROR(SUMIF('(Z+) Monthly CF'!F6:EW6,"=1",'(Z+) Monthly CF'!F54:EW54),0) -> 0 | P14: =IFERROR(SUMIF('(Z+) Monthly CF'!G6:EX6,"=2",'(Z+) Monthly CF'!G54:EX54),0) -> 0 | Q14: =IFERROR(SUMIF('(Z+) Monthly CF'!H6:EY6,"=3",'(Z+) Monthly CF'!H54:EY54),0) -> 0 | R14: =IFERROR(SUMIF('(Z+) Monthly CF'!I6:EZ6,"=4",'(Z+) Monthly CF'!I54:EZ54),0) -> 0 | S14: =IFERROR(SUMIF('(Z+) Monthly CF'!J6:FA6,"=5",'(Z+) Monthly CF'!J54:FA54),0) -> 0 | T14: =IFERROR(SUMIF('(Z+) Monthly CF'!K6:FB6,"=6",'(Z+) Monthly CF'!K54:FB54),0) -> 0 | U14: =IFERROR(SUMIF('(Z+) Monthly CF'!L6:FC6,"=7",'(Z+) Monthly CF'!L54:FC54),0) -> 0 | V14: =IFERROR(SUMIF('(Z+) Monthly CF'!M6:FD6,"=8",'(Z+) Monthly CF'!M54:FD54),0) -> 59724978
A15: Construction Type | B15: Modular | D15: Total | E15: =IFERROR(Inputs!L21,0) -> 60177608 | F15: =IFERROR(E15/B10,0) -> 268650.04 | G15: =IFERROR(SUM(G13:G14),0) -> 1 | M15: Levered Cash Flow | O15: =IFERROR(SUM(O5:O14),0) -> -23836030 | P15: =IFERROR(SUM(P5:P14),0) -> -1826248.5 | Q15: =IFERROR(SUM(Q5:Q14),0) -> 20963207 | R15: =IFERROR(SUM(R5:R14),0) -> 6603605.6 | S15: =IFERROR(SUM(S5:S14),0) -> 6836955.6 | T15: =IFERROR(SUM(T5:T14),0) -> 7075772.8 | U15: =IFERROR(SUM(U5:U14),0) -> 7320183.1 | V15: =IFERROR(SUM(V5:V14),0) -> 23513978
A17: IRR% - Construction Loan LTC vs Interest Rate | I17: IRR% - Hold Period vs Exit Cap | Q17: Operating Assumptions | R17: /Unit /Month | S17: Annual | T17: /Unit | V17: Drivers
A18: IRR% | E18: Interest Rate | I18: IRR% | M18: Exit Cap | Q18: Rent | R18: =IFERROR('(Z+) OpEx'!J31/Dashboard!B10/12,0) -> 2444.7968 | S18: =R18*12*$B$10 -> 6571613.8 | T18: =IFERROR(S18/$B$10,0) -> 29337.562 | V18: OnSite$ | W18: 90000
B19: ='(Z+) Monthly CF'!F103 -> 0.15538478 | C19: =E19-0.02 -> 0.07 | D19: =E19-0.01 -> 0.08 | E19: =9/100 -> 0.09 | F19: =E19+0.01 -> 0.1 | G19: =F19+0.01 -> 0.11 | J19: ='(Z+) Monthly CF'!F103 -> 0.15538478 | K19: =IFERROR(L19-0.25%,0) -> 0.0625 | L19: =IFERROR(M19-0.25%,0) -> 0.065 | M19: =IFERROR(6.75/100,0) -> 0.0675 | N19: =IFERROR(M19+0.25%,0) -> 0.07 | O19: =IFERROR(N19+0.25%,0) -> 0.0725 | Q19: Other Income | R19: =IFERROR('(Z+) OpEx'!J33/B10/12,0) -> 66.822844 | S19: =IFERROR('(Z+) OpEx'!J33,0) -> 179619.8 | T19: =IFERROR(S19/$B$10,0) -> 801.87412 | V19: Constr. Time | W19: 11
B20: =IFERROR(B21+0.05,0) -> 0.8 | C20: 0.17508472 | D20: 0.16905209 | E20: 0.1635294 | F20: 0.15849965 | G20: 0.15396062 | J20: =IFERROR(J21-12,0) -> 60 | K20: 0.18505458 | L20: 0.16565065 | M20: 0.14619973 | N20: 0.12658924 | O20: 0.10669253 | Q20: Total Rental Income | R20: =IFERROR(SUM(R18:R19),0) -> 2511.6196 | S20: =IFERROR(SUM(S18:S19),0) -> 6751233.6 | T20: =IFERROR(S20/$B$10,0) -> 30139.436 | V20: Hold Period | W20: 84
B21: =IFERROR(B22+0.05,0) -> 0.75 | C21: 0.16903169 | D21: 0.16388296 | E21: 0.15916845 | F21: 0.15487793 | G21: 0.15104044 | J21: =IFERROR(J22-12,0) -> 72 | K21: 0.18146794 | L21: 0.16638525 | M21: 0.15126211 | N21: 0.13601667 | O21: 0.12055787 | Q21: Vacancy & Credit Loss | R21: =IFERROR('(Z+) OpEx'!K34/B10/12,0) -> -73.343904 | S21: =IFERROR('(Z+) OpEx'!J34,0) -> -197148.41 | T21: =IFERROR(S21/$B$10,0) -> -880.12685 | V21: Rent Growth | W21: 0.025
A22: Constr. LTC | B22: =70/100 -> 0.7 | C22: 0.16370944 | D22: 0.15934016 | E22: 0.15538478 | F22: 0.15176193 | G22: 0.14847781 | I22: Hold Period | J22: =IFERROR(84,0) -> 84 | K22: 0.17922924 | L22: 0.16730761 | M22: 0.15538478 | N22: 0.14340383 | O22: 0.13130299 | Q22: Effective Gross Income | R22: =IFERROR(SUM(R20:R21),0) -> 2438.2757 | S22: =IFERROR(SUM(S20:S21),0) -> 6554085.2 | T22: =IFERROR(S22/$B$10,0) -> 29259.309
B23: =IFERROR(B22-5%,0) -> 0.65 | C23: 0.15911227 | D23: 0.15544184 | E23: 0.15205938 | F23: 0.14896865 | G23: 0.14618538 | J23: =IFERROR(J22+12,0) -> 96 | K23: 0.17784042 | L23: 0.16830321 | M23: 0.15880408 | N23: 0.1493039 | O23: 0.13976169 | Q23: Operating Expenses | R23: =IFERROR('(Z+) OpEx'!J36/B10/12,0) -> -642.84165 | S23: =IFERROR('(Z+) OpEx'!J36,0) -> -1727958.3 | T23: =IFERROR(S23/$B$10,0) -> -7714.0998
B24: =IFERROR(B23-5%,0) -> 0.6 | C24: 0.15504945 | D24: 0.1519296 | E24: 0.14910477 | F24: 0.14651422 | G24: 0.14416016 | J24: =IFERROR(J23+12,0) -> 108 | K24: 0.17697797 | L24: 0.1692821 | M24: 0.16165414 | N24: 0.154067 | O24: 0.14649333 | Q24: Property Tax Exemption | R24: Yes | S24: =IFERROR(0,0) -> 0 | T24: =IFERROR(S24/B10,0) -> 0
Q25: NOI | R25: =IFERROR(SUM(R22:R23),0) -> 1795.4341 | S25: =R25*12*$B$10 -> 4826126.8 | T25: =IFERROR(S25/$B$10,0) -> 21545.209
A26: IRR% - Constr. Timeline vs On-Site Cost | I26: IRR % - Hold Period vs Perm. Interest Rate
A27: IRR% | E27: On-site Cost $/unit | I27: IRR% | M27: Perm Int. Rate
B28: ='(Z+) Monthly CF'!F103 -> 0.15538478 | C28: =IFERROR(E28-20000,0) -> 70000 | D28: =IFERROR(E28-10000,0) -> 80000 | E28: =IFERROR(90000,0) -> 90000 | F28: =IFERROR(E28+10000,0) -> 100000 | G28: =IFERROR(F28+10000,0) -> 110000 | J28: ='(Z+) Monthly CF'!F103 -> 0.15538478 | K28: =IFERROR(L28-0.25%,0) -> 0.0525 | L28: =IFERROR(M28-0.25%,0) -> 0.055 | M28: =IFERROR(5.75/100,0) -> 0.0575 | N28: =IFERROR(M28+0.25%,0) -> 0.06 | O28: =IFERROR(N28+0.25%,0) -> 0.0625
B29: =IFERROR(B31-4,0) -> 7 | C29: 0.23031353 | D29: 0.2048513 | E29: 0.17895251 | F29: 0.15224361 | G29: 0.12424155 | J29: =IFERROR(J30-12,0) -> 60 | K29: 0.15257681 | L29: 0.14940372 | M29: 0.14619973 | N29: 0.14296493 | O29: 0.13969936
B30: =IFERROR(B31-2,0) -> 9 | C30: 0.21621862 | D30: 0.19159481 | E30: 0.16655741 | F30: 0.14070632 | G30: 0.11352964 | J30: =IFERROR(J31-12,0) -> 72 | K30: 0.15860149 | L30: 0.15495571 | M30: 0.15126211 | N30: 0.14752056 | O30: 0.14373096
A31: Construction Timeline | B31: =IFERROR(11,0) -> 11 | C31: 0.20355343 | D31: 0.17966238 | E31: 0.15538446 | F31: 0.13024003 | G31: 0.10380639 | I31: Hold Period | J31: =IFERROR(84,0) -> 84 | K31: 0.1633119 | L31: 0.15937983 | M31: 0.15538478 | N31: 0.15132635 | O31: 0.14720411
B32: =IFERROR(B31+2,0) -> 13 | C32: 0.19208373 | D32: 0.1688492 | E32: 0.14517463 | F32: 0.12065169 | G32: 0.094870414 | J32: =IFERROR(J31+12,0) -> 96 | K32: 0.16707755 | L32: 0.16297862 | M32: 0.15880408 | N32: 0.15455317 | O32: 0.1502251
B33: =IFERROR(B32+2,0) -> 15 | C33: 0.18148727 | D33: 0.15882171 | E33: 0.13568382 | F33: 0.11171451 | G33: 0.085550992 | J33: =IFERROR(J32+12,0) -> 108 | K33: 0.17011494 | L33: 0.16592736 | M33: 0.16165414 | N33: 0.15729421 | O33: 0.15284641
A35: IRR% - Rent Growth vs Exit Cap | I35: IRR % - Hold Period vs Constr. Interest Rate
A36: IRR% | E36: Exit Cap | I36: IRR% | M36: Contstruction Int. Rate
B37: ='(Z+) Monthly CF'!F103 -> 0.15538478 | C37: =IFERROR(D37-0.0025,0) -> 0.0625 | D37: =IFERROR(E37-0.0025,0) -> 0.065 | E37: =IFERROR(6.75/100,0) -> 0.0675 | F37: =IFERROR(E37+0.0025,0) -> 0.07 | G37: =IFERROR(F37+0.0025,0) -> 0.0725 | J37: ='(Z+) Monthly CF'!F103 -> 0.15538478 | K37: =IFERROR(L37-0.25%,0) -> 0.085 | L37: =IFERROR(M37-0.25%,0) -> 0.0875 | M37: =IFERROR(9/100,0) -> 0.09 | N37: =IFERROR(M37+0.25%,0) -> 0.0925 | O37: =IFERROR(N37+0.25%,0) -> 0.095
B38: =IFERROR(B39+0.01,0) -> 0.045 | C38: 0.20007318 | D38: 0.1892186 | E38: 0.17844735 | F38: 0.16771751 | G38: 0.15698611 | J38: =IFERROR(J39-12,0) -> 60 | K38: 0.14893566 | L38: 0.14755359 | M38: 0.14619973 | N38: 0.1448719 | O38: 0.14357423
B39: =IFERROR(B40+0.01,0) -> 0.035 | C39: 0.18957965 | D39: 0.17820111 | E39: 0.16686664 | F39: 0.15552765 | G39: 0.14413291 | J39: =IFERROR(J40-12,0) -> 72 | K39: 0.1535418 | L39: 0.15239009 | M39: 0.15126211 | N39: 0.15015522 | O39: 0.14907457
A40: Rent Growth Post-Occ | B40: =IFERROR(2.5/100,0) -> 0.025 | C40: 0.17922924 | D40: 0.16730761 | E40: 0.15538478 | F40: 0.14340383 | G40: 0.13130299 | I40: Hold Period | J40: =IFERROR(84,0) -> 84 | K40: 0.15731899 | L40: 0.15634142 | M40: 0.15538478 | N40: 0.15444615 | O40: 0.15353143
B41: =IFERROR(B40-0.01,0) -> 0.015 | C41: 0.16902912 | D41: 0.15654564 | E41: 0.14400926 | F41: 0.1313527 | G41: 0.11850087 | J41: =IFERROR(J40+12,0) -> 96 | K41: 0.16047235 | L41: 0.15962865 | M41: 0.15880408 | N41: 0.15799542 | O41: 0.15720915
B42: =IFERROR(B40-0.02,0) -> 0.005 | C42: 0.15898654 | D42: 0.14592304 | E42: 0.13274801 | F42: 0.11938151 | G42: 0.10573165 | J42: =IFERROR(J41+12,0) -> 108 | K42: 0.16311449 | L42: 0.16237538 | M42: 0.16165414 | N42: 0.16094735 | O42: 0.1602619

Sheet (Z+) Dev Budget
C3: Development Budget
C5: Category | E5: Factor | F5: Unit | G5: Budget | H5: $/GSF | I5: $/NRSF | J5: $/LSF | K5: $/Unit | L5: % of Tot.
C6: Acquisition Costs
C7: Land Cost | G7: 1600000 | H7: =IFERROR(G7/Inputs!$D$16,0) -> 117.79864 | I7: =IFERROR(G7/Inputs!$D$17,0) -> 15.776603 | J7: =IFERROR(G7/Inputs!$D$13,0) -> 54.270402 | K7: =IFERROR(G7/Inputs!$H$14,0) -> 7142.8571 | L7: =IFERROR(G7/$G$127,0) -> 0
C8: Escrow/Closing | E8: =IFERROR(0.1/100,0) -> 0.001 | G8: =IFERROR(G7*E8,0) -> 1600 | H8: =IFERROR(G8/Inputs!$D$16,0) -> 0.11779864 | I8: =IFERROR(G8/Inputs!$D$17,0) -> 0.015776603 | J8: =IFERROR(G8/Inputs!$D$13,0) -> 0.054270402 | K8: =IFERROR(G8/Inputs!$H$14,0) -> 7.1428571 | L8: =IFERROR(G8/$G$126,0) -> 2.6587963e-05
C9: Acquisition Fee | E9: =IFERROR(0/100,0) -> 0 | G9: =IFERROR(0,0) -> 0 | H9: =IFERROR(G9/Inputs!$D$16,0) -> 0 | I9: =IFERROR(G9/Inputs!$D$17,0) -> 0 | J9: =IFERROR(G9/Inputs!$D$13,0) -> 0 | K9: =IFERROR(G9/Inputs!H14,0) -> 0 | L9: =IFERROR(G9/$G$126,0) -> 0
C10: Total Acquisition Costs | E10: =IFERROR(0,0) -> 0 | G10: =IFERROR(SUM(G7:G9),0) -> 1601600 | H10: =IFERROR(G10/Inputs!$D$16,0) -> 117.91644 | I10: =IFERROR(G10/Inputs!$D$17,0) -> 15.79238 | J10: =IFERROR(G10/Inputs!$D$13,0) -> 54.324673 | K10: =IFERROR(G10/Inputs!H14,0) -> 7150 | L10: =IFERROR(G10/$G$127,0) -> 0
C12: Hard Costs
C13: Module Costs
C14: 1-BED 1-BA (420 SF) | E14: =IFERROR(90000,0) -> 90000 | F14: DU | G14: =IFERROR(IFERROR(E14*Inputs!O11,0),0) -> 20160000 | H14: =IFERROR(G14/Inputs!$D$16,0) -> 1484.2628 | I14: =IFERROR(G14/Inputs!$D$17,0) -> 198.7852 | J14: =IFERROR(G14/Inputs!$D$13,0) -> 683.80707 | K14: =IFERROR(G14/Inputs!$H$14,0) -> 90000 | L14: =IFERROR(G14/$G$127,0) -> 0
C15: 2-BED 1-BA (840 SF) | E15: =IFERROR(160000,0) -> 160000 | F15: DU | G15: =IFERROR(E15*Inputs!O12, 0) -> 0 | L15: =IFERROR(G15/$G$126,0) -> 0
C16: 3-BED 2-BA (840 SF) | E16: =IFERROR(180000,0) -> 180000 | F16: DU | G16: =IFERROR(E16*Inputs!O13,0) -> 0 | L16: =IFERROR(G16/$G$126,0) -> 0
C17: Service Mods | E17: =IFERROR(75000,0) -> 75000 | F17: DU | G17: =IFERROR(E17*SUM(Inputs!O16:O20),0) -> 0 | H17: =IFERROR(G17/Inputs!$D$16,0) -> 0 | I17: =IFERROR(G17/Inputs!$D$17,0) -> 0 | J17: =IFERROR(G17/Inputs!$D$13,0) -> 0 | K17: =IFERROR(G17/Inputs!$H$14,0) -> 0 | L17: =IFERROR(G17/$G$126,0) -> 0
C18: Staircases | E18: =IFERROR(15000,0) -> 15000 | F18: DU | G18: =IFERROR(E18*Inputs!O15,0) -> 255000 | H18: =IFERROR(G18/Inputs!$D$16,0) -> 18.774158 | I18: =IFERROR(G18/Inputs!$D$17,0) -> 2.5143962 | J18: =IFERROR(G18/Inputs!$D$13,0) -> 8.6493454 | K18: =IFERROR(G18/Inputs!$H$14,0) -> 1138.3929 | L18: =IFERROR(G18/$G$126,0) -> 0.0042374565
C19: Onsite Costs | E19: =IFERROR(Dashboard!W18,0) -> 90000 | F19: DU | G19: =IFERROR(E19*Inputs!H14,0) -> 20160000 | H19: =IFERROR(G19/Inputs!$D$16,0) -> 1484.2628 | I19: =IFERROR(G19/Inputs!$D$17,0) -> 198.7852 | J19: =IFERROR(G19/Inputs!$D$13,0) -> 683.80707 | K19: =IFERROR(G19/Inputs!$H$14,0) -> 90000 | L19: =IFERROR(G19/$G$126,0) -> 0.33500833
C20: Podium Cost | E20: =IFERROR(105,0) -> 105 | F20: Footprint SF | G20: =IFERROR(Inputs!O8*E20*Inputs!O7,0) -> 1500345 | H20: =IFERROR(G20/Inputs!$D$16,0) -> 110.46162 | I20: =IFERROR(G20/Inputs!$D$17,0) -> 14.793967 | J20: =IFERROR(G20/Inputs!$D$13,0) -> 50.890204 | K20: =IFERROR(G20/Inputs!$H$14,0) -> 6697.9688 | L20: =IFERROR(G20/$G$126,0) -> 0.024931948
C21: Transport & Insurance | E21: =IFERROR(1500,0) -> 1500 | F21: DU | G21: =IFERROR(Inputs!H14*E21,0) -> 336000 | H21: =IFERROR(G21/Inputs!$D$16,0) -> 24.737714 | I21: =IFERROR(G21/Inputs!$D$17,0) -> 3.3130867 | J21: =IFERROR(G21/Inputs!$D$13,0) -> 11.396784 | K21: =IFERROR(G21/Inputs!$H$14,0) -> 1500 | L21: =IFERROR(G21/$G$126,0) -> 0.0055834721
C22: Cost Escalation Allowance | E22: =IFERROR((1+Inputs!L9)^(Inputs!E23/12)-1,0) -> 0.019803903 | F22: GC Contr | G22: =IFERROR(+E22*SUM(G19,G20),0) -> 428959.37 | H22: =IFERROR(G22/Inputs!$D$16,0) -> 31.581768 | I22: =IFERROR(G22/Inputs!$D$17,0) -> 4.2297011 | J22: =IFERROR(G22/Inputs!$D$13,0) -> 14.549873 | K22: =IFERROR(G22/Inputs!$H$14,0) -> 1914.9972 | L22: =IFERROR(G22/$G$126,0) -> 0.0071282222
C23: Subtotal - GC Contract Prelim | E23: =IFERROR(0,0) -> 0 | G23: =IFERROR(+SUM(G14:G22),0) -> 42840304 | H23: =IFERROR(G23/Inputs!$D$16,0) -> 3154.0809 | I23: =IFERROR(G23/Inputs!$D$17,0) -> 422.42155 | J23: =IFERROR(G23/Inputs!$D$13,0) -> 1453.1003 | K23: =IFERROR(G23/Inputs!$H$14,0) -> 191251.36 | L23: =IFERROR(G23/$G$126,0) -> 0.71189776
C24: Enviro Contingency | E24: =IFERROR(0,0) -> 0 | F24: DU | G24: =IFERROR(0,0) -> 0 | H24: =IFERROR(G24/Inputs!$D$16,0) -> 0 | I24: =IFERROR(G24/Inputs!$D$17,0) -> 0 | J24: =IFERROR(G24/Inputs!$D$13,0) -> 0 | K24: =IFERROR(G24/Inputs!$H$14,0) -> 0 | L24: =IFERROR(G24/$G$126,0) -> 0
C25: Owner's Construction Security | E25: =IFERROR(1600,0) -> 1600 | F25: Constr Mo | G25: =IFERROR(E25*Inputs!E26,0) -> 17600 | H25: =IFERROR(G25/Inputs!$D$16,0) -> 1.295785 | I25: =IFERROR(G25/Inputs!$D$17,0) -> 0.17354264 | J25: =IFERROR(G25/Inputs!$D$13,0) -> 0.59697443 | K25: =IFERROR(G25/Inputs!$H$14,0) -> 78.571429 | L25: =IFERROR(G25/$G$126,0) -> 0.00029246759
C26: Quality Control Peer (Inspections) | E26: =IFERROR(0,0) -> 0 | F26: DU | G26: =IFERROR(E26*Inputs!H14,0) -> 0 | H26: =IFERROR(G26/Inputs!$D$16,0) -> 0 | I26: =IFERROR(G26/Inputs!$D$17,0) -> 0 | J26: =IFERROR(G26/Inputs!$D$13,0) -> 0 | K26: =IFERROR(G26/Inputs!$H$14,0) -> 0 | L26: =IFERROR(G26/$G$126,0) -> 0
C27: Commercial / Tenant Improvements | E27: =IFERROR(0,0) -> 0 | F27: Comm NRSF | G27: =IFERROR(E27*Inputs!D17,0) -> 0 | H27: =IFERROR(G27/Inputs!$D$16,0) -> 0 | I27: =IFERROR(G27/Inputs!$D$17,0) -> 0 | J27: =IFERROR(G27/Inputs!$D$13,0) -> 0 | K27: =IFERROR(G27/Inputs!$H$14,0) -> 0 | L27: =IFERROR(G27/$G$126,0) -> 0
C28: Demolition | E28: =IFERROR(3,0) -> 3 | F28: Land SF | G28: =IFERROR(E28*Inputs!D13,0) -> 88446 | H28: =IFERROR(G28/Inputs!$D$16,0) -> 6.5117615 | I28: =IFERROR(G28/Inputs!$D$17,0) -> 0.87211091 | J28: =IFERROR(G28/Inputs!$D$13,0) -> 3 | K28: =IFERROR(G28/Inputs!$H$14,0) -> 394.84821 | L28: =IFERROR(G28/$G$126,0) -> 0.0014697493
C29: Owner's Contingency | E29: =IFERROR(5/100,0) -> 0.05 | G29: =IFERROR(+SUM(G23-G14-G22,G28)*E29,0) -> 1116989.6 | H29: =IFERROR(G29/Inputs!$D$16,0) -> 82.237405 | I29: =IFERROR(G29/Inputs!$D$17,0) -> 11.013938 | J29: =IFERROR(G29/Inputs!$D$13,0) -> 37.88717 | K29: =IFERROR(G29/Inputs!$H$14,0) -> 4986.5605 | L29: =IFERROR(G29/$G$126,0) -> 0.018561548
C30: Total Hard Costs | E30: =IFERROR(0,0) -> 0 | G30: =IFERROR(+SUM(G23:G29),0) -> 44063340 | H30: =IFERROR(G30/Inputs!$D$16,0) -> 3244.1259 | I30: =IFERROR(G30/Inputs!$D$17,0) -> 434.48115 | J30: =IFERROR(G30/Inputs!$D$13,0) -> 1494.5845 | K30: =IFERROR(G30/Inputs!$H$14,0) -> 196711.34 | L30: =IFERROR(G30/$G$126,0) -> 0.73222152
C32: Soft Costs
C33: Environmental - Phase I Report | E33: =IFERROR(0,0) -> 0 | G33: =IFERROR(2500,0) -> 2500 | H33: =IFERROR(G33/Inputs!$D$16,0) -> 0.18406037 | I33: =IFERROR(G33/Inputs!$D$17,0) -> 0.024650943 | J33: =IFERROR(G33/Inputs!$D$13,0) -> 0.084797504 | K33: =IFERROR(G33/Inputs!$H$14,0) -> 11.160714 | L33: =IFERROR(G33/$G$126,0) -> 4.1543691e-05
C34: Environmental - Phase II Report | E34: =IFERROR(0,0) -> 0 | G34: =IFERROR(0,0) -> 0 | H34: =IFERROR(G34/Inputs!$D$16,0) -> 0 | I34: =IFERROR(G34/Inputs!$D$17,0) -> 0 | J34: =IFERROR(G34/Inputs!$D$13,0) -> 0 | K34: =IFERROR(G34/Inputs!$H$14,0) -> 0 | L34: =IFERROR(G34/$G$126,0) -> 0
C35: Geotech-Soils - Soils Investigation | E35: =IFERROR(0,0) -> 0 | G35: =IFERROR(6000,0) -> 6000 | H35: =IFERROR(G35/Inputs!$D$16,0) -> 0.44174489 | I35: =IFERROR(G35/Inputs!$D$17,0) -> 0.059162262 | J35: =IFERROR(G35/Inputs!$D$13,0) -> 0.20351401 | K35: =IFERROR(G35/Inputs!$H$14,0) -> 26.785714 | L35: =IFERROR(G35/$G$126,0) -> 9.970486e-05
C36: ALTA Survey | E36: =IFERROR(0,0) -> 0 | G36: =IFERROR(4000,0) -> 4000 | H36: =IFERROR(G36/Inputs!$D$16,0) -> 0.29449659 | I36: =IFERROR(G36/Inputs!$D$17,0) -> 0.039441508 | J36: =IFERROR(G36/Inputs!$D$13,0) -> 0.13567601 | K36: =IFERROR(G36/Inputs!$H$14,0) -> 17.857143 | L36: =IFERROR(G36/$G$126,0) -> 6.6469906e-05
C37: Soil Management Plan | E37: =IFERROR(0,0) -> 0 | G37: =IFERROR(0,0) -> 0 | H37: =IFERROR(G37/Inputs!$D$16,0) -> 0 | I37: =IFERROR(G37/Inputs!$D$17,0) -> 0 | J37: =IFERROR(G37/Inputs!$D$13,0) -> 0 | K37: =IFERROR(G37/Inputs!$H$14,0) -> 0 | L37: =IFERROR(G37/$G$126,0) -> 0
C38: Architectural - Pre-Conceptual/Massing | E38: =IFERROR(0,0) -> 0 | G38: =IFERROR(0,0) -> 0 | H38: =IFERROR(G38/Inputs!$D$16,0) -> 0 | I38: =IFERROR(G38/Inputs!$D$17,0) -> 0 | J38: =IFERROR(G38/Inputs!$D$13,0) -> 0 | K38: =IFERROR(G38/Inputs!$H$14,0) -> 0 | L38: =IFERROR(G38/$G$126,0) -> 0
C39: Construction Estimating/ROM | E39: =IFERROR(0,0) -> 0 | G39: =IFERROR(0,0) -> 0 | H39: =IFERROR(G39/Inputs!$D$16,0) -> 0 | I39: =IFERROR(G39/Inputs!$D$17,0) -> 0 | J39: =IFERROR(G39/Inputs!$D$13,0) -> 0 | K39: =IFERROR(G39/Inputs!$H$14,0) -> 0 | L39: =IFERROR(G39/$G$126,0) -> 0
C40: Dry/Wet Utility Study | E40: =IFERROR(0,0) -> 0 | G40: =IFERROR(2500,0) -> 2500 | H40: =IFERROR(G40/Inputs!$D$16,0) -> 0.18406037 | I40: =IFERROR(G40/Inputs!$D$17,0) -> 0.024650943 | J40: =IFERROR(G40/Inputs!$D$13,0) -> 0.084797504 | K40: =IFERROR(G40/Inputs!$H$14,0) -> 11.160714 | L40: =IFERROR(G40/$G$126,0) -> 4.1543691e-05
C41: Fee Study | E41: =IFERROR(0,0) -> 0 | G41: =IFERROR(0,0) -> 0 | H41: =IFERROR(G41/Inputs!$D$16,0) -> 0 | I41: =IFERROR(G41/Inputs!$D$17,0) -> 0 | J41: =IFERROR(G41/Inputs!$D$13,0) -> 0 | K41: =IFERROR(G41/Inputs!$H$14,0) -> 0 | L41: =IFERROR(G41/$G$126,0) -> 0
C42: Entitlement Consultant - Land Use Report | E42: =IFERROR(0,0) -> 0 | G42: =IFERROR(0,0) -> 0 | H42: =IFERROR(G42/Inputs!$D$16,0) -> 0 | I42: =IFERROR(G42/Inputs!$D$17,0) -> 0 | J42: =IFERROR(G42/Inputs!$D$13,0) -> 0 | K42: =IFERROR(G42/Inputs!$H$14,0) -> 0 | L42: =IFERROR(G42/$G$126,0) -> 0
C43: Historical | E43: =IFERROR(0,0) -> 0 | G43: =IFERROR(0,0) -> 0 | H43: =IFERROR(G43/Inputs!$D$16,0) -> 0 | I43: =IFERROR(G43/Inputs!$D$17,0) -> 0 | J43: =IFERROR(G43/Inputs!$D$13,0) -> 0 | K43: =IFERROR(G43/Inputs!$H$14,0) -> 0 | L43: =IFERROR(G43/$G$126,0) -> 0
C44: Appraisal | E44: =IFERROR(0,0) -> 0 | G44: =IFERROR(0,0) -> 0 | H44: =IFERROR(G44/Inputs!$D$16,0) -> 0 | I44: =IFERROR(G44/Inputs!$D$17,0) -> 0 | J44: =IFERROR(G44/Inputs!$D$13,0) -> 0 | K44: =IFERROR(G44/Inputs!$H$14,0) -> 0 | L44: =IFERROR(G44/$G$126,0) -> 0
C45: Lead & Asbestos - Report | E45: =IFERROR(0,0) -> 0 | G45: =IFERROR(0,0) -> 0 | H45: =IFERROR(G45/Inputs!$D$16,0) -> 0 | I45: =IFERROR(G45/Inputs!$D$17,0) -> 0 | J45: =IFERROR(G45/Inputs!$D$13,0) -> 0 | K45: =IFERROR(G45/Inputs!$H$14,0) -> 0 | L45: =IFERROR(G45/$G$126,0) -> 0
C46: Subtotal - Due Diligence | E46: =IFERROR(0,0) -> 0 | G46: =IFERROR(+SUM(G33:G45),0) -> 15000 | H46: =IFERROR(G46/Inputs!$D$16,0) -> 1.1043622 | I46: =IFERROR(G46/Inputs!$D$17,0) -> 0.14790566 | J46: =IFERROR(G46/Inputs!$D$13,0) -> 0.50878502 | K46: =IFERROR(G46/Inputs!$H$14,0) -> 66.964286 | L46: =IFERROR(G46/$G$126,0) -> 0.00024926215
C47: Consulting - Architectural | E47: =IFERROR(3000,0) -> 3000 | F47: DU | G47: =IFERROR(E47*Inputs!$H$14,0) -> 672000 | H47: =IFERROR(G47/Inputs!$D$16,0) -> 49.475428 | I47: =IFERROR(G47/Inputs!$D$17,0) -> 6.6261734 | J47: =IFERROR(G47/Inputs!$D$13,0) -> 22.793569 | K47: =IFERROR(G47/Inputs!$H$14,0) -> 3000 | L47: =IFERROR(G47/$G$126,0) -> 0.011166944
C48: Consulting - Structural | E48: =IFERROR(1000,0) -> 1000 | F48: DU | G48: =IFERROR(E48*Inputs!$H$14,0) -> 224000 | H48: =IFERROR(G48/Inputs!$D$16,0) -> 16.491809 | I48: =IFERROR(G48/Inputs!$D$17,0) -> 2.2087245 | J48: =IFERROR(G48/Inputs!$D$13,0) -> 7.5978563 | K48: =IFERROR(G48/Inputs!$H$14,0) -> 1000 | L48: =IFERROR(G48/$G$126,0) -> 0.0037223148
C49: Consulting - MEP | E49: =IFERROR(800,0) -> 800 | F49: DU | G49: =IFERROR(E49*Inputs!$H$14,0) -> 179200 | H49: =IFERROR(G49/Inputs!$D$16,0) -> 13.193447 | I49: =IFERROR(G49/Inputs!$D$17,0) -> 1.7669796 | J49: =IFERROR(G49/Inputs!$D$13,0) -> 6.0782851 | K49: =IFERROR(G49/Inputs!$H$14,0) -> 800 | L49: =IFERROR(G49/$G$126,0) -> 0.0029778518
C50: Consulting - Civil | E50: =IFERROR(400,0) -> 400 | F50: DU | G50: =IFERROR(E50*Inputs!$H$14,0) -> 89600 | H50: =IFERROR(G50/Inputs!$D$16,0) -> 6.5967237 | I50: =IFERROR(G50/Inputs!$D$17,0) -> 0.88348978 | J50: =IFERROR(G50/Inputs!$D$13,0) -> 3.0391425 | K50: =IFERROR(G50/Inputs!$H$14,0) -> 400 | L50: =IFERROR(G50/$G$126,0) -> 0.0014889259
C51: Consulting - Landscaping | E51: =IFERROR(80,0) -> 80 | F51: DU | G51: =IFERROR(E51*Inputs!$H$14,0) -> 17920 | H51: =IFERROR(G51/Inputs!$D$16,0) -> 1.3193447 | I51: =IFERROR(G51/Inputs!$D$17,0) -> 0.17669796 | J51: =IFERROR(G51/Inputs!$D$13,0) -> 0.60782851 | K51: =IFERROR(G51/Inputs!$H$14,0) -> 80 | L51: =IFERROR(G51/$G$126,0) -> 0.00029778518
C52: Consulting - Disabled Access | G52: =IFERROR(E52*Inputs!$H$14,0) -> 0 | H52: =IFERROR(G52/Inputs!$D$16,0) -> 0 | I52: =IFERROR(G52/Inputs!$D$17,0) -> 0 | J52: =IFERROR(G52/Inputs!$D$13,0) -> 0 | K52: =IFERROR(G52/Inputs!$H$14,0) -> 0 | L52: =IFERROR(G52/$G$126,0) -> 0
C53: Consulting - Wet & Dry Utilities | E53: =IFERROR(600,0) -> 600 | F53: DU | G53: =IFERROR(E53*Inputs!$H$14,0) -> 134400 | H53: =IFERROR(G53/Inputs!$D$16,0) -> 9.8950856 | I53: =IFERROR(G53/Inputs!$D$17,0) -> 1.3252347 | J53: =IFERROR(G53/Inputs!$D$13,0) -> 4.5587138 | K53: =IFERROR(G53/Inputs!$H$14,0) -> 600 | L53: =IFERROR(G53/$G$126,0) -> 0.0022333889
C54: Consulting - Acoustical | G54: =IFERROR(E54*Inputs!$H$14,0) -> 0 | H54: =IFERROR(G54/Inputs!$D$16,0) -> 0 | I54: =IFERROR(G54/Inputs!$D$17,0) -> 0 | J54: =IFERROR(G54/Inputs!$D$13,0) -> 0 | K54: =IFERROR(G54/Inputs!$H$14,0) -> 0 | L54: =IFERROR(G54/$G$126,0) -> 0
C55: Consulting - Surveying | E55: =IFERROR(40,0) -> 40 | F55: DU | G55: =IFERROR(E55*Inputs!$H$14,0) -> 8960 | H55: =IFERROR(G55/Inputs!$D$16,0) -> 0.65967237 | I55: =IFERROR(G55/Inputs!$D$17,0) -> 0.088348978 | J55: =IFERROR(G55/Inputs!$D$13,0) -> 0.30391425 | K55: =IFERROR(G55/Inputs!$H$14,0) -> 40 | L55: =IFERROR(G55/$G$126,0) -> 0.00014889259
C56: Consulting - External Building Maintenance | E56: =IFERROR(120,0) -> 120 | F56: DU | G56: =IFERROR(E56*Inputs!$H$14,0) -> 26880 | H56: =IFERROR(G56/Inputs!$D$16,0) -> 1.9790171 | I56: =IFERROR(G56/Inputs!$D$17,0) -> 0.26504694 | J56: =IFERROR(G56/Inputs!$D$13,0) -> 0.91174276 | K56: =IFERROR(G56/Inputs!$H$14,0) -> 120 | L56: =IFERROR(G56/$G$126,0) -> 0.00044667777
C57: Consulting - CEQA | G57: =IFERROR(E57*Inputs!$H$14,0) -> 0 | H57: =IFERROR(G57/Inputs!$D$16,0) -> 0 | I57: =IFERROR(G57/Inputs!$D$17,0) -> 0 | J57: =IFERROR(G57/Inputs!$D$13,0) -> 0 | K57: =IFERROR(G57/Inputs!$H$14,0) -> 0 | L57: =IFERROR(G57/$G$126,0) -> 0
C58: Consulting - Expeditor | G58: =IFERROR(E58*Inputs!$H$14,0) -> 0 | H58: =IFERROR(G58/Inputs!$D$16,0) -> 0 | I58: =IFERROR(G58/Inputs!$D$17,0) -> 0 | J58: =IFERROR(G58/Inputs!$D$13,0) -> 0 | K58: =IFERROR(G58/Inputs!$H$14,0) -> 0 | L58: =IFERROR(G58/$G$126,0) -> 0
C59: Consulting - Fire | G59: =IFERROR(E59*Inputs!$H$14,0) -> 0 | H59: =IFERROR(G59/Inputs!$D$16,0) -> 0 | I59: =IFERROR(G59/Inputs!$D$17,0) -> 0 | J59: =IFERROR(G59/Inputs!$D$13,0) -> 0 | K59: =IFERROR(G59/Inputs!$H$14,0) -> 0 | L59: =IFERROR(G59/$G$126,0) -> 0
C60: Consulting - Geotech-Soils | G60: =IFERROR(E60*Inputs!$H$14,0) -> 0 | H60: =IFERROR(G60/Inputs!$D$16,0) -> 0 | I60: =IFERROR(G60/Inputs!$D$17,0) -> 0 | J60: =IFERROR(G60/Inputs!$D$13,0) -> 0 | K60: =IFERROR(G60/Inputs!$H$14,0) -> 0 | L60: =IFERROR(G60/$G$126,0) -> 0
C61: Consulting - Interior Design | G61: =IFERROR(E61*Inputs!$H$14,0) -> 0 | H61: =IFERROR(G61/Inputs!$D$16,0) -> 0 | I61: =IFERROR(G61/Inputs!$D$17,0) -> 0 | J61: =IFERROR(G61/Inputs!$D$13,0) -> 0 | K61: =IFERROR(G61/Inputs!$H$14,0) -> 0 | L61: =IFERROR(G61/$G$126,0) -> 0
C62: Consulting - IT (Low voltage) | E62: =IFERROR(170,0) -> 170 | F62: DU | G62: =+IFERROR(E62*Inputs!$H$14,0) -> 38080 | H62: =IFERROR(G62/Inputs!$D$16,0) -> 2.8036076 | I62: =IFERROR(G62/Inputs!$D$17,0) -> 0.37548316 | J62: =IFERROR(G62/Inputs!$D$13,0) -> 1.2916356 | K62: =IFERROR(G62/Inputs!$H$14,0) -> 170 | L62: =IFERROR(G62/$G$126,0) -> 0.00063279351
C63: Consulting - Land Use | G63: =IFERROR(E63*Inputs!$H$14,0) -> 0 | H63: =IFERROR(G63/Inputs!$D$16,0) -> 0 | I63: =IFERROR(G63/Inputs!$D$17,0) -> 0 | J63: =IFERROR(G63/Inputs!$D$13,0) -> 0 | K63: =IFERROR(G63/Inputs!$H$14,0) -> 0 | L63: =IFERROR(G63/$G$126,0) -> 0
C64: Consulting - Lead & Asbestos | G64: =IFERROR(E64*Inputs!$H$14,0) -> 0 | H64: =IFERROR(G64/Inputs!$D$16,0) -> 0 | I64: =IFERROR(G64/Inputs!$D$17,0) -> 0 | J64: =IFERROR(G64/Inputs!$D$13,0) -> 0 | K64: =IFERROR(G64/Inputs!$H$14,0) -> 0 | L64: =IFERROR(G64/$G$126,0) -> 0
C65: Consulting - Legal | G65: =IFERROR(E65*Inputs!$H$14,0) -> 0 | H65: =IFERROR(G65/Inputs!$D$16,0) -> 0 | I65: =IFERROR(G65/Inputs!$D$17,0) -> 0 | J65: =IFERROR(G65/Inputs!$D$13,0) -> 0 | K65: =IFERROR(G65/Inputs!$H$14,0) -> 0 | L65: =IFERROR(G65/$G$126,0) -> 0
C66: Consulting - Lighting | E66: =IFERROR(25,0) -> 25 | F66: DU | G66: =IFERROR(E66*Inputs!$H$14,0) -> 5600 | H66: =IFERROR(G66/Inputs!$D$16,0) -> 0.41229523 | I66: =IFERROR(G66/Inputs!$D$17,0) -> 0.055218112 | J66: =IFERROR(G66/Inputs!$D$13,0) -> 0.18994641 | K66: =IFERROR(G66/Inputs!$H$14,0) -> 25 | L66: =IFERROR(G66/$G$126,0) -> 9.3057869e-05
C67: Consulting - Market Research | G67: =IFERROR(E67*Inputs!$H$14,0) -> 0 | H67: =IFERROR(G67/Inputs!$D$16,0) -> 0 | I67: =IFERROR(G67/Inputs!$D$17,0) -> 0 | J67: =IFERROR(G67/Inputs!$D$13,0) -> 0 | K67: =IFERROR(G67/Inputs!$H$14,0) -> 0 | L67: =IFERROR(G67/$G$126,0) -> 0
C68: Consulting - Marketing | G68: =IFERROR(E68*Inputs!$H$14,0) -> 0 | H68: =IFERROR(G68/Inputs!$D$16,0) -> 0 | I68: =IFERROR(G68/Inputs!$D$17,0) -> 0 | J68: =IFERROR(G68/Inputs!$D$13,0) -> 0 | K68: =IFERROR(G68/Inputs!$H$14,0) -> 0 | L68: =IFERROR(G68/$G$126,0) -> 0
C69: Consulting - Methane | G69: =IFERROR(E69*Inputs!$H$14,0) -> 0 | H69: =IFERROR(G69/Inputs!$D$16,0) -> 0 | I69: =IFERROR(G69/Inputs!$D$17,0) -> 0 | J69: =IFERROR(G69/Inputs!$D$13,0) -> 0 | K69: =IFERROR(G69/Inputs!$H$14,0) -> 0 | L69: =IFERROR(G69/$G$126,0) -> 0
C70: Consulting - Misc Engineering | G70: =IFERROR(E70*Inputs!$H$14,0) -> 0 | H70: =IFERROR(G70/Inputs!$D$16,0) -> 0 | I70: =IFERROR(G70/Inputs!$D$17,0) -> 0 | J70: =IFERROR(G70/Inputs!$D$13,0) -> 0 | K70: =IFERROR(G70/Inputs!$H$14,0) -> 0 | L70: =IFERROR(G70/$G$126,0) -> 0
C71: Consulting - GC Precon/Estimating | G71: =IFERROR(E71*Inputs!$H$14,0) -> 0 | H71: =IFERROR(G71/Inputs!$D$16,0) -> 0 | I71: =IFERROR(G71/Inputs!$D$17,0) -> 0 | J71: =IFERROR(G71/Inputs!$D$13,0) -> 0 | K71: =IFERROR(G71/Inputs!$H$14,0) -> 0 | L71: =IFERROR(G71/$G$126,0) -> 0
C72: Consulting - Photography-Video | G72: =IFERROR(E72*Inputs!$H$14,0) -> 0 | H72: =IFERROR(G72/Inputs!$D$16,0) -> 0 | I72: =IFERROR(G72/Inputs!$D$17,0) -> 0 | J72: =IFERROR(G72/Inputs!$D$13,0) -> 0 | K72: =IFERROR(G72/Inputs!$H$14,0) -> 0 | L72: =IFERROR(G72/$G$126,0) -> 0
C73: Consulting - Property Tax | G73: =IFERROR(E73*Inputs!$H$14,0) -> 0 | H73: =IFERROR(G73/Inputs!$D$16,0) -> 0 | I73: =IFERROR(G73/Inputs!$D$17,0) -> 0 | J73: =IFERROR(G73/Inputs!$D$13,0) -> 0 | K73: =IFERROR(G73/Inputs!$H$14,0) -> 0 | L73: =IFERROR(G73/$G$126,0) -> 0
C74: Consulting - Public Outreach | G74: =IFERROR(E74*Inputs!$H$14,0) -> 0 | H74: =IFERROR(G74/Inputs!$D$16,0) -> 0 | I74: =IFERROR(G74/Inputs!$D$17,0) -> 0 | J74: =IFERROR(G74/Inputs!$D$13,0) -> 0 | K74: =IFERROR(G74/Inputs!$H$14,0) -> 0 | L74: =IFERROR(G74/$G$126,0) -> 0
C75: Consulting - Quality Control Peer (Inspections) | G75: =IFERROR(E75*Inputs!$H$14,0) -> 0 | H75: =IFERROR(G75/Inputs!$D$16,0) -> 0 | I75: =IFERROR(G75/Inputs!$D$17,0) -> 0 | J75: =IFERROR(G75/Inputs!$D$130,0) -> 0 | K75: =IFERROR(G75/Inputs!$H$14,0) -> 0 | L75: =IFERROR(G75/$G$126,0) -> 0
C76: Consulting - Traffic Studies | G76: =IFERROR(E76*Inputs!$H$14,0) -> 0 | H76: =IFERROR(G76/Inputs!$D$16,0) -> 0 | I76: =IFERROR(G76/Inputs!$D$17,0) -> 0 | J76: =IFERROR(G76/Inputs!$D$13,0) -> 0 | K76: =IFERROR(G76/Inputs!$H$14,0) -> 0 | L76: =IFERROR(G76/$G$126,0) -> 0
C77: Consulting - Water Proofing | E77: =IFERROR(115,0) -> 115 | F77: DU | G77: =IFERROR(E77*Inputs!$H$14,0) -> 25760 | H77: =IFERROR(G77/Inputs!$D$16,0) -> 1.8965581 | I77: =IFERROR(G77/Inputs!$D$17,0) -> 0.25400331 | J77: =IFERROR(G77/Inputs!$D$13,0) -> 0.87375348 | K77: =IFERROR(G77/Inputs!$H$14,0) -> 115 | L77: =IFERROR(G77/$G$126,0) -> 0.0004280662
C78: Consulting - Reimbursables | E78: =IFERROR(95,0) -> 95 | F78: DU | G78: =IFERROR(E78*Inputs!$H$14,0) -> 21280 | H78: =IFERROR(G78/Inputs!$D$16,0) -> 1.5667219 | I78: =IFERROR(G78/Inputs!$D$17,0) -> 0.20982882 | J78: =IFERROR(G78/Inputs!$D$13,0) -> 0.72179635 | K78: =IFERROR(G78/Inputs!$H$14,0) -> 95 | L78: =IFERROR(G78/$G$126,0) -> 0.0003536199
C79: Other Consultant (Consulting - Misc) | D79: =IFERROR(5,0) -> 5 | E79: =IFERROR(0,0) -> 0 | F79: DU | G79: =IFERROR(E79*Inputs!$H$14,0) -> 0 | H79: =IFERROR(G79/Inputs!$D$16,0) -> 0 | I79: =IFERROR(G79/Inputs!$D$17,0) -> 0 | J79: =IFERROR(G79/Inputs!$D$13,0) -> 0 | K79: =IFERROR(G79/Inputs!$H$14,0) -> 0 | L79: =IFERROR(G79/$G$127,0) -> 0
C80: Subtotal - Consultants | D80: =IFERROR(5,0) -> 5 | E80: =IFERROR(0,0) -> 0 | G80: =IFERROR(SUM(G47:G79),0) -> 1443680 | H80: =IFERROR(G80/Inputs!$D$16,0) -> 106.28971 | I80: =IFERROR(G80/Inputs!$D$17,0) -> 14.235229 | J80: =IFERROR(SUM(J47:J79),0) -> 48.968184 | K80: =IFERROR(SUM(K47:K79),0) -> 6445 | L80: =IFERROR(G80/$G$126,0) -> 0.023990319
C81: Fees - Plan Check, Demo, Building Permits | E81: =IFERROR(5000,0) -> 5000 | F81: DU | G81: =IFERROR(E81*Inputs!H14,0) -> 1120000 | H81: =IFERROR(G81/Inputs!$D$16,0) -> 82.459047 | I81: =IFERROR(G81/Inputs!$D$17,0) -> 11.043622 | J81: =IFERROR(G81/Inputs!$D$13,0) -> 37.989282 | K81: =IFERROR(G81/Inputs!$H$14,0) -> 5000 | L81: =IFERROR(G81/$G$126,0) -> 0.018611574
C82: Fees - Municipal Agency Engineering | E82: =IFERROR(2000,0) -> 2000 | F82: DU | G82: =IFERROR(E82*Inputs!H14,0) -> 448000 | H82: =IFERROR(G82/Inputs!$D$16,0) -> 32.983619 | I82: =IFERROR(G82/Inputs!$D$17,0) -> 4.4174489 | J82: =IFERROR(G82/Inputs!$D$13,0) -> 15.195713 | K82: =IFERROR(G82/Inputs!$H$14,0) -> 2000 | L82: =IFERROR(G82/$G$126,0) -> 0.0074446295
C83: Fees - School | E83: =IFERROR(0,0) -> 0 | G83: =IFERROR(0,0) -> 0 | H83: =IFERROR(G83/Inputs!$D$16,0) -> 0 | I83: =IFERROR(G83/Inputs!$D$17,0) -> 0 | J83: =IFERROR(G83/Inputs!$D$13,0) -> 0 | K83: =IFERROR(G83/Inputs!$H$14,0) -> 0 | L83: =IFERROR(G83/$G$126,0) -> 0
C84: Fees - Planning & Entitlements | E84: =IFERROR(0,0) -> 0 | G84: =IFERROR(30000,0) -> 30000 | H84: =IFERROR(G84/Inputs!$D$16,0) -> 2.2087245 | I84: =IFERROR(G84/Inputs!$D$17,0) -> 0.29581131 | J84: =IFERROR(G84/Inputs!$D$13,0) -> 1.01757 | K84: =IFERROR(G84/Inputs!$H$14,0) -> 133.92857 | L84: =IFERROR(G84/$G$126,0) -> 0.0004985243
C85: Fees - Housing | E85: =IFERROR(0,0) -> 0 | G85: =IFERROR(7500,0) -> 7500 | H85: =IFERROR(G85/Inputs!$D$16,0) -> 0.55218112 | I85: =IFERROR(G85/Inputs!$D$17,0) -> 0.073952828 | J85: =IFERROR(G85/Inputs!$D$13,0) -> 0.25439251 | K85: =IFERROR(G85/Inputs!$H$14,0) -> 33.482143 | L85: =IFERROR(G85/$G$126,0) -> 0.00012463107
C86: Fees - Misc | E86: =IFERROR(0,0) -> 0 | G86: =IFERROR(0,0) -> 0 | H86: =IFERROR(G86/Inputs!$D$16,0) -> 0 | I86: =IFERROR(G86/Inputs!$D$17,0) -> 0 | J86: =IFERROR(G86/Inputs!$D$13,0) -> 0 | K86: =IFERROR(G86/Inputs!$H$14,0) -> 0 | L86: =IFERROR(G86/$G$126,0) -> 0
C87: Fees - Water Meters | E87: =IFERROR(420,0) -> 420 | F87: DU | G87: =IFERROR(E87*Inputs!$H$14,0) -> 94080 | H87: =IFERROR(G87/Inputs!$D$16,0) -> 6.9265599 | I87: =IFERROR(G87/Inputs!$D$17,0) -> 0.92766427 | J87: =IFERROR(G87/Inputs!$D$13,0) -> 3.1910997 | K87: =IFERROR(G87/Inputs!$H$14,0) -> 420 | L87: =IFERROR(G87/$G$126,0) -> 0.0015633722
C88: Fees - Gas Meters | E88: =IFERROR(0,0) -> 0 | G88: =IFERROR(E88*Inputs!$H$14,0) -> 0 | H88: =IFERROR(G88/Inputs!$D$16,0) -> 0 | I88: =IFERROR(G88/Inputs!$D$17,0) -> 0 | J88: =IFERROR(G88/Inputs!$D$13,0) -> 0 | K88: =IFERROR(G88/Inputs!$H$14,0) -> 0 | L88: =IFERROR(G88/$G$126,0) -> 0
C89: Fees - Impact | E89: =IFERROR(0,0) -> 0 | G89: =IFERROR(0,0) -> 0 | H89: =IFERROR(G89/Inputs!$D$16,0) -> 0 | I89: =IFERROR(G89/Inputs!$D$17,0) -> 0 | J89: =IFERROR(G89/Inputs!$D$13,0) -> 0 | K89: =IFERROR(G89/Inputs!$H$14,0) -> 0 | L89: =IFERROR(G89/$G$126,0) -> 0
C90: Bond | E90: =IFERROR(0,0) -> 0 | G90: =IFERROR(10000,0) -> 10000 | H90: =IFERROR(G90/Inputs!$D$16,0) -> 0.73624149 | I90: =IFERROR(G90/Inputs!$D$17,0) -> 0.098603771 | J90: =IFERROR(G90/Inputs!$D$13,0) -> 0.33919001 | K90: =IFERROR(G90/Inputs!$H$14,0) -> 44.642857 | L90: =IFERROR(G90/$G$126,0) -> 0.00016617477
C91: Fees - Park | E91: =IFERROR(0,0) -> 0 | G91: =IFERROR(10000,0) -> 10000 | H91: =IFERROR(G91/Inputs!$D$16,0) -> 0.73624149 | I91: =IFERROR(G91/Inputs!$D$17,0) -> 0.098603771 | J91: =IFERROR(G91/Inputs!$D$13,0) -> 0.33919001 | K91: =IFERROR(G91/Inputs!$H$14,0) -> 44.642857 | L91: =IFERROR(G91/$G$126,0) -> 0.00016617477
C92: Subtotal - City Fees | E92: =IFERROR(0,0) -> 0 | G92: =IFERROR(SUM(G81:G91),0) -> 1719580 | H92: =IFERROR(G92/Inputs!$D$16,0) -> 126.60261 | I92: =IFERROR(G92/Inputs!$D$17,0) -> 16.955707 | J92: =IFERROR(SUM(J81:J91),0) -> 58.326436 | K92: =IFERROR(SUM(K81:K91),0) -> 7676.6964 | L92: =IFERROR(G92/$G$126,0) -> 0.02857508
C93: Relocation Expense | E93: =IFERROR(0,0) -> 0 | G93: =IFERROR(0,0) -> 0 | H93: =IFERROR(G93/Inputs!$D$16,0) -> 0 | I93: =IFERROR(G93/Inputs!$D$17,0) -> 0 | J93: =IFERROR(G93/Inputs!$D$13,0) -> 0 | K93: =IFERROR(G93/Inputs!$H$14,0) -> 0 | L93: =IFERROR(G93/$G$126,0) -> 0
C94: FF&E | E94: =IFERROR(0,0) -> 0 | G94: =IFERROR(100000,0) -> 100000 | H94: =IFERROR(G94/Inputs!$D$16,0) -> 7.3624149 | I94: =IFERROR(G94/Inputs!$D$17,0) -> 0.98603771 | J94: =IFERROR(G94/Inputs!$D$13,0) -> 3.3919001 | K94: =IFERROR(G94/Inputs!$H$14,0) -> 446.42857 | L94: =IFERROR(G94/$G$126,0) -> 0.0016617477
C95: Insurance | E95: =IFERROR(0,0) -> 0 | F95: GC Contr | G95: =IFERROR(150000,0) -> 150000 | H95: =IFERROR(G95/Inputs!$D$16,0) -> 11.043622 | I95: =IFERROR(G95/Inputs!$D$17,0) -> 1.4790566 | J95: =IFERROR(G95/Inputs!$D$130,0) -> 0 | K95: =IFERROR(G95/Inputs!$H$14,0) -> 669.64286 | L95: =IFERROR(G95/$G$126,0) -> 0.0024926215
C96: Leasing | E96: =IFERROR(0,0) -> 0 | F96: Mkt DU | G96: =IFERROR(0,0) -> 0 | H96: =IFERROR(G96/Inputs!$D$16,0) -> 0 | I96: =IFERROR(G96/Inputs!$D$17,0) -> 0 | J96: =IFERROR(G96/Inputs!$D$13,0) -> 0 | K96: =IFERROR(G96/Inputs!$H$14,0) -> 0 | L96: =IFERROR(G96/$G$126,0) -> 0
C97: Leasing Commission | E97: =IFERROR(0,0) -> 0 | F97: Mkt DU | G97: =IFERROR(E97*Inputs!H14,0) -> 0 | H97: =IFERROR(G97/Inputs!$D$16,0) -> 0 | I97: =IFERROR(G97/Inputs!$D$17,0) -> 0 | J97: =IFERROR(G97/Inputs!$D$13,0) -> 0 | K97: =IFERROR(G97/Inputs!$H$14,0) -> 0 | L97: =IFERROR(G97/$G$126,0) -> 0
C98: Model Unit | E98: =IFERROR(0,0) -> 0 | G98: =IFERROR(0,0) -> 0 | H98: =IFERROR(G98/Inputs!$D$16,0) -> 0 | I98: =IFERROR(G98/Inputs!$D$17,0) -> 0 | J98: =IFERROR(G98/Inputs!$D$13,0) -> 0 | K98: =IFERROR(G98/Inputs!$H$14,0) -> 0 | L98: =IFERROR(G98/$G$126,0) -> 0
C99: Rental Concession Reserve | E99: =IFERROR(0,0) -> 0 | G99: =IFERROR(0,0) -> 0 | H99: =IFERROR(G99/Inputs!$D$16,0) -> 0 | I99: =IFERROR(G99/Inputs!$D$17,0) -> 0 | J99: =IFERROR(G99/Inputs!$D$13,0) -> 0 | K99: =IFERROR(G99/Inputs!$H$14,0) -> 0 | L99: =IFERROR(G99/$G$126,0) -> 0
C100: CMFA/HOM Fees | E100: =IFERROR(0,0) -> 0 | G100: =IFERROR(10000,0) -> 10000 | H100: =IFERROR(G100/Inputs!$D$16,0) -> 0.73624149 | I100: =IFERROR(G100/Inputs!$D$17,0) -> 0.098603771 | J100: =IFERROR(G100/Inputs!$D$13,0) -> 0.33919001 | K100: =IFERROR(G100/Inputs!$H$14,0) -> 44.642857 | L100: =IFERROR(G100/$G$126,0) -> 0.00016617477
C101: Marketing | E101: =IFERROR(0,0) -> 0 | G101: =IFERROR(0,0) -> 0 | H101: =IFERROR(G101/Inputs!$D$16,0) -> 0 | I101: =IFERROR(G101/Inputs!$D$17,0) -> 0 | J101: =IFERROR(G101/Inputs!$D$13,0) -> 0 | K101: =IFERROR(G101/Inputs!$H$14,0) -> 0 | L101: =IFERROR(G101/$G$126,0) -> 0
C102: Operating Shortfall Reserve | E102: =IFERROR(0,0) -> 0 | G102: =IFERROR(0,0) -> 0 | H102: =IFERROR(G102/Inputs!$D$16,0) -> 0 | I102: =IFERROR(G102/Inputs!$D$17,0) -> 0 | J102: =IFERROR(G102/Inputs!$D$13,0) -> 0 | K102: =IFERROR(G102/Inputs!$H$14,0) -> 0 | L102: =IFERROR(G102/$G$126,0) -> 0
C103: Owner Reimbursables | E103: =IFERROR(0,0) -> 0 | G103: =IFERROR(0,0) -> 0 | H103: =IFERROR(G103/Inputs!$D$16,0) -> 0 | I103: =IFERROR(G103/Inputs!$D$17,0) -> 0 | J103: =IFERROR(G103/Inputs!$D$13,0) -> 0 | K103: =IFERROR(G103/Inputs!$H$14,0) -> 0 | L103: =IFERROR(G103/$G$126,0) -> 0
C104: Owner Printing | E104: =IFERROR(0,0) -> 0 | G104: =IFERROR(0,0) -> 0 | H104: =IFERROR(G104/Inputs!$D$16,0) -> 0 | I104: =IFERROR(G104/Inputs!$D$17,0) -> 0 | J104: =IFERROR(G104/Inputs!$D$13,0) -> 0 | K104: =IFERROR(G104/Inputs!$H$14,0) -> 0 | L104: =IFERROR(G104/$G$126,0) -> 0
C105: Temp Utilities | E105: =IFERROR(0,0) -> 0 | G105: =IFERROR(0,0) -> 0 | H105: =IFERROR(G105/Inputs!$D$16,0) -> 0 | I105: =IFERROR(G105/Inputs!$D$17,0) -> 0 | J105: =IFERROR(G105/Inputs!$D$13,0) -> 0 | K105: =IFERROR(G105/Inputs!$H$14,0) -> 0 | L105: =IFERROR(G105/$G$126,0) -> 0
...

Sheet (Z+) OpEx
C3: Operating Expenses
C5: Operating Expenses & Reserves
C7: Non-Control. Expenses | D7: Factor | E7: Month | F7: Year | G7: PUPM | H7: PUPY | I7: Growth (LU) | J7: Growth (Stab)
C8: Prop. Taxes | D8: =IFERROR(IF(M19=1,1.2%,0),0) -> 0 | E8: =IFERROR(F8/12,0) -> 0 | F8: =IFERROR(+MIN(D8*'(Z+) Dev Budget'!G119,6*'(Z+) Rent Roll'!P20), 0) -> 0 | G8: =IFERROR(+E8/Inputs!$H$14,0) -> 0 | H8: =IFERROR(+F8/Inputs!$H$14,0) -> 0 | I8: =IFERROR(0/100,0) -> 0 | J8: =IFERROR(2/100,0) -> 0.02
C9: Insurance | D9: =IFERROR(69,0) -> 69 | E9: =IFERROR((D9*'(Z+) Rent Roll'!E20)*(1+I9),0) -> 15765.12 | F9: =IFERROR(+E9*12,0) -> 189181.44 | G9: =IFERROR(+E9/Inputs!$H$14,0) -> 70.38 | H9: =IFERROR(+F9/Inputs!$H$14,0) -> 844.56 | I9: =IFERROR(2/100,0) -> 0.02 | J9: =IFERROR(3/100,0) -> 0.03
C10: Management | D10: =IFERROR(5/100,0) -> 0.05 | E10: =IFERROR(('(Z+) Rent Roll'!L20+'(Z+) Rent Roll'!H24)*D10,0) -> 25636.8 | F10: =IFERROR(E10*12,0) -> 307641.6 | G10: =IFERROR(+E10/Inputs!$H$14,0) -> 114.45 | H10: =IFERROR(+F10/Inputs!$H$14,0) -> 1373.4 | I10: =IFERROR(0/100,0) -> 0 | J10: =IFERROR('(Z+) Rent Roll'!M20,0) -> 0.025
C11: CMFA - Fee | D11: =IFERROR(0,0) -> 0 | E11: =IFERROR(F11/12,0) -> 583.33333 | F11: =IFERROR(7000,0) -> 7000 | G11: =IFERROR(+E11/Inputs!$H$14,0) -> 2.6041667 | H11: =IFERROR(F11/Inputs!$H$14,0) -> 31.25 | I11: =IFERROR(0/100,0) -> 0 | J11: =IFERROR(0/100,0) -> 0
C12: Non-Profit Partner - Fee | D12: =IFERROR(0,0) -> 0 | E12: =IFERROR(F12/12,0) -> 4806.6667 | F12: =IFERROR((MAX(20000,250*'(Z+) Rent Roll'!E20))*(1+I12),0) -> 57680 | G12: =IFERROR(+E12/Inputs!$H$14,0) -> 21.458333 | H12: =IFERROR(F12/Inputs!$H$14,0) -> 257.5 | I12: =IFERROR(3/100,0) -> 0.03 | J12: =IFERROR(3/100,0) -> 0.03
C13: Controllable Expenses
C14: Electric | D14: =IFERROR(30,0) -> 30 | E14: =IFERROR((D14*Inputs!$H$14)*(1+I14),0) -> 6921.6 | F14: =IFERROR(E14*12,0) -> 83059.2 | G14: =IFERROR(+E14/Inputs!$H$14,0) -> 30.9 | H14: =IFERROR(+F14/Inputs!$H$14,0) -> 370.8 | I14: =IFERROR(3/100,0) -> 0.03 | J14: =IFERROR(3/100,0) -> 0.03
C15: Water/Sewer | D15: =IFERROR(30,0) -> 30 | E15: =IFERROR((D15*Inputs!$H$14)*(1+I15),0) -> 6921.6 | F15: =IFERROR(E15*12,0) -> 83059.2 | G15: =IFERROR(+E15/Inputs!$H$14,0) -> 30.9 | H15: =IFERROR(+F15/Inputs!$H$14,0) -> 370.8 | I15: =IFERROR(3/100,0) -> 0.03 | J15: =IFERROR(3/100,0) -> 0.03
C16: Gas | D16: =IFERROR(20,0) -> 20 | E16: =IFERROR((D16*Inputs!$H$14)*(1+I16),0) -> 4614.4 | F16: =IFERROR(E16*12,0) -> 55372.8 | G16: =IFERROR(+E16/Inputs!$H$14,0) -> 20.6 | H16: =IFERROR(+F16/Inputs!$H$14,0) -> 247.2 | I16: =IFERROR(3/100,0) -> 0.03 | J16: =IFERROR(3/100,0) -> 0.03
C17: Trash | D17: =IFERROR(28,0) -> 28 | E17: =IFERROR((D17*Inputs!$H$14)*(1+I17),0) -> 6460.16 | F17: =IFERROR(E17*12,0) -> 77521.92 | G17: =IFERROR(+E17/Inputs!$H$14,0) -> 28.84 | H17: =IFERROR(+F17/Inputs!$H$14,0) -> 346.08 | I17: =IFERROR(3/100,0) -> 0.03 | J17: =IFERROR(3/100,0) -> 0.03
C18: Landscape | D18: =IFERROR(0,0) -> 0 | E18: =IFERROR((600*(1+I18)),0) -> 618 | F18: =IFERROR(E18*12,0) -> 7416 | G18: =IFERROR(+E18/Inputs!$H$14,0) -> 2.7589286 | H18: =IFERROR(+F18/Inputs!$H$14,0) -> 33.107143 | I18: =IFERROR(3/100,0) -> 0.03 | J18: =IFERROR(3/100,0) -> 0.03
C19: M&R/Turnover | D19: =IFERROR(50,0) -> 50 | E19: =IFERROR((D19*Inputs!H14)*(1+I19),0) -> 11536 | F19: =IFERROR(E19*12,0) -> 138432 | G19: =IFERROR(+E19/Inputs!$H$14,0) -> 51.5 | H19: =IFERROR(+F19/Inputs!$H$14,0) -> 618 | I19: =IFERROR(3/100,0) -> 0.03 | J19: =IFERROR(3/100,0) -> 0.03 | M19: 1
C20: Payroll/Security | D20: =IFERROR(0,0) -> 0 | E20: =IFERROR(+F20/12,0) -> 29125.973 | F20: =IFERROR((1472*Inputs!H14)*(1+I20),0) -> 349511.68 | G20: =IFERROR(+E20/Inputs!$H$14,0) -> 130.02667 | H20: =IFERROR(+F20/Inputs!$H$14,0) -> 1560.32 | I20: =IFERROR(6/100,0) -> 0.06 | J20: =IFERROR(3/100,0) -> 0.03
C21: HCID Fee | D21: =IFERROR(22,0) -> 22 | E21: =(D21*Inputs!H14)*(1+I21) -> 5075.84 | F21: =IFERROR(E21*12,0) -> 60910.08 | G21: =IFERROR(+E21/Inputs!$H$14,0) -> 22.66 | H21: =IFERROR(+F21/Inputs!$H$14,0) -> 271.92 | I21: =IFERROR(3/100,0) -> 0.03 | J21: =IFERROR(3/100,0) -> 0.03
C22: Elevator Maint. | D22: =IFERROR(5,0) -> 5 | E22: =IFERROR(1000*(1+I22),0) -> 1030 | F22: =IFERROR(E22*12,0) -> 12360 | G22: =IFERROR(+E22/Inputs!$H$14,0) -> 4.5982143 | H22: =IFERROR(+F22/Inputs!$H$14,0) -> 55.178571 | I22: =IFERROR(3/100,0) -> 0.03 | J22: =IFERROR(3/100,0) -> 0.03
C23: Legal | D23: =IFERROR(5,0) -> 5 | E23: =IFERROR((D23*Inputs!H14)*(1+I23),0) -> 1153.6 | F23: =IFERROR(E23*12,0) -> 13843.2 | G23: =IFERROR(+E23/Inputs!$H$14,0) -> 5.15 | H23: =IFERROR(+F23/Inputs!$H$14,0) -> 61.8 | I23: =IFERROR(3/100,0) -> 0.03 | J23: =IFERROR(3/100,0) -> 0.03
C24: Misc. | D24: =IFERROR(180,0) -> 180 | E24: =IFERROR((D24*Inputs!H14)*(1+I24),0) -> 41529.6 | F24: =IFERROR(E24*12,0) -> 498355.2 | G24: =IFERROR(+E24/Inputs!$H$14,0) -> 185.4 | H24: =IFERROR(+F24/Inputs!$H$14,0) -> 2224.8 | I24: =IFERROR(3/100,0) -> 0.03 | J24: =IFERROR(3.1/100,0) -> 0.031
C25: Mgr's Rent Credit | D25: =IFERROR(0,0) -> 0 | E25: =IFERROR((D25*Inputs!H14)*(1+I25),0) -> 0 | F25: =IFERROR(E25*12,0) -> 0 | G25: =IFERROR(+E25/Inputs!$H$14,0) -> 0 | H25: =IFERROR(+F25/Inputs!$H$14,0) -> 0 | I25: =IFERROR(3/100,0) -> 0.03 | J25: =IFERROR(3.1/100,0) -> 0.031
C26: Reserves | D26: =IFERROR(1,0) -> 1 | E26: =IFERROR((D26*Inputs!H14)*(1+I26),0) -> 230.72 | F26: =IFERROR(E26*12,0) -> 2768.64 | G26: =IFERROR(+E26/Inputs!$H$14,0) -> 1.03 | H26: =IFERROR(+F26/Inputs!H14,0) -> 12.36 | I26: =IFERROR(3/100,0) -> 0.03 | J26: =IFERROR(3/100,0) -> 0.03
C27: Total | D27: =IFERROR(F27/G35, 0) -> 0.31681548 | E27: =IFERROR(SUM(E8:E26),0) -> 162009.41 | F27: =IFERROR(SUM(F8:F26),0) -> 1944113 | G27: =IFERROR(SUM(G8:G26),0) -> 723.25631 | H27: =IFERROR(SUM(H8:H26),0) -> 8679.0757 | I27: =IFERROR(3/100,0) -> 0.03 | J27: =IFERROR(SUMPRODUCT(J8:J26,H8:H26)/SUM(H8:H26), 0) -> 0.029357109
F29: Untrended (Today) | I29: Trended (Stabilization)
C30: Operating Summary | F30: Covenants | G30: As Rented | H30: Tax Exempt | I30: Covenants | J30: As Rented | K30: Tax Exempt
C31: Residential Rents (GPR) | F31: =IFERROR('(Z+) Rent Roll'!H20*12*Inputs!$H$14,0) -> 6152832 | G31: =IFERROR('(Z+) Rent Roll'!L20*12,0) -> 6152832 | H31: =IFERROR(+G31,0) -> 6152832 | I31: =IFERROR('(Z+) Rent Roll'!H20*12*Inputs!$F$34,0) -> 29337.562 | J31: =IFERROR(INDEX('(Z+) Monthly CF'!$F$14:$HB$14,1,MATCH(Inputs!$D$34,'(Z+) Monthly CF'!$F$5:$HB$5,0))*12,0) -> 6571613.8 | K31: =IFERROR(+J31,0) -> 6571613.8
C32: Commercial Rents (MG, net of Vac) | F32: =IFERROR('(Z+) Rent Roll'!$H$24*12,0) -> 0 | G32: =IFERROR('(Z+) Rent Roll'!$H$24*12,0) -> 0 | H32: =IFERROR('(Z+) Rent Roll'!$H$24*12,0) -> 0 | I32: =IFERROR('(Z+) Rent Roll'!$H$24*12*Inputs!$F$34,0) -> 0 | J32: =IFERROR('(Z+) Rent Roll'!$H$24*12,0) -> 0 | K32: =IFERROR('(Z+) Rent Roll'!$H$24*12,0) -> 0
C33: Other Income | F33: =IFERROR('(Z+) Rent Roll'!$H$36*12,0) -> 168173.38 | G33: =IFERROR('(Z+) Rent Roll'!$H$36*12,0) -> 168173.38 | H33: =IFERROR('(Z+) Rent Roll'!$H$36*12,0) -> 168173.38 | I33: =IFERROR('(Z+) Rent Roll'!$H$36*12*Inputs!$F$34,0) -> 179619.8 | J33: =IFERROR(INDEX('(Z+) Monthly CF'!$F$15:$HB$15,1,MATCH(Inputs!$D$34,'(Z+) Monthly CF'!$F$5:$HB$5,0))*12,0) -> 179619.8 | K33: =IFERROR(+J33,0) -> 179619.8
C34: Residential Losses | F34: =IFERROR(-'(Z+) Rent Roll'!N20*F31,0) -> -184584.96 | G34: =IFERROR(-'(Z+) Rent Roll'!N20*G31,0) -> -184584.96 | H34: =IFERROR(+G34,0) -> -184584.96 | I34: =IFERROR(-'(Z+) Rent Roll'!N20*I31,0) -> -880.12685 | J34: =IFERROR(INDEX('(Z+) Monthly CF'!$F$17:$HB$17,1,MATCH(Inputs!$D$34,'(Z+) Monthly CF'!$F$5:$HB$5,0))*12,0) -> -197148.41 | K34: =IFERROR(+J34,0) -> -197148.41
C35: Effective Gross Income | F35: =IFERROR(SUM(F31:F34),0) -> 6136420.4 | G35: =IFERROR(SUM(G31:G34),0) -> 6136420.4 | H35: =IFERROR(SUM(H31:H34),0) -> 6136420.4 | I35: =IFERROR(SUM(I31:I34),0) -> 208077.24 | J35: =IFERROR(SUM(J31:J34),0) -> 6554085.2 | K35: =IFERROR(SUM(K31:K34),0) -> 6554085.2
C36: Operating Expenses | F36: =IFERROR(-SUM(F14:F26,F8,F9)-$D$10*F31,0) -> -1879433 | G36: =IFERROR(-F27,0) -> -1944113 | H36: =IFERROR(+G36+$F$8*(SUM('(Z+) Rent Roll'!E12:E19)/Inputs!H14),0) -> -1944113 | I36: =IFERROR(J36+$D$10*(J31-I31),0) -> -1400844.5 | J36: =IFERROR(INDEX('(Z+) Monthly CF'!$F$47:$HB$47,1,MATCH(Inputs!$D$34,'(Z+) Monthly CF'!$F$5:$HB$5,0))*12,0) -> -1727958.3 | K36: =IFERROR(+J36+F8*(SUM('(Z+) Rent Roll'!E12:E19)/Inputs!H14),0) -> -1727958.3
C37: Net Operating Income | F37: =IFERROR(SUM(F35:F36),0) -> 4256987.5 | G37: =IFERROR(SUM(G35:G36),0) -> 4192307.5 | H37: =IFERROR(SUM(H35:H36),0) -> 4192307.5 | I37: =IFERROR(SUM(I35:I36),0) -> -1192767.3 | J37: =IFERROR(SUM(J35:J36),0) -> 4826126.8 | K37: =IFERROR(SUM(K35:K36),0) -> 4826126.8
C38: Return on Cost | F38: =IFERROR(F37/('(Z+) Dev Budget'!$G$126-'(Z+) Dev Budget'!$G$22),0) -> 0.071248263 | G38: =IFERROR(G37/('(Z+) Dev Budget'!$G$126-'(Z+) Dev Budget'!$G$22),0) -> 0.070165728 | H38: =IFERROR(H37/('(Z+) Dev Budget'!$G$126-'(Z+) Dev Budget'!$G$22),0) -> 0.070165728 | I38: =IFERROR(I37/'(Z+) Dev Budget'!$G$126,0) -> -0.019820783 | J38: =IFERROR(J37/'(Z+) Dev Budget'!$G$126,0) -> 0.080198049 | K38: =IFERROR(+K37/'(Z+) Dev Budget'!$G$126,0) -> 0.080198049
C39: Cash-on-Cash | F39: =IFERROR((F37+IPMT('(Z+) Financing'!$H$18*365.25/360,1,'(Z+) Financing'!$H$21,'(Z+) Financing'!$H$19))/Inputs!$L$23,0) -> 0.12656009 | G39: =IFERROR((G37+IPMT('(Z+) Financing'!$H$18*365.25/360,1,'(Z+) Financing'!$H$21,'(Z+) Financing'!$H$19))/Inputs!$L$23,0) -> 0.12090861 | H39: =IFERROR((H37+IPMT('(Z+) Financing'!$H$18*365.25/360,1,'(Z+) Financing'!$H$21,'(Z+) Financing'!$H$19))/Inputs!$L$23,0) -> 0.12090861 | I39: =IFERROR((I37+IPMT('(Z+) Financing'!$H$18*365.25/360,1,'(Z+) Financing'!$H$21,'(Z+) Financing'!$H$19))/Inputs!$L$23,0) -> -0.34961778 | J39: =IFERROR((J37+IPMT('(Z+) Financing'!$H$18*365.25/360,1,'(Z+) Financing'!$H$21,'(Z+) Financing'!$H$19))/Inputs!$L$23,0) -> 0.17628922 | K39: =IFERROR((K37+IPMT('(Z+) Financing'!$H$18*365.25/360,1,'(Z+) Financing'!$H$21,'(Z+) Financing'!$H$19))/Inputs!$L$23,0) -> 0.17628922
C40: Operating Ratio | F40: =IFERROR(IFERROR(-F36/F35,0),0) -> 0.30627513 | G40: =IFERROR(-G36/G35,0) -> 0.31681548 | H40: =IFERROR(-H36/H35,0) -> 0.31681548 | I40: =IFERROR(-I36/I35,0) -> 6.7323295 | J40: =IFERROR(-J36/J35,0) -> 0.263646 | K40: =IFERROR(-K36/K35,0) -> 0.263646
C41: Valuation | F41: =IFERROR((F37+$F$8)/('(Z+) Financing'!$H$8+$D$8),0) -> 74034564 | G41: =IFERROR((G37+$F$8)/('(Z+) Financing'!$H$8+$D$8),0) -> 72909695 | H41: =IFERROR((H37+$F$8)/('(Z+) Financing'!$H$8+$D$8),0) -> 72909695 | I41: =IFERROR((I37+$F$8*1.02^(Inputs!$E$33/12))/('(Z+) Financing'!$H$8+$D$8),0) -> -20743779 | J41: =IFERROR((J37+$F$8*1.02^(Inputs!$E$33/12))/('(Z+) Financing'!$H$8+$D$8),0) -> 83932640 | K41: =IFERROR((K37+$F$8*1.02^(Inputs!$E$33/12))/('(Z+) Financing'!$H$8+$D$8),0) -> 83932640
C42: Per Unit | F42: =IFERROR(F41/Inputs!H14,0) -> 330511.45 | G42: =IFERROR(G41/Inputs!H14,0) -> 325489.71 | H42: =IFERROR(H41/Inputs!H14,0) -> 325489.71 | I42: =IFERROR(I41/Inputs!H14,0) -> -92606.157 | J42: =IFERROR(J41/Inputs!H14,0) -> 374699.29 | K42: =IFERROR(K41/Inputs!H14,0) -> 374699.29
C43: Value-Add | F43: =IFERROR(F41/'(Z+) Dev Budget'!$G$126-1,0) -> 0.23026764 | G43: =IFERROR(G41/'(Z+) Dev Budget'!$G$126-1,0) -> 0.21157515 | H43: =IFERROR(H41/'(Z+) Dev Budget'!$G$126-1,0) -> 0.21157515 | I43: =IFERROR(I41/'(Z+) Dev Budget'!$G$126-1,0) -> -1.3447093 | J43: =IFERROR(J41/'(Z+) Dev Budget'!$G$126-1,0) -> 0.39474869 | K43: =IFERROR(K41/'(Z+) Dev Budget'!$G$126-1,0) -> 0.39474869

Sheet (Z+) Financing
C3: Financing
C5: Acquisition Financing | F5: Permanent Financing | J5: LP Returns
C6: LTC | D6: =IFERROR(0/100,0) -> 0 | F6: Underwriting Method | H6: As Rented | J6: Project Unlevered IRR | K6: ='(Z+) Monthly CF'!F102 -> 0.097391468
C7: Interest Rate | D7: =IFERROR(8.37/100,0) -> 0.0837 | F7: Underwritten NOI | H7: =+IFERROR('(Z+) OpEx'!J37,0) -> 4826126.8 | J7: Project Levered IRR | K7: =IFERROR('(Z+) Monthly CF'!F103,0) -> 0.15538478
C8: Closing Costs % | D8: =IFERROR(1/100,0) -> 0.01 | F8: Cap Rate | H8: =+IFERROR(5.75/100,0) -> 0.0575 | J8: Going-In Cash/Cash | K8: =+IFERROR('(Z+) OpEx'!G39,0) -> 0.12090861
C9: Closing Costs | D9: =IFERROR(D8*D10,0) -> 0 | F9: Valuation at Refi | H9: =MIN(H7/H8,(INDEX('(Z+) OpEx'!$I$37:$K$37,MATCH(H6,'(Z+) OpEx'!$I$30:$K$30,0))+'(Z+) OpEx'!F8*1.02^(Inputs!E33/12))/(H8+'(Z+) OpEx'!D8)) -> 83932640 | J9: Stabilized Project Cash/Cash | K9: =IFERROR('(Z+) OpEx'!J39,0) -> 0.17628922
C10: Loan Proceeds | D10: =IFERROR(D6*'(Z+) Dev Budget'!G10,0) -> 0 | F10: Value-Add | H10: =+H9/'(Z+) Dev Budget'!G126-1 -> 0.39474869 | J10: Going-In Return on Cost | K10: =+IFERROR('(Z+) OpEx'!G38,0) -> 0.070165728
F11: Minimum DSCR | H11: 1.2 | J11: Stabilized Return on Cost | K11: =IFERROR('(Z+) OpEx'!J38,0) -> 0.080198049
C12: Mezzanine Financing | D12: OFF | F12: DSCR Rate Margin | H12: =0 -> 0 | J12: Equity Multiple (Project-Level) | K12: =IFERROR('(Z+) Monthly CF'!F104,0) -> 1.7201935
C13: Underwriting Method | D13: Covenants | F13: DSCR Loan Amount | H13: =-PV((H18+H12)/12*365.25/360,H21*12,H7/H11/12) -> 59946712 | J13: Gross Profit | K13: =IFERROR('(Z+) Monthly CF'!D73,0) -> 34023171
C14: Underwritten NOI | D14: =+MIN(INDEX('(Z+) OpEx'!$F$37:$H$37,MATCH(D13,'(Z+) OpEx'!$F$30:$H$30,0)),INDEX('(Z+) OpEx'!$F$35:$H$35,MATCH(D28,'(Z+) OpEx'!$F$30:$H$30,0))*(1-'(Z+) OpEx'!D27)) -> 4192307.5 | F14: Max LTV | H14: =75/100 -> 0.75 | J14: Levered Profit | K14: =IFERROR('(Z+) Monthly CF'!D100,0) -> 17170572
C15: Cap Rate | D15: =IFERROR(5.75/100,0) -> 0.0575 | F15: LTV Loan Amount | H15: =H9*H14 -> 62949480
C16: Interest Rate | D16: =IFERROR(11/100,0) -> 0.11 | F16: Max LTC | H16: =80/100 -> 0.8
C17: Valuation at Refi | D17: =MIN(D14/D15,(INDEX('(Z+) OpEx'!$F$37:$H$37,MATCH(D13,'(Z+) OpEx'!$F$30:$H$30,0))+'(Z+) OpEx'!F8)/(D30+'(Z+) OpEx'!D8)) -> 70949791 | F17: LTC Loan Amount | H17: =IFERROR('(Z+) Dev Budget'!G126*H16,0) -> 48142087
C18: Max LTC | D18: =IFERROR(70/100,0) -> 0.7 | F18: Interest Rate | H18: =Dashboard!K12 -> 0.0575
C19: LTC Loan Amount | D19: =IFERROR((D18-D32)*'(Z+) Dev Budget'!G118,0) -> 0 | F19: Loan Proceeds | H19: =ROUNDDOWN(MIN(H13,H15,H17),-3) -> 48142000
C20: Debt Yield | D20: =IFERROR(6.5/100,0) -> 0.065 | F20: Net After Fees | H20: =+H19*(1-H22) -> 47660580
C21: DY Loan Amount | D21: =(D14/D20)-D38 -> 28161038 | F21: Amortization | H21: 35
C22: Loan Proceeds | D22: =MAX(0,ROUNDDOWN(MIN(D19,D21),-3))*($D$12="ON") -> 0 | F22: Fees | H22: =IFERROR(1/100,0) -> 0.01
C23: Closing Costs % | D23: =IFERROR(1.5/100,0) -> 0.015 | F23: LTV | H23: =IFERROR(H19/(H7/H8),0) -> 0.573579
C24: Closing Costs | D24: =D22*D23*1.005 -> 0 | F24: LTC | H24: =IFERROR(H19/'(Z+) Dev Budget'!G126,0) -> 0.79999856
C25: LTC | D25: =IFERROR(+D22/'(Z+) Dev Budget'!G126,0) -> 0
F26: Exit Valuation | G26: Covenants | H26: As Rented
C27: Construction Financing | F27: Exit Month | G27: =IFERROR(Inputs!E38,0) -> 49034 | H27: =IFERROR(Inputs!E38,0) -> 49034
C28: Underwriting Method | D28: As Rented | F28: Cap Rate (Exit) | G28: =IFERROR(5.75/100,0) -> 0.0575 | H28: =IFERROR(Dashboard!J5,0) -> 0.0675
C29: Underwritten NOI | D29: =+MIN(INDEX('(Z+) OpEx'!$I$37:$K$37,MATCH(D28,'(Z+) OpEx'!$I$30:$K$30,0)),INDEX('(Z+) OpEx'!$I$35:$K$35,MATCH(D28,'(Z+) OpEx'!$I$30:$K$30,0))*(1-'(Z+) OpEx'!D27)) -> 4477649.6 | F29: Fwd EGI at Exit | G29: =IFERROR(SUMIF('(Z+) Monthly CF'!$4:$4,"<="&EOMONTH(Inputs!E$38,12),'(Z+) Monthly CF'!$29:$29)-SUMIF('(Z+) Monthly CF'!$4:$4,"<="&Inputs!E$38,'(Z+) Monthly CF'!$29:$29),0) -> 236154.02 | H29: =IFERROR(SUMIF('(Z+) Monthly CF'!$4:$4,"<="&EOMONTH(Inputs!E$38,12),'(Z+) Monthly CF'!$19:$19)-SUMIF('(Z+) Monthly CF'!$4:$4,"<="&Inputs!E$38,'(Z+) Monthly CF'!$19:$19),0) -> 7438456.8
C30: Cap Rate | D30: =+IFERROR(6/100,0) -> 0.06 | F30: Fwd NOI at Exit | G30: =IFERROR('(Z+) OpEx'!F37,0) -> 4256987.5 | H30: =IFERROR('(Z+) OpEx'!G37,0) -> 4192307.5
C31: Valuation at Refi | D31: =MIN(D29/D30,(INDEX('(Z+) OpEx'!$F$37:$H$37,MATCH(D28,'(Z+) OpEx'!$F$30:$H$30,0))+'(Z+) OpEx'!F8)/(D30+'(Z+) OpEx'!D8)) -> 69871791 | F31: Adj NOI at Exit | G31: =IFERROR(G30,0) -> 4256987.5 | H31: =IFERROR(H30,0) -> 4192307.5
C32: Max LTC | D32: =+IFERROR(Dashboard!J11,0) -> 0.7 | F32: Value at Exit | G32: =IFERROR(MIN(G30,G31)/G28,0) -> 74034564 | H32: =IFERROR(MIN(H30,H31)/H28,0) -> 62108259
C33: LTC Loan Amount | D33: =+IFERROR(D32*'(Z+) Dev Budget'!G118,0) -> 36336474 | F33: GSF | G33: =IFERROR(G32/Inputs!D16,0) -> 5450.7318 | H33: =IFERROR(H32/Inputs!D16,0) -> 4572.6677
C34: Max LTV | D34: 0.75 | F34: LSF | G34: =IFERROR(G32/Inputs!D13,0) -> 2511.1785 | H34: =IFERROR(H32/Inputs!D13,0) -> 2106.6501
C35: LTV Loan Amount | D35: =IFERROR(D34*D31,0) -> 52403843 | F35: RSF | G35: =IFERROR(G32/Inputs!D16,0) -> 5450.7318 | H35: =IFERROR(H32/Inputs!D16,0) -> 4572.6677
C36: Interest Rate | D36: =Dashboard!J12 -> 0.09 | F36: Unit | G36: =IFERROR(G32/'(Z+) Rent Roll'!E20,0) -> 330511.45 | H36: =IFERROR(H32/'(Z+) Rent Roll'!E20,0) -> 277269.01
C37: DSCR Loan Amount | D37: =-PV((H18+H12)/12*365.25/360,H21*12,D29/H11/12) -> 55618175 | F37: Appreciation to Cost | G37: =IFERROR((G32-'(Z+) Dev Budget'!G126)/'(Z+) Dev Budget'!G126,0) -> 0.23026764 | H37: =IFERROR((H32-'(Z+) Dev Budget'!G126)/'(Z+) Dev Budget'!G126,0) -> 0.032082534
C38: Loan Proceeds | D38: =+ROUNDDOWN(D33,-3) -> 36336000 | F38: Sale Costs | G38: =IFERROR(2.5%+0.013373,0) -> 0.038373 | H38: =IFERROR(0.025+0.013373,0) -> 0.038373
C39: Closing Costs % | D39: =1/100 -> 0.01 | F39: Sales Proceeds | G39: =IFERROR(G32*(1-G38),0) -> 71193636 | H39: =IFERROR(H32*(1-H38),0) -> 59724978
C40: Closing Costs | D40: =D38*D39*1.005 -> 365176.8 | F40: Sale Proceeds | G40: As Rented | H40: =IFERROR(IF(G40="Covenants",G39,H39),0) -> 59724978
C41: LTC | D41: =IFERROR(+D38/'(Z+) Dev Budget'!G126,0) -> 0.60381263
C43: Subordinate / Soft Debt — Amount | D43: 0
C44: Sub Rate | D44: 0
C45: Sub Amort (yrs; 0 = IO/deferred) | D45: 0

Sheet (Z+) Rent Roll
C3: Rent Roll
C5: Rent Roll - Residential
C6: Unit Type | D6: Beds | E6: Units | F6: Utility Allowance | G6: Natural Rent | H6: Nat. Income | I6: Voucher Pmt | J6: % Subsid. | K6: Adj. Rents | L6: Adj. Income | M6: Growth | N6: Stab. Vac. | O6: Avg SF | P6: NRSF | Q6: PSF Rent | R6: OS/Unit | S6: Tot. OS
C7: Manager 1BR | E7: =IFERROR(1,0) -> 1 | F7: =IFERROR(0,0) -> 0 | G7: =IFERROR(I7-F7,0) -> 2289 | H7: =IFERROR(G7*E7,0) -> 2289 | I7: =IFERROR(I9,0) -> 2289 | J7: =IFERROR(100/100,0) -> 1 | K7: =IFERROR((I7-G7)*J7+G7,0) -> 2289 | L7: =IFERROR(K7*E7,0) -> 2289 | M7: =IFERROR(+Inputs!$L$7,0) -> 0.025 | N7: =IFERROR(+Inputs!$L$6,0) -> 0.03 | O7: =IFERROR(O13,0) -> 419 | P7: =IFERROR(O7*E7,0) -> 419 | Q7: =IFERROR(K7/O7,0) -> 5.4630072 | R7: =IFERROR(100,0) -> 100 | S7: =IFERROR(R7*E7,0) -> 100
C8: Market Rate 0BR | D8: =IFERROR(1,0) -> 1 | E8: =IFERROR(IF(Inputs!$O$29="NO",ROUND((Inputs!$H$14-$E$7-Inputs!$O$32)*M24,0),0),0) -> 0 | F8: =IFERROR(0,0) -> 0 | G8: =IFERROR(2041-F8,0) -> 2041 | H8: =IFERROR(G8*E8,0) -> 0 | I8: =IFERROR(G8,0) -> 2041 | J8: =IFERROR(100/100,0) -> 1 | K8: =IFERROR((I8-G8)*J8+G8,0) -> 2041 | L8: =IFERROR(K8*E8,0) -> 0 | M8: =IFERROR(+Inputs!$L$7,0) -> 0.025 | N8: =IFERROR(+Inputs!$L$6,0) -> 0.03 | O8: =IFERROR(310,0) -> 310 | P8: =IFERROR(O8*E8,0) -> 0 | Q8: =IFERROR(K8/O8,0) -> 6.583871 | R8: =IFERROR(100,0) -> 100 | S8: =IFERROR(R8*E8,0) -> 0
C9: Market Rate 1BR | D9: =IFERROR(0,0) -> 0 | E9: =IFERROR(IF(Inputs!$O$29="NO",ROUND((Inputs!$H$14-$E$7-Inputs!$O$32)*M25,0),0),0) -> 0 | F9: =IFERROR(0,0) -> 0 | G9: =IFERROR(2289-F9,0) -> 2289 | H9: =IFERROR(G9*E9,0) -> 0 | I9: =IFERROR(G9,0) -> 2289 | J9: =IFERROR(100/100,0) -> 1 | K9: =IFERROR((I9-G9)*J9+G9,0) -> 2289 | L9: =IFERROR(K9*E9,0) -> 0 | M9: =IFERROR(+Inputs!$L$7,0) -> 0.025 | N9: =IFERROR(+Inputs!$L$6,0) -> 0.03 | O9: =IFERROR(419,0) -> 419 | P9: =IFERROR(O9*E9,0) -> 0 | Q9: =IFERROR(K9/O9,0) -> 5.4630072 | R9: =IFERROR(100,0) -> 100 | S9: =IFERROR(R9*E9,0) -> 0
C10: Market Rate 2BR | D10: =IFERROR(2,0) -> 2 | E10: =IFERROR(IF(Inputs!$O$29="NO",ROUND((Inputs!$H$14-$E$7-Inputs!$O$32)*M26,0),0),0) -> 0 | F10: =IFERROR(0,0) -> 0 | G10: =IFERROR(2887-F10,0) -> 2887 | H10: =IFERROR(G10*E10,0) -> 0 | I10: =IFERROR(G10,0) -> 2887 | J10: =IFERROR(100/100,0) -> 1 | K10: =IFERROR((I10-G10)*J10+G10,0) -> 2887 | L10: =IFERROR(K10*E10,0) -> 0 | M10: =IFERROR(+Inputs!$L$7,0) -> 0.025 | N10: =IFERROR(+Inputs!$L$6,0) -> 0.03 | O10: =IFERROR(730,0) -> 730 | P10: =IFERROR(O10*E10,0) -> 0 | Q10: =IFERROR(K10/O10,0) -> 3.9547945 | R10: =IFERROR(100,0) -> 100 | S10: =IFERROR(R10*E10,0) -> 0
C11: Market Rate 3BR | D11: =IFERROR(3,0) -> 3 | E11: =IFERROR(IF(Inputs!$O$29="NO",ROUND((Inputs!$H$14-$E$7-Inputs!$O$32)*M27,0),0),0) -> 0 | F11: =IFERROR(0,0) -> 0 | G11: =IFERROR(3668-F11,0) -> 3668 | H11: =IFERROR(G11*E11,0) -> 0 | I11: =IFERROR(G11,0) -> 3668 | J11: =IFERROR(100/100,0) -> 1 | K11: =IFERROR((I11-G11)*J11+G11,0) -> 3668 | L11: =IFERROR(K11*E11,0) -> 0 | M11: =IFERROR(+Inputs!$L$7,0) -> 0.025 | N11: =IFERROR(+Inputs!$L$6,0) -> 0.03 | O11: =IFERROR(830,0) -> 830 | P11: =IFERROR(O11*E11,0) -> 0 | Q11: =IFERROR(K11/O11,0) -> 4.4192771 | R11: =IFERROR(100,0) -> 100 | S11: =IFERROR(R11*E11,0) -> 0
C12: HUD/TCAC 80% AMI 0BR | D12: =IFERROR(1,0) -> 1 | E12: =IFERROR(ROUND((Inputs!H14-$E$7-SUM($E$16:$E$19)-SUM($E$8:$E$11))*M24,0),0) -> 0 | F12: =IFERROR(0,0) -> 0 | G12: =IFERROR(0,0) -> 0 | H12: =IFERROR(G12*E12,0) -> 0 | I12: =IFERROR(2023.68,0) -> 2023.68 | J12: =IFERROR(100/100,0) -> 1 | K12: =IFERROR((I12-G12)*J12+G12,0) -> 2023.68 | L12: =IFERROR(K12*E12,0) -> 0 | M12: =IFERROR(+Inputs!$L$7,0) -> 0.025 | N12: =IFERROR(+Inputs!$L$6,0) -> 0.03 | O12: =IFERROR(O8,0) -> 310 | P12: =IFERROR(O12*E12,0) -> 0 | Q12: =IFERROR(K12/O12,0) -> 6.528 | R12: =IFERROR(100,0) -> 100 | S12: =IFERROR(R12*E12,0) -> 0
C13: HUD/TCAC 80% AMI 1BR | D13: =IFERROR(0,0) -> 0 | E13: =IFERROR(ROUNDUP(Inputs!H14*0.8,0)-1,0) -> 179 | F13: =IFERROR(0,0) -> 0 | G13: =IFERROR(0,0) -> 0 | H13: =IFERROR(G13*E13,0) -> 0 | I13: =IFERROR(2289,0) -> 2289 | J13: =IFERROR(100/100,0) -> 1 | K13: =IFERROR((I13-G13)*J13+G13,0) -> 2289 | L13: =IFERROR(K13*E13,0) -> 409731 | M13: =IFERROR(+Inputs!$L$7,0) -> 0.025 | N13: =IFERROR(+Inputs!$L$6,0) -> 0.03 | O13: =IFERROR(O9,0) -> 419 | P13: =IFERROR(O13*E13,0) -> 75001 | Q13: =IFERROR(K13/O13,0) -> 5.4630072 | R13: =IFERROR(100,0) -> 100 | S13: =IFERROR(R13*E13,0) -> 17900
C14: HUD/TCAC 80% AMI 2BR | D14: =IFERROR(2,0) -> 2 | E14: =IFERROR(ROUND((Inputs!H14-$E$7-SUM($E$16:$E$19)-SUM($E$8:$E$11))*M26,0),0) -> 0 | F14: =IFERROR(0,0) -> 0 | G14: =IFERROR(0,0) -> 0 | H14: =IFERROR(G14*E14,0) -> 0 | I14: =IFERROR(2896.392,0) -> 2896.392 | J14: =IFERROR(100/100,0) -> 1 | K14: =IFERROR((I14-G14)*J14+G14,0) -> 2896.392 | L14: =IFERROR(K14*E14,0) -> 0 | M14: =IFERROR(+Inputs!$L$7,0) -> 0.025 | N14: =IFERROR(+Inputs!$L$6,0) -> 0.03 | O14: =IFERROR(O10,0) -> 730 | P14: =IFERROR(O14*E14,0) -> 0 | Q14: =IFERROR(K14/O14,0) -> 3.9676603 | R14: =IFERROR(100,0) -> 100 | S14: =IFERROR(R14*E14,0) -> 0
C15: HUD/TCAC 80% AMI 3BR | D15: =IFERROR(3,0) -> 3 | E15: =IFERROR(ROUND((Inputs!H14-$E$7-SUM($E$16:$E$19)-SUM($E$8:$E$11))*M27,0),0) -> 0 | F15: =IFERROR(0,0) -> 0 | G15: =IFERROR(0,0) -> 0 | H15: =IFERROR(G15*E15,0) -> 0 | I15: =IFERROR(3718.512,0) -> 3718.512 | J15: =IFERROR(100/100,0) -> 1 | K15: =IFERROR((I15-G15)*J15+G15,0) -> 3718.512 | L15: =IFERROR(K15*E15,0) -> 0 | M15: =IFERROR(+Inputs!$L$7,0) -> 0.025 | N15: =IFERROR(+Inputs!$L$6,0) -> 0.03 | O15: =IFERROR(O11,0) -> 830 | P15: =IFERROR(O15*E15,0) -> 0 | Q15: =IFERROR(K15/O15,0) -> 4.4801349 | R15: =IFERROR(100,0) -> 100 | S15: =IFERROR(R15*E15,0) -> 0
C16: HCD 110% AMI 0BR | D16: =IFERROR(1,0) -> 1 | E16: =IFERROR(ROUND(Inputs!$O$32*M24,0),0) -> 0 | F16: =IFERROR(0,0) -> 0 | G16: =IFERROR(0,0) -> 0 | H16: =IFERROR(G16*E16,0) -> 0 | I16: =IFERROR(2023.68,0) -> 2023.68 | J16: =IFERROR(100/100,0) -> 1 | K16: =IFERROR((I16-G16)*J16+G16,0) -> 2023.68 | L16: =IFERROR(K16*E16,0) -> 0 | M16: =IFERROR(+Inputs!$L$7,0) -> 0.025 | N16: =IFERROR(+Inputs!$L$6,0) -> 0.03 | O16: =IFERROR(O8,0) -> 310 | P16: =IFERROR(O16*E16,0) -> 0 | Q16: =IFERROR(K16/O16,0) -> 6.528 | R16: =IFERROR(100,0) -> 100 | S16: =IFERROR(R16*E16,0) -> 0
C17: HCD 110% AMI 1BR | D17: =IFERROR(0,0) -> 0 | E17: =IFERROR(ROUNDDOWN(Inputs!H14*0.2,0),0) -> 44 | F17: =IFERROR(0,0) -> 0 | G17: =IFERROR(0,0) -> 0 | H17: =IFERROR(G17*E17,0) -> 0 | I17: =IFERROR(2289,0) -> 2289 | J17: =IFERROR(100/100,0) -> 1 | K17: =IFERROR((I17-G17)*J17+G17,0) -> 2289 | L17: =IFERROR(K17*E17,0) -> 100716 | M17: =IFERROR(+Inputs!$L$7,0) -> 0.025 | N17: =IFERROR(+Inputs!$L$6,0) -> 0.03 | O17: =IFERROR(O9,0) -> 419 | P17: =IFERROR(O17*E17,0) -> 18436 | Q17: =IFERROR(K17/O17,0) -> 5.4630072 | R17: =IFERROR(100,0) -> 100 | S17: =IFERROR(R17*E17,0) -> 4400
C18: HCD 110% AMI 2BR | D18: =IFERROR(2,0) -> 2 | E18: =IFERROR(ROUND(Inputs!$O$32*M26,0),0) -> 0 | F18: =IFERROR(0,0) -> 0 | G18: =IFERROR(0,0) -> 0 | H18: =IFERROR(G18*E18,0) -> 0 | I18: =IFERROR(2896.392,0) -> 2896.392 | J18: =IFERROR(100/100,0) -> 1 | K18: =IFERROR((I18-G18)*J18+G18,0) -> 2896.392 | L18: =IFERROR(K18*E18,0) -> 0 | M18: =IFERROR(+Inputs!$L$7,0) -> 0.025 | N18: =IFERROR(+Inputs!$L$6,0) -> 0.03 | O18: =IFERROR(O10,0) -> 730 | P18: =IFERROR(O18*E18,0) -> 0 | Q18: =IFERROR(K18/O18,0) -> 3.9676603 | R18: =IFERROR(100,0) -> 100 | S18: =IFERROR(R18*E18,0) -> 0
C19: HCD 110% AMI 3BR | D19: =IFERROR(3,0) -> 3 | E19: =IFERROR(ROUND(Inputs!$O$32*M27,0),0) -> 0 | F19: =IFERROR(0,0) -> 0 | G19: =IFERROR(0,0) -> 0 | H19: =IFERROR(G19*E19,0) -> 0 | I19: =IFERROR(3718.512,0) -> 3718.512 | J19: =IFERROR(100/100,0) -> 1 | K19: =IFERROR((I19-G19)*J19+G19,0) -> 3718.512 | L19: =IFERROR(K19*E19,0) -> 0 | M19: =IFERROR(+Inputs!$L$7,0) -> 0.025 | N19: =IFERROR(+Inputs!$L$6,0) -> 0.03 | O19: =IFERROR(O11,0) -> 830 | P19: =IFERROR(O19*E19,0) -> 0 | Q19: =IFERROR(K19/O19,0) -> 4.4801349 | R19: =IFERROR(100,0) -> 100 | S19: =IFERROR(R19*E19,0) -> 0
C20: Summary/Blended | D20: =IFERROR(SUMPRODUCT(D7:D19,E7:E19)+SUMPRODUCT(D46:D49,E46:E49),0) -> 0 | E20: =IFERROR(SUM(E7:E19,E46:E49),0) -> 0 | F20: =IFERROR((SUMPRODUCT(E7:E19,F7:F19)+SUMPRODUCT(E46:E49,F46:F49))/E20,0) -> 0 | G20: =IFERROR((SUMPRODUCT(E7:E19,G7:G19)+SUMPRODUCT(E46:E49,G46:G49))/E20,0) -> 0 | H20: =IFERROR(SUM(H7:H19,H46:H49),0) -> 0 | I20: =IFERROR((SUMPRODUCT($E$7:$E$19,I7:I19)+SUMPRODUCT($E$46:$E$49,I46:I49))/Inputs!H14,0) -> 0 | J20: =IFERROR((SUMPRODUCT(E7:E19,J7:J19)+SUMPRODUCT(E46:E49,J46:J49))/E20,0) -> 0 | K20: =IFERROR((SUMPRODUCT($E$7:$E$19,K7:K19)+SUMPRODUCT($E$46:$E$49,K46:K49))/Inputs!H14,0) -> 0 | L20: =IFERROR(K20*E20,0) -> 512736 | M20: =IFERROR((SUMPRODUCT(M7:M19,$L$7:$L$19)+SUMPRODUCT(M46:M49,L46:L49))/$L$20,0) -> 0 | N20: =IFERROR((SUMPRODUCT(N7:N19,$L$7:$L$19)+SUMPRODUCT(N46:N49,L46:L49))/$L$20,0) -> 0 | O20: =IFERROR(P20/E20,0) -> 419 | P20: =IFERROR(SUM(P7:P19,P46:P49),0) -> 0 | Q20: =IFERROR(L20/P20,0) -> 5.4630072 | R20: =IFERROR(S20/E20,0) -> 100 | S20: =IFERROR(SUM(S7:S19,S46:S49),0) -> 0
C22: Rent Roll - Commercial (Modified Gross) | K22: Untrended | P22: Market | S22: Restricted
C23: SF | D23: $/SF/M | E23: $/SF/Y | F23: Vacancy | G23: Growth | H23: Net Tot. (M) | K23: Unit Mix Summary | M23: % | N23: # | O23: Avg SF | P23: Rent | Q23: PSF | R23: Base Rent | S23: Eff Rent | T23: PSF
C24: =IFERROR(0,0) -> 0 | D24: =IFERROR(E24/12,0) -> 2.5 | E24: =IFERROR(30,0) -> 30 | F24: =IFERROR(Inputs!L6,0) -> 0.03 | G24: =IFERROR(Inputs!L7,0) -> 0.025 | H24: =IFERROR(C24*E24*(1-F24)/12,0) -> 0 | K24: Single | M24: =IFERROR(0/100,0) -> 0 | N24: =IFERROR(+E8+E12+E16+E46,0) -> 0 | O24: =+IFERROR((P8+P12+P16)/N24,0) -> 0 | P24: =+IFERROR(L8/E8,0) -> 0 | Q24: =+IFERROR(P24/O24,0) -> 0 | R24: =+IFERROR((H12+H16)/(E12+E16),0) -> 0 | S24: =+IFERROR((L12+L16)/(E12+E16),0) -> 0 | T24: =IFERROR(+S24/O12,0) -> 0
K25: 1B | M25: =IFERROR(100/100,0) -> 1 | N25: =IFERROR(+E9+E13+E17+E7+E47,0) -> 0 | O25: =+IFERROR((P7+P9+P13+P17)/N25,0) -> 419 | P25: =+IFERROR(L9/E9,0) -> 0 | Q25: =+IFERROR(P25/O25,0) -> 0 | R25: =+IFERROR((H13+H17)/(E13+E17),0) -> 0 | S25: =+IFERROR((L13+L17)/(E13+E17),0) -> 2289 | T25: =IFERROR(+S25/O13,0) -> 5.4630072
C26: Other Income | E26: Unit | F26: Basis | G26: Factor | H26: Total | I26: Growth | K26: 2B | M26: =IFERROR(0/100,0) -> 0 | N26: =IFERROR(+E10+E14+E18+E48,0) -> 0 | O26: =+IFERROR((P10+P14+P18)/N26,0) -> 0 | P26: =+IFERROR(L10/E10,0) -> 0 | Q26: =+IFERROR(P26/O26,0) -> 0 | R26: =+IFERROR((H14+H18)/(E14+E18),0) -> 0 | S26: =+IFERROR((L14+L18)/(E14+E18),0) -> 0 | T26: =IFERROR(+S26/O14,0) -> 0
C27: Parking Income | E27: Spaces | F27: =IFERROR(Inputs!H15,0) -> 224 | G27: =IFERROR(50,0) -> 50 | H27: =IFERROR(G27*F27*(1-N20),0) -> 10864 | I27: =IFERROR(3/100,0) -> 0.03 | K27: 3B | M27: =IFERROR(0/100,0) -> 0 | N27: =IFERROR(+E11+E15+E19+E49,0) -> 0 | O27: =+IFERROR((P11+P15+P19)/N27,0) -> 0 | P27: =+IFERROR(L11/E11,0) -> 0 | Q27: =+IFERROR(P27/O27,0) -> 0 | R27: =+IFERROR((H15+H19)/(E15+E19),0) -> 0 | S27: =+IFERROR((L15+L19)/(E15+E19),0) -> 0 | T27: =IFERROR(+S27/O15,0) -> 0
C28: Electric Reimbursement | E28: =IFERROR(+'(Z+) OpEx'!C14,0) -> Electric | F28: =IFERROR(+'(Z+) OpEx'!E14,0) -> 6921.6 | G28: =IFERROR(0,0) -> 0 | H28: =IFERROR(+F28*G28*(1-$N$20),0) -> 0 | I28: =IFERROR(+'(Z+) OpEx'!J14,0) -> 0.03 | K28: Total | M28: =IFERROR(SUM(M24:M27),0) -> 1 | N28: =IFERROR(+SUM(N24:N27),0) -> 224 | O28: =IFERROR(+P20/N28,0) -> 419 | P28: =+IFERROR(SUM(L8:L11)/SUM(E8:E11),0) -> 0 | Q28: =IFERROR(P28/(SUM(P8:P11)/SUM(E8:E11)),0) -> 0 | R28: =IFERROR(+SUM(H12:H19,H46:H49)/SUM(E12:E19,E46:E49),0) -> 0 | S28: =IFERROR(+SUM(L12:L19,L46:L49)/SUM(E12:E19,E46:E49),0) -> 0 | T28: =IFERROR(+SUM(L12:L19,L46:L49)/(SUM(P12:P19,P46:P49)),0) -> 0
C29: Water/Sewer Reimbursement | E29: =IFERROR(+'(Z+) OpEx'!C15,0) -> Water/Sewer | F29: =IFERROR(+'(Z+) OpEx'!E15,0) -> 6921.6 | G29: =IFERROR(0,0) -> 0 | H29: =IFERROR(+F29*G29*(1-$N$20),0) -> 0 | I29: =IFERROR(+'(Z+) OpEx'!J15,0) -> 0.03
C30: Gas Reimbursement | E30: =IFERROR(+'(Z+) OpEx'!C16,0) -> Gas | F30: =IFERROR(+'(Z+) OpEx'!E16,0) -> 4614.4 | G30: =IFERROR(0,0) -> 0 | H30: =IFERROR(+F30*G30*(1-$N$20),0) -> 0 | I30: =IFERROR(+'(Z+) OpEx'!J16,0) -> 0.03 | K30: Trended(Stabilization) | P30: Market | S30: Restricted
C31: Trash Reimbursement | E31: =IFERROR(+'(Z+) OpEx'!C17,0) -> Trash | F31: =IFERROR(+'(Z+) OpEx'!E17,0) -> 6460.16 | G31: =IFERROR(0,0) -> 0 | H31: =IFERROR(+F31*G31*(1-$N$20),0) -> 0 | I31: =IFERROR(+'(Z+) OpEx'!J17,0) -> 0.03 | K31: Unit Mix Summary | M31: % | N31: # | O31: Avg SF | P31: Rent | Q31: PSF | R31: Base Rent | S31: Eff Rent | T31: PSF
C32: Storage | E32: Sto. Units | F32: =IFERROR(0,0) -> 0 | G32: =IFERROR(50,0) -> 50 | H32: =IFERROR(+G32*F32,0) -> 0 | I32: =IFERROR(3/100,0) -> 0.03 | K32: Single | M32: =IFERROR(M24,0) -> 0 | N32: =IFERROR(+N24,0) -> 0 | O32: =IFERROR(+O24,0) -> 0 | P32: =IFERROR(+P24*Inputs!$F$34,0) -> 0 | Q32: =+IFERROR(P32/O32,0) -> 0 | R32: =IFERROR(+R24*Inputs!$F$34,0) -> 0 | S32: =IFERROR(+S24*INDEX('(Z+) Monthly CF'!$F$9:$HB$9,1,MATCH(Inputs!$D$34,'(Z+) Monthly CF'!$F$5:$HB$5,0)),0) -> 0 | T32: =+IFERROR(S32/O32,0) -> 0
C33: Pet Rent | E33: % of Units | F33: =IFERROR(10/100,0) -> 0.1 | G33: =IFERROR(35,0) -> 35 | H33: =IFERROR(+ROUND(E20*F33,0)*G33,0) -> 770 | I33: =IFERROR(+M20,0) -> 0.025 | K33: 1B | M33: =IFERROR(M25,0) -> 1 | N33: =IFERROR(+N25,0) -> 224 | O33: =IFERROR(+O25,0) -> 419 | P33: =IFERROR(+P25*Inputs!$F$34,0) -> 0 | Q33: =+IFERROR(P33/O33,0) -> 0 | R33: =IFERROR(+R25*Inputs!$F$34,0) -> 0 | S33: =IFERROR(+S25*INDEX('(Z+) Monthly CF'!$F$9:$HB$9,1,MATCH(Inputs!$D$34,'(Z+) Monthly CF'!$F$5:$HB$5,0)),0) -> 2444.7968 | T33: =+IFERROR(S33/O33,0) -> 5.8348372
C34: Laundry | E34: Units | F34: =IFERROR(+E20,0) -> 224 | G34: =IFERROR(10,0) -> 10 | H34: =IFERROR(+F34*G34*(1-$N$20),0) -> 2172.8 | I34: =IFERROR(3/100,0) -> 0.03 | K34: 2B | M34: =IFERROR(M26,0) -> 0 | N34: =IFERROR(+N26,0) -> 0 | O34: =IFERROR(+O26,0) -> 0 | P34: =IFERROR(+P26*Inputs!$F$34,0) -> 0 | Q34: =+IFERROR(P34/O34,0) -> 0 | R34: =IFERROR(+R26*Inputs!$F$34,0) -> 0 | S34: =IFERROR(+S26*INDEX('(Z+) Monthly CF'!$F$9:$HB$9,1,MATCH(Inputs!$D$34,'(Z+) Monthly CF'!$F$5:$HB$5,0)),0) -> 0 | T34: =+IFERROR(S34/O34,0) -> 0
C35: ICMS Subsidy | E35: ICMS Exp. | F35: =IFERROR(+'(Z+) OpEx'!E24,0) -> 41529.6 | G35: =IFERROR(50/100,0) -> 0.5 | H35: =IFERROR((+G35*F35)/100,0) -> 207.648 | I35: =IFERROR(0/100,0) -> 0 | K35: 3B | M35: =IFERROR(M27,0) -> 0 | N35: =IFERROR(+N27,0) -> 0 | O35: =IFERROR(+O27,0) -> 0 | P35: =IFERROR(+P27*Inputs!$F$34,0) -> 0 | Q35: =+IFERROR(P35/O35,0) -> 0 | R35: =IFERROR(+R27*Inputs!$F$34,0) -> 0 | S35: =IFERROR(+S27*INDEX('(Z+) Monthly CF'!$F$9:$HB$9,1,MATCH(Inputs!$D$34,'(Z+) Monthly CF'!$F$5:$HB$5,0)),0) -> 0 | T35: =+IFERROR(S35/O35,0) -> 0
C36: Total Other Income | H36: =IFERROR(+SUM(H27:H35),0) -> 14014.448 | I36: =IFERROR(+SUMPRODUCT(I27:I35,H27:H35)/SUM(H27:H35),0) -> 0.029280782 | K36: Total | M36: =IFERROR(SUM(M32:M35),0) -> 1 | N36: =IFERROR(+SUM(N32:N35),0) -> 224 | O36: =IFERROR(+O28,0) -> 419 | P36: =+IFERROR(SUM(L8:L11)/SUM(E8:E11),0)*Inputs!$F$34 -> 0 | Q36: =+P36/(SUM(O16:O19)/SUM(E16:E19)) -> 0 | R36: =IFERROR(+SUM(H12:H19,H46:H49)/SUM(E12:E19,E46:E49)*Inputs!$F$34,0) -> 0 | S36: =IFERROR(+SUM(L12:L19,L46:L49)/SUM(E12:E19,E46:E49)*Inputs!$F$34,0) -> 0 | T36: =+IFERROR(S36/O36,0) -> 5.8348372
C38: Payroll Expense | E38: Quantity | F38: Hourly | G38: Annual | H38: Bonus | I38: Load | J38: Total
C39: Full-Time Manager | E39: =IFERROR(0.5,0) -> 0.5 | F39: =IFERROR(35,0) -> 35 | G39: =IFERROR(+F39*52*40,0) -> 72800 | H39: =IFERROR(10/100,0) -> 0.1 | I39: =IFERROR(20/100,0) -> 0.2 | J39: =IFERROR(+G39*(1+H39)*(1+I39)*E39,0) -> 48048
C40: Assistant Manager | E40: =IFERROR(0.5,0) -> 0.5 | F40: =IFERROR(22,0) -> 22 | G40: =IFERROR(+F40*52*40,0) -> 45760 | H40: =IFERROR(5/100,0) -> 0.05 | I40: =IFERROR(20/100,0) -> 0.2 | J40: =IFERROR(+G40*(1+H40)*(1+I40)*E40,0) -> 28828.8
C41: Maintenance Tech | E41: =IFERROR(0.5,0) -> 0.5 | F41: =IFERROR(29,0) -> 29 | G41: =IFERROR(+F41*52*40,0) -> 60320 | H41: =IFERROR(10/100,0) -> 0.1 | I41: =IFERROR(20/100,0) -> 0.2 | J41: =IFERROR(+G41*(1+H41)*(1+I41)*E41,0) -> 39811.2
C42: Full-Time Leasing | E42: =IFERROR(0.5,0) -> 0.5 | F42: =IFERROR(18,0) -> 18 | G42: =IFERROR(+F42*52*40,0) -> 37440 | H42: =IFERROR(5/100,0) -> 0.05 | I42: =IFERROR(20/100,0) -> 0.2 | J42: =IFERROR(+G42*(1+H42)*(1+I42)*E42,0) -> 23587.2
C43: Total | J43: =IFERROR(+SUM(J39:J42),0) -> 140275.2
C46: Restricted Tier C 0BR | D46: =IFERROR(1,0) -> 1 | E46: =IFERROR(0,0) -> 0 | F46: =IFERROR(0,0) -> 0 | G46: =IFERROR(0,0) -> 0 | H46: =IFERROR(G46*E46,0) -> 0 | I46: =IFERROR(0,0) -> 0 | J46: =IFERROR(100/100,0) -> 1 | K46: =IFERROR((I46-G46)*J46+G46,0) -> 0 | L46: =IFERROR(K46*E46,0) -> 0 | M46: =IFERROR(+Inputs!$L$7,0) -> 0.025 | N46: =IFERROR(+Inputs!$L$6,0) -> 0.03 | O46: =IFERROR(O8,0) -> 0 | P46: =IFERROR(O46*E46,0) -> 0 | Q46: =IFERROR(K46/O46,0) -> 0 | R46: =IFERROR(100,0) -> 100 | S46: =IFERROR(R46*E46,0) -> 0
C47: Restricted Tier C 1BR | D47: =IFERROR(0,0) -> 0 | E47: =IFERROR(0,0) -> 0 | F47: =IFERROR(0,0) -> 0 | G47: =IFERROR(0,0) -> 0 | H47: =IFERROR(G47*E47,0) -> 0 | I47: =IFERROR(0,0) -> 0 | J47: =IFERROR(100/100,0) -> 1 | K47: =IFERROR((I47-G47)*J47+G47,0) -> 0 | L47: =IFERROR(K47*E47,0) -> 0 | M47: =IFERROR(+Inputs!$L$7,0) -> 0.025 | N47: =IFERROR(+Inputs!$L$6,0) -> 0.03 | O47: =IFERROR(O9,0) -> 0 | P47: =IFERROR(O47*E47,0) -> 0 | Q47: =IFERROR(K47/O47,0) -> 0 | R47: =IFERROR(100,0) -> 100 | S47: =IFERROR(R47*E47,0) -> 0
C48: Restricted Tier C 2BR | D48: =IFERROR(2,0) -> 2 | E48: =IFERROR(0,0) -> 0 | F48: =IFERROR(0,0) -> 0 | G48: =IFERROR(0,0) -> 0 | H48: =IFERROR(G48*E48,0) -> 0 | I48: =IFERROR(0,0) -> 0 | J48: =IFERROR(100/100,0) -> 1 | K48: =IFERROR((I48-G48)*J48+G48,0) -> 0 | L48: =IFERROR(K48*E48,0) -> 0 | M48: =IFERROR(+Inputs!$L$7,0) -> 0.025 | N48: =IFERROR(+Inputs!$L$6,0) -> 0.03 | O48: =IFERROR(O10,0) -> 0 | P48: =IFERROR(O48*E48,0) -> 0 | Q48: =IFERROR(K48/O48,0) -> 0 | R48: =IFERROR(100,0) -> 100 | S48: =IFERROR(R48*E48,0) -> 0
C49: Restricted Tier C 3BR | D49: =IFERROR(3,0) -> 3 | E49: =IFERROR(0,0) -> 0 | F49: =IFERROR(0,0) -> 0 | G49: =IFERROR(0,0) -> 0 | H49: =IFERROR(G49*E49,0) -> 0 | I49: =IFERROR(0,0) -> 0 | J49: =IFERROR(100/100,0) -> 1 | K49: =IFERROR((I49-G49)*J49+G49,0) -> 0 | L49: =IFERROR(K49*E49,0) -> 0 | M49: =IFERROR(+Inputs!$L$7,0) -> 0.025 | N49: =IFERROR(+Inputs!$L$6,0) -> 0.03 | O49: =IFERROR(O11,0) -> 0 | P49: =IFERROR(O49*E49,0) -> 0 | Q49: =IFERROR(K49/O49,0) -> 0 | R49: =IFERROR(100,0) -> 100 | S49: =IFERROR(R49*E49,0) -> 0

Sheet (Z+) Monthly CF
A1: 2828 STANFORD AVE, LOS ANGELES CA, 90011-2018
A2: Monthly Cash Flow
D3: Totals
A4: Date | F4: =+EOMONTH(Inputs!E20,0) -> 46387 | G4: =EOMONTH($F$4, 1) -> 46418 | H4: =EOMONTH($G$4, 1) -> 46446 | I4: =EOMONTH($H$4, 1) -> 46477 | J4: =EOMONTH($I$4, 1) -> 46507 | K4: =EOMONTH($J$4, 1) -> 46538 | L4: =EOMONTH($K$4, 1) -> 46568 | M4: =EOMONTH($L$4, 1) -> 46599 | N4: =EOMONTH($M$4, 1) -> 46630 | O4: =EOMONTH($N$4, 1) -> 46660 | P4: =EOMONTH($O$4, 1) -> 46691 | Q4: =EOMONTH($P$4, 1) -> 46721 | R4: =EOMONTH($Q$4, 1) -> 46752 | S4: =EOMONTH($R$4, 1) -> 46783 | T4: =EOMONTH($S$4, 1) -> 46812 | U4: =EOMONTH($T$4, 1) -> 46843 | V4: =EOMONTH($U$4, 1) -> 46873 | W4: =EOMONTH($V$4, 1) -> 46904 | X4: =EOMONTH($W$4, 1) -> 46934 | Y4: =EOMONTH($X$4, 1) -> 46965 | Z4: =EOMONTH($Y$4, 1) -> 46996 | AA4: =EOMONTH($Z$4, 1) -> 47026 | AB4: =EOMONTH($AA$4, 1) -> 47057 | AC4: =EOMONTH($AB$4, 1) -> 47087 | AD4: =EOMONTH($AC$4, 1) -> 47118 | AE4: =EOMONTH($AD$4, 1) -> 47149 | AF4: =EOMONTH($AE$4, 1) -> 47177 | AG4: =EOMONTH($AF$4, 1) -> 47208 | AH4: =EOMONTH($AG$4, 1) -> 47238 | AI4: =EOMONTH($AH$4, 1) -> 47269 | AJ4: =EOMONTH($AI$4, 1) -> 47299 | AK4: =EOMONTH($AJ$4, 1) -> 47330 | AL4: =EOMONTH($AK$4, 1) -> 47361 | AM4: =EOMONTH($AL$4, 1) -> 47391 | AN4: =EOMONTH($AM$4, 1) -> 47422 | AO4: =EOMONTH($AN$4, 1) -> 47452 | AP4: =EOMONTH($AO$4, 1) -> 47483 | AQ4: =EOMONTH($AP$4, 1) -> 47514 | AR4: =EOMONTH($AQ$4, 1) -> 47542 | AS4: =EOMONTH($AR$4, 1) -> 47573 | AT4: =EOMONTH($AS$4, 1) -> 47603 | AU4: =EOMONTH($AT$4, 1) -> 47634 | AV4: =EOMONTH($AU$4, 1) -> 47664 | AW4: =EOMONTH($AV$4, 1) -> 47695 | AX4: =EOMONTH($AW$4, 1) -> 47726 | AY4: =EOMONTH($AX$4, 1) -> 47756 | AZ4: =EOMONTH($AY$4, 1) -> 47787 | BA4: =EOMONTH($AZ$4, 1) -> 47817 | BB4: =EOMONTH($BA$4, 1) -> 47848 | BC4: =EOMONTH($BB$4, 1) -> 47879 | BD4: =EOMONTH($BC$4, 1) -> 47907 | BE4: =EOMONTH($BD$4, 1) -> 47938 | BF4: =EOMONTH($BE$4, 1) -> 47968 | BG4: =EOMONTH($BF$4, 1) -> 47999 | BH4: =EOMONTH($BG$4, 1) -> 48029 | BI4: =EOMONTH($BH$4, 1) -> 48060 | BJ4: =EOMONTH($BI$4, 1) -> 48091 | BK4: =EOMONTH($BJ$4, 1) -> 48121 | BL4: =EOMONTH($BK$4, 1) -> 48152 | BM4: =EOMONTH($BL$4, 1) -> 48182 | BN4: =EOMONTH($BM$4, 1) -> 48213 | BO4: =EOMONTH($BN$4, 1) -> 48244 | BP4: =EOMONTH($BO$4, 1) -> 48273 | BQ4: =EOMONTH($BP$4, 1) -> 48304 | BR4: =EOMONTH($BQ$4, 1) -> 48334 | BS4: =EOMONTH($BR$4, 1) -> 48365 | BT4: =EOMONTH($BS$4, 1) -> 48395 | BU4: =EOMONTH($BT$4, 1) -> 48426 | BV4: =EOMONTH($BU$4, 1) -> 48457 | BW4: =EOMONTH($BV$4, 1) -> 48487 | BX4: =EOMONTH($BW$4, 1) -> 48518 | BY4: =EOMONTH($BX$4, 1) -> 48548 | BZ4: =EOMONTH($BY$4, 1) -> 48579 | CA4: =EOMONTH($BZ$4, 1) -> 48610 | CB4: =EOMONTH($CA$4, 1) -> 48638 | CC4: =EOMONTH($CB$4, 1) -> 48669 | CD4: =EOMONTH($CC$4, 1) -> 48699 | CE4: =EOMONTH($CD$4, 1) -> 48730 | CF4: =EOMONTH($CE$4, 1) -> 48760 | CG4: =EOMONTH($CF$4, 1) -> 48791 | CH4: =EOMONTH($CG$4, 1) -> 48822 | CI4: =EOMONTH($CH$4, 1) -> 48852 | CJ4: =EOMONTH($CI$4, 1) -> 48883 | CK4: =EOMONTH($CJ$4, 1) -> 48913 | CL4: =EOMONTH($CK$4, 1) -> 48944 | CM4: =EOMONTH($CL$4, 1) -> 48975 | CN4: =EOMONTH($CM$4, 1) -> 49003 | CO4: =EOMONTH($CN$4, 1) -> 49034 | CP4: =EOMONTH($CO$4, 1) -> 49064 | CQ4: =EOMONTH($CP$4, 1) -> 49095 | CR4: =EOMONTH($CQ$4, 1) -> 49125 | CS4: =EOMONTH($CR$4, 1) -> 49156 | CT4: =EOMONTH($CS$4, 1) -> 49187 | CU4: =EOMONTH($CT$4, 1) -> 49217 | CV4: =EOMONTH($CU$4, 1) -> 49248 | CW4: =EOMONTH($CV$4, 1) -> 49278 | CX4: =EOMONTH($CW$4, 1) -> 49309 | CY4: =EOMONTH($CX$4, 1) -> 49340 | CZ4: =EOMONTH($CY$4, 1) -> 49368 | DA4: =EOMONTH($CZ$4, 1) -> 49399 | DB4: =EOMONTH($DA$4, 1) -> 49429 | DC4: =EOMONTH($DB$4, 1) -> 49460 | DD4: =EOMONTH($DC$4, 1) -> 49490 | DE4: =EOMONTH($DD$4, 1) -> 49521 | DF4: =EOMONTH($DE$4, 1) -> 49552 | DG4: =EOMONTH($DF$4, 1) -> 49582 | DH4: =EOMONTH($DG$4, 1) -> 49613 | DI4: =EOMONTH($DH$4, 1) -> 49643 | DJ4: =EOMONTH($DI$4, 1) -> 49674 | DK4: =EOMONTH($DJ$4, 1) -> 49705 | DL4: =EOMONTH($DK$4, 1) -> 49734 | DM4: =EOMONTH(DL4, 1) -> 49765 | DN4: =EOMONTH(DM4, 1) -> 49795 | DO4: =EOMONTH(DN4, 1) -> 49826 | DP4: =EOMONTH(DO4, 1) -> 49856 | DQ4: =EOMONTH(DP4, 1) -> 49887 | DR4: =EOMONTH(DQ4, 1) -> 49918 | DS4: =EOMONTH(DR4, 1) -> 49948 | DT4: =EOMONTH(DS4, 1) -> 49979 | DU4: =EOMONTH(DT4, 1) -> 50009
A5: Month | F5: 1 | G5: =F5+1 -> 2 | H5: =G5+1 -> 3 | I5: =H5+1 -> 4 | J5: =I5+1 -> 5 | K5: =J5+1 -> 6 | L5: =K5+1 -> 7 | M5: =L5+1 -> 8 | N5: =M5+1 -> 9 | ... DU5: =DT5+1 -> 120
A6: Year | F6: =ROUNDUP(F5/12,0) -> 1 | G6: =ROUNDUP(G5/12,0) -> 1 | H6: =ROUNDUP(H5/12,0) -> 1 | I6: =ROUNDUP(I5/12,0) -> 1 | J6: =ROUNDUP(J5/12,0) -> 1 | K6: =ROUNDUP(K5/12,0) -> 1 | L6: =ROUNDUP(L5/12,0) -> 1 | M6: =ROUNDUP(M5/12,0) -> 1 | ... DU6: =ROUNDUP(DU5/12,0) -> 10
A7: Calendar Year | F7: =+YEAR(F4) -> 2026 | G7: =+YEAR(G4) -> 2027 | H7: =+YEAR(H4) -> 2027 | I7: =+YEAR(I4) -> 2027 | J7: =+YEAR(J4) -> 2027 | K7: =+YEAR(K4) -> 2027 | L7: =+YEAR(L4) -> 2027 | M7: =+YEAR(M4) -> 2027 | ... DU7: =+YEAR(DU4) -> 2036
A9: Rent Growth Factor | F9: =+IFERROR(IF(AND(F5>=Inputs!$L$10,F5<Inputs!$D$29),(1+Inputs!$L$7)^(('(Z+) Monthly CF'!F5-Inputs!$L$10)/12),IF(F5>=Inputs!$D$29,E9*((1+Inputs!$L$7)^(1/12)),1)),0) -> 1 | G9: =+IFERROR(IF(AND(G5>=Inputs!$L$10,G5<Inputs!$D$29),(1+Inputs!$L$7)^(('(Z+) Monthly CF'!G5-Inputs!$L$10)/12),IF(G5>=Inputs!$D$29,F9*((1+Inputs!$L$7)^(1/12)),1)),0) -> 1.0020598 | H9: =+IFERROR(IF(AND(H5>=Inputs!$L$10,H5<Inputs!$D$29),(1+Inputs!$L$7)^(('(Z+) Monthly CF'!H5-Inputs!$L$10)/12),IF(H5>=Inputs!$D$29,G9*((1+Inputs!$L$7)^(1/12)),1)),0) -> 1.0041239 | I9: =+IFERROR(IF(AND(I5>=Inputs!$L$10,I5<Inputs!$D$29),(1+Inputs!$L$7)^(('(Z+) Monthly CF'!I5-Inputs!$L$10)/12),IF(I5>=Inputs!$D$29,H9*((1+Inputs!$L$7)^(1/12)),1)),0) -> 1.0061922 | J9: =+IFERROR(IF(AND(J5>=Inputs!$L$10,J5<Inputs!$D$29),(1+Inputs!$L$7)^(('(Z+) Monthly CF'!J5-Inputs!$L$10)/12),IF(J5>=Inputs!$D$29,I9*((1+Inputs!$L$7)^(1/12)),1)),0) -> 1.0082648 | K9: =+IFERROR(IF(AND(K5>=Inputs!$L$10,K5<Inputs!$D$29),(1+Inputs!$L$7)^(('(Z+) Monthly CF'!K5-Inputs!$L$10)/12),IF(K5>=Inputs!$D$29,J9*((1+Inputs!$L$7)^(1/12)),1)),0) -> 1.0103417 | L9: =+IFERROR(IF(AND(L5>=Inputs!$L$10,L5<Inputs!$D$29),(1+Inputs!$L$7)^(('(Z+) Monthly CF'!L5-Inputs!$L$10)/12),IF(L5>=Inputs!$D$29,K9*((1+Inputs!$L$7)^(1/12)),1)),0) -> 1.0124228 | M9: =+IFERROR(IF(AND(M5>=Inputs!$L$10,M5<Inputs!$D$29),(1+Inputs!$L$7)^(('(Z+) Monthly CF'!M5-Inputs!$L$10)/12),IF(M5>=Inputs!$D$29,L9*((1+Inputs!$L$7)^(1/12)),1)),0) -> 1.0145083 | ... DU9: =+IFERROR(IF(AND(DU5>=Inputs!$L$10,DU5<Inputs!$D$29),(1+Inputs!$L$7)^(('(Z+) Monthly CF'!DU5-Inputs!$L$10)/12),IF(DU5>=Inputs!$D$29,DT9*((1+Inputs!$L$7)^(1/12)),1)),0) -> 1.2774532
A10: Expense Growth Factor | F10: =+IFERROR(IF(AND(F5>=Inputs!$L$10,F5<Inputs!$D$29),(1+'(Z+) OpEx'!$I$27)^(('(Z+) Monthly CF'!F5-Inputs!$L$10)/12),IF(F5>=Inputs!$D$29,E10*((1+'(Z+) OpEx'!$J$27)^(1/12)),1)),0) -> 1 | G10: =+IFERROR(IF(AND(G5>=Inputs!$L$10,G5<Inputs!$D$29),(1+'(Z+) OpEx'!$I$27)^(('(Z+) Monthly CF'!G5-Inputs!$L$10)/12),IF(G5>=Inputs!$D$29,F10*((1+'(Z+) OpEx'!$J$27)^(1/12)),1)),0) -> 1.0024663 | H10: =+IFERROR(IF(AND(H5>=Inputs!$L$10,H5<Inputs!$D$29),(1+'(Z+) OpEx'!$I$27)^(('(Z+) Monthly CF'!H5-Inputs!$L$10)/12),IF(H5>=Inputs!$D$29,G10*((1+'(Z+) OpEx'!$J$27)^(1/12)),1)),0) -> 1.0049386 | I10: =+IFERROR(IF(AND(I5>=Inputs!$L$10,I5<Inputs!$D$29),(1+'(Z+) OpEx'!$I$27)^(('(Z+) Monthly CF'!I5-Inputs!$L$10)/12),IF(I5>=Inputs!$D$29,H10*((1+'(Z+) OpEx'!$J$27)^(1/12)),1)),0) -> 1.0074171 | J10: =+IFERROR(IF(AND(J5>=Inputs!$L$10,J5<Inputs!$D$29),(1+'(Z+) OpEx'!$I$27)^(('(Z+) Monthly CF'!J5-Inputs!$L$10)/12),IF(J5>=Inputs!$D$29,I10*((1+'(Z+) OpEx'!$J$27)^(1/12)),1)),0) -> 1.0099016 | K10: =+IFERROR(IF(AND(K5>=Inputs!$L$10,K5<Inputs!$D$29),(1+'(Z+) OpEx'!$I$27)^(('(Z+) Monthly CF'!K5-Inputs!$L$10)/12),IF(K5>=Inputs!$D$29,J10*((1+'(Z+) OpEx'!$J$27)^(1/12)),1)),0) -> 1.0123923 | L10: =+IFERROR(IF(AND(L5>=Inputs!$L$10,L5<Inputs!$D$29),(1+'(Z+) OpEx'!$I$27)^(('(Z+) Monthly CF'!L5-Inputs!$L$10)/12),IF(L5>=Inputs!$D$29,K10*((1+'(Z+) OpEx'!$J$27)^(1/12)),1)),0) -> 1.0148892 | M10: =+IFERROR(IF(AND(M5>=Inputs!$L$10,M5<Inputs!$D$29),(1+'(Z+) OpEx'!$I$27)^(('(Z+) Monthly CF'!M5-Inputs!$L$10)/12),IF(M5>=Inputs!$D$29,L10*((1+'(Z+) OpEx'!$J$27)^(1/12)),1)),0) -> 1.0173921 | ... DU10: =+IFERROR(IF(AND(DU5>=Inputs!$L$10,DU5<Inputs!$D$29),(1+'(Z+) OpEx'!$I$27)^(('(Z+) Monthly CF'!DU5-Inputs!$L$10)/12),IF(DU5>=Inputs!$D$29,DT10*((1+'(Z+) OpEx'!$J$27)^(1/12)),1)),0) -> 1.3337224
A11: Chunk Rent | F11: =+IFERROR(IF(AND(F5>=Inputs!$L$10,F5<Inputs!$D$29),'(Z+) Rent Roll'!$K$20*(1+Inputs!$L$7)^(('(Z+) Monthly CF'!F5-Inputs!$L$10)/12),IF(F5>=Inputs!$D$29,E11*((1+Inputs!$L$7)^(1/12)),'(Z+) Rent Roll'!$K$20)),0) -> 2289 | G11: =+IFERROR(IF(AND(G5>=Inputs!$L$10,F5<Inputs!$D$29),'(Z+) Rent Roll'!$K$20*(1+Inputs!$L$7)^(('(Z+) Monthly CF'!F5-Inputs!$L$10)/12),IF(G5>=Inputs!$D$29,F11*((1+Inputs!$L$7)^(1/12)),'(Z+) Rent Roll'!$K$20)),0) -> 2289 | H11: =+IFERROR(IF(AND(H5>=Inputs!$L$10,F5<Inputs!$D$29),'(Z+) Rent Roll'!$K$20*(1+Inputs!$L$7)^(('(Z+) Monthly CF'!F5-Inputs!$L$10)/12),IF(H5>=Inputs!$D$29,G11*((1+Inputs!$L$7)^(1/12)),'(Z+) Rent Roll'!$K$20)),0) -> 2289 | I11: =+IFERROR(IF(AND(I5>=Inputs!$L$10,F5<Inputs!$D$29),'(Z+) Rent Roll'!$K$20*(1+Inputs!$L$7)^(('(Z+) Monthly CF'!F5-Inputs!$L$10)/12),IF(I5>=Inputs!$D$29,H11*((1+Inputs!$L$7)^(1/12)),'(Z+) Rent Roll'!$K$20)),0) -> 2289 | J11: =+IFERROR(IF(AND(J5>=Inputs!$L$10,F5<Inputs!$D$29),'(Z+) Rent Roll'!$K$20*(1+Inputs!$L$7)^(('(Z+) Monthly CF'!F5-Inputs!$L$10)/12),IF(J5>=Inputs!$D$29,I11*((1+Inputs!$L$7)^(1/12)),'(Z+) Rent Roll'!$K$20)),0) -> 2289 | K11: =+IFERROR(IF(AND(K5>=Inputs!$L$10,F5<Inputs!$D$29),'(Z+) Rent Roll'!$K$20*(1+Inputs!$L$7)^(('(Z+) Monthly CF'!F5-Inputs!$L$10)/12),IF(K5>=Inputs!$D$29,J11*((1+Inputs!$L$7)^(1/12)),'(Z+) Rent Roll'!$K$20)),0) -> 2289 | L11: =+IFERROR(IF(AND(L5>=Inputs!$L$10,F5<Inputs!$D$29),'(Z+) Rent Roll'!$K$20*(1+Inputs!$L$7)^(('(Z+) Monthly CF'!F5-Inputs!$L$10)/12),IF(L5>=Inputs!$D$29,K11*((1+Inputs!$L$7)^(1/12)),'(Z+) Rent Roll'!$K$20)),0) -> 2289 | M11: =+IFERROR(IF(AND(M5>=Inputs!$L$10,F5<Inputs!$D$29),'(Z+) Rent Roll'!$K$20*(1+Inputs!$L$7)^(('(Z+) Monthly CF'!F5-Inputs!$L$10)/12),IF(M5>=Inputs!$D$29,L11*((1+Inputs!$L$7)^(1/12)),'(Z+) Rent Roll'!$K$20)),0) -> 2289 | N11: =+IFERROR(IF(AND(N5>=Inputs!$L$10,F5<Inputs!$D$29),'(Z+) Rent Roll'!$K$20*(1+Inputs!$L$7)^(('(Z+) Monthly CF'!F5-Inputs!$L$10)/12),IF(N5>=Inputs!$D$29,M11*((1+Inputs!$L$7)^(1/12)),'(Z+) Rent Roll'!$K$20)),0) -> 2289 | O11: =+IFERROR(IF(AND(O5>=Inputs!$L$10,F5<Inputs!$D$29),'(Z+) Rent Roll'!$K$20*(1+Inputs!$L$7)^(('(Z+) Monthly CF'!F5-Inputs!$L$10)/12),IF(O5>=Inputs!$D$29,N11*((1+Inputs!$L$7)^(1/12)),'(Z+) Rent Roll'!$K$20)),0) -> 2289 | P11: =+IFERROR(IF(AND(P5>=Inputs!$L$10,F5<Inputs!$D$29),'(Z+) Rent Roll'!$K$20*(1+Inputs!$L$7)^(('(Z+) Monthly CF'!F5-Inputs!$L$10)/12),IF(P5>=Inputs!$D$29,O11*((1+Inputs!$L$7)^(1/12)),'(Z+) Rent Roll'!$K$20)),0) -> 2289 | Q11: =+IFERROR(IF(AND(Q5>=Inputs!$L$10,F5<Inputs!$D$29),'(Z+) Rent Roll'!$K$20*(1+Inputs!$L$7)^(('(Z+) Monthly CF'!F5-Inputs!$L$10)/12),IF(Q5>=Inputs!$D$29,P11*((1+Inputs!$L$7)^(1/12)),'(Z+) Rent Roll'!$K$20)),0) -> 2289 | R11: =+IFERROR(IF(AND(R5>=Inputs!$L$10,F5<Inputs!$D$29),'(Z+) Rent Roll'!$K$20*(1+Inputs!$L$7)^(('(Z+) Monthly CF'!F5-Inputs!$L$10)/12),IF(R5>=Inputs!$D$29,Q11*((1+Inputs!$L$7)^(1/12)),'(Z+) Rent Roll'!$K$20)),0) -> 2289 | S11: =+IFERROR(IF(AND(S5>=Inputs!$L$10,F5<Inputs!$D$29),'(Z+) Rent Roll'!$K$20*(1+Inputs!$L$7)^(('(Z+) Monthly CF'!F5-Inputs!$L$10)/12),IF(S5>=Inputs!$D$29,R11*((1+Inputs!$L$7)^(1/12)),'(Z+) Rent Roll'!$K$20)),0) -> 2289 | T11: =+IFERROR(IF(AND(T5>=Inputs!$L$10,F5<Inputs!$D$29),'(Z+) Rent Roll'!$K$20*(1+Inputs!$L$7)^(('(Z+) Monthly CF'!F5-Inputs!$L$10)/12),IF(T5>=Inputs!$D$29,S11*((1+Inputs!$L$7)^(1/12)),'(Z+) Rent Roll'!$K$20)),0) -> 2289 | U11: =+IFERROR(IF(AND(U5>=Inputs!$L$10,F5<Inputs!$D$29),'(Z+) Rent Roll'!$K$20*(1+Inputs!$L$7)^(('(Z+) Monthly CF'!F5-Inputs!$L$10)/12),IF(U5>=Inputs!$D$29,T11*((1+Inputs!$L$7)^(1/12)),'(Z+) Rent Roll'!$K$20)),0) -> 2289 | V11: =+IFERROR(IF(AND(V5>=Inputs!$L$10,F5<Inputs!$D$29),'(Z+) Rent Roll'!$K$20*(1+Inputs!$L$7)^(('(Z+) Monthly CF'!F5-Inputs!$L$10)/12),IF(V5>=Inputs!$D$29,U11*((1+Inputs!$L$7)^(1/12)),'(Z+) Rent Roll'!$K$20)),0) -> 2289 | W11: =+IFERROR(IF(AND(W5>=Inputs!$L$10,F5<Inputs!$D$29),'(Z+) Rent Roll'!$K$20*(1+Inputs!$L$7)^(('(Z+) Monthly CF'!F5-Inputs!$L$10)/12),IF(W5>=Inputs!$D$29,V11*((1+Inputs!$L$7)^(1/12)),'(Z+) Rent Roll'!$K$20)),0) -> 2289 | X11: =+IFERROR(IF(AND(X5>=Inputs!$L$10,F5<Inputs!$D$29),'(Z+) Rent Roll'!$K$20*(1+Inputs!$L$7)^(('(Z+) Monthly CF'!F5-Inputs!$L$10)/12),IF(X5>=Inputs!$D$29,W11*((1+Inputs!$L$7)^(1/12)),'(Z+) Rent Roll'!$K$20)),0) -> 2289 | Y11: =+IFERROR(IF(AND(Y5>=Inputs!$L$10,F5<Inputs!$D$29),'(Z+) Rent Roll'!$K$20*(1+Inputs!$L$7)^(('(Z+) Monthly CF'!F5-Inputs!$L$10)/12),IF(Y5>=Inputs!$D$29,X11*((1+Inputs!$L$7)^(1/12)),'(Z+) Rent Roll'!$K$20)),0) -> 2289 | Z11: =+IFERROR(IF(AND(Z5>=Inputs!$L$10,F5<Inputs!$D$29),'(Z+) Rent Roll'!$K$20*(1+Inputs!$L$7)^(('(Z+) Monthly CF'!F5-Inputs!$L$10)/12),IF(Z5>=Inputs!$D$29,Y11*((1+Inputs!$L$7)^(1/12)),'(Z+) Rent Roll'!$K$20)),0) -> 2289 | AA11: =+IFERROR(IF(AND(AA5>=Inputs!$L$10,F5<Inputs!$D$29),'(Z+) Rent Roll'!$K$20*(1+Inputs!$L$7)^(('(Z+) Monthly CF'!F5-Inputs!$L$10)/12),IF(AA5>=Inputs!$D$29,Z11*((1+Inputs!$L$7)^(1/12)),'(Z+) Rent Roll'!$K$20)),0) -> 2289 | AB11: =+IFERROR(IF(AND(AB5>=Inputs!$L$10,F5<Inputs!$D$29),'(Z+) Rent Roll'!$K$20*(1+Inputs!$L$7)^(('(Z+) Monthly CF'!F5-Inputs!$L$10)/12),IF(AB5>=Inputs!$D$29,AA11*((1+Inputs!$L$7)^(1/12)),'(Z+) Rent Roll'!$K$20)),0) -> 2289 | AC11: =+IFERROR(IF(AND(AC5>=Inputs!$L$10,F5<Inputs!$D$29),'(Z+) Rent Roll'!$K$20*(1+Inputs!$L$7)^(('(Z+) Monthly CF'!F5-Inputs!$L$10)/12),IF(AC5>=Inputs!$D$29,AB11*((1+Inputs!$L$7)^(1/12)),'(Z+) Rent Roll'!$K$20)),0) -> 2289 | AD11: =+IFERROR(IF(AND(AD5>=Inputs!$L$10,F5<Inputs!$D$29),'(Z+) Rent Roll'!$K$20*(1+Inputs!$L$7)^(('(Z+) Monthly CF'!F5-Inputs!$L$10)/12),IF(AD5>=Inputs!$D$29,AC11*((1+Inputs!$L$7)^(1/12)),'(Z+) Rent Roll'!$K$20)),0) -> 2289 | AE11: =+IFERROR(IF(AND(AE5>=Inputs!$L$10,F5<Inputs!$D$29),'(Z+) Rent Roll'!$K$20*(1+Inputs!$L$7)^(('(Z+) Monthly CF'!F5-Inputs!$L$10)/12),IF(AE5>=Inputs!$D$29,AD11*((1+Inputs!$L$7)^(1/12)),'(Z+) Rent Roll'!$K$20)),0) -> 2289 | AF11: =+IFERROR(IF(AND(AF5>=Inputs!$L$10,F5<Inputs!$D$29),'(Z+) Rent Roll'!$K$20*(1+Inputs!$L$7)^(('(Z+) Monthly CF'!F5-Inputs!$L$10)/12),IF(AF5>=Inputs!$D$29,AE11*((1+Inputs!$L$7)^(1/12)),'(Z+) Rent Roll'!$K$20)),0) -> 2289 | AG11: =+IFERROR(IF(AND(AG5>=Inputs!$L$10,F5<Inputs!$D$29),'(Z+) Rent Roll'!$K$20*(1+Inputs!$L$7)^(('(Z+) Monthly CF'!F5-Inputs!$L$10)/12),IF(AG5>=Inputs!$D$29,AF11*((1+Inputs!$L$7)^(1/12)),'(Z+) Rent Roll'!$K$20)),0) -> 2289 | AH11: =+IFERROR(IF(AND(AH5>=Inputs!$L$10,F5<Inputs!$D$29),'(Z+) Rent Roll'!$K$20*(1+Inputs!$L$7)^(('(Z+) Monthly CF'!F5-Inputs!$L$10)/12),IF(AH5>=Inputs!$D$29,AG11*((1+Inputs!$L$7)^(1/12)),'(Z+) Rent Roll'!$K$20)),0) -> 2289 | AI11: =+IFERROR(IF(AND(AI5>=Inputs!$L$10,F5<Inputs!$D$29),'(Z+) Rent Roll'!$K$20*(1+Inputs!$L$7)^(('(Z+) Monthly CF'!F5-Inputs!$L$10)/12),IF(AI5>=Inputs!$D$29,AH11*((1+Inputs!$L$7)^(1/12)),'(Z+) Rent Roll'!$K$20)),0) -> 2289 | AJ11: =+IFERROR(IF(AND(AJ5>=Inputs!$L$10,F5<Inputs!$D$29),'(Z+) Rent Roll'!$K$20*(1+Inputs!$L$7)^(('(Z+) Monthly CF'!F5-Inputs!$L$10)/12),IF(AJ5>=Inputs!$D$29,AI11*((1+Inputs!$L$7)^(1/12)),'(Z+) Rent Roll'!$K$20)),0) -> 2289 | AK11: =+IFERROR(IF(AND(AK5>=Inputs!$L$10,F5<Inputs!$D$29),'(Z+) Rent Roll'!$K$20*(1+Inputs!$L$7)^(('(Z+) Monthly CF'!F5-Inputs!$L$10)/12),IF(AK5>=Inputs!$D$29,AJ11*((1+Inputs!$L$7)^(1/12)),'(Z+) Rent Roll'!$K$20)),0) -> 2289 | AL11: =+IFERROR(IF(AND(AL5>=Inputs!$L$10,F5<Inputs!$D$29),'(Z+) Rent Roll'!$K$20*(1+Inputs!$L$7)^(('(Z+) Monthly CF'!F5-Inputs!$L$10)/12),IF(AL5>=Inputs!$D$29,AK11*((1+Inputs!$L$7)^(1/12)),'(Z+) Rent Roll'!$K$20)),0) -> 2289 | AM11: =+IFERROR(IF(AND(AM5>=Inputs!$L$10,F5<Inputs!$D$29),'(Z+) Rent Roll'!$K$20*(1+Inputs!$L$7)^(('(Z+) Monthly CF'!F5-Inputs!$L$10)/12),IF(AM5>=Inputs!$D$29,AL11*((1+Inputs!$L$7)^(1/12)),'(Z+) Rent Roll'!$K$20)),0) -> 2289 | AN11: =+IFERROR(IF(AND(AN5>=Inputs!$L$10,F5<Inputs!$D$29),'(Z+) Rent Roll'!$K$20*(1+Inputs!$L$7)^(('(Z+) Monthly CF'!F5-Inputs!$L$10)/12),IF(AN5>=Inputs!$D$29,AM11*((1+Inputs!$L$7)^(1/12)),'(Z+) Rent Roll'!$K$20)),0) -> 2289 | AO11: =+IFERROR(IF(AND(AO5>=Inputs!$L$10,F5<Inputs!$D$29),'(Z+) Rent Roll'!$K$20*(1+Inputs!$L$7)^(('(Z+) Monthly CF'!F5-Inputs!$L$10)/12),IF(AO5>=Inputs!$D$29,AN11*((1+Inputs!$L$7)^(1/12)),'(Z+) Rent Roll'!$K$20)),0) -> 2289 | AP11: =+IFERROR(IF(AND(AP5>=Inputs!$L$10,F5<Inputs!$D$29),'(Z+) Rent Roll'!$K$20*(1+Inputs!$L$7)^(('(Z+) Monthly CF'!F5-Inputs!$L$10)/12),IF(AP5>=Inputs!$D$29,AO11*((1+Inputs!$L$7)^(1/12)),'(Z+) Rent Roll'!$K$20)),0) -> 2289 | AQ11: =+IFERROR(IF(AND(AQ5>=Inputs!$L$10,F5<Inputs!$D$29),'(Z+) Rent Roll'!$K$20*(1+Inputs!$L$7)^(('(Z+) Monthly CF'!F5-Inputs!$L$10)/12),IF(AQ5>=Inputs!$D$29,AP11*((1+Inputs!$L$7)^(1/12)),'(Z+) Rent Roll'!$K$20)),0) -> 2289 | AR11: =+IFERROR(IF(AND(AR5>=Inputs!$L$10,F5<Inputs!$D$29),'(Z+) Rent Roll'!$K$20*(1+Inputs!$L$7)^(('(Z+) Monthly CF'!F5-Inputs!$L$10)/12),IF(AR5>=Inputs!$D$29,AQ11*((1+Inputs!$L$7)^(1/12)),'(Z+) Rent Roll'!$K$20)),0) -> 2289 | AS11: =+IFERROR(IF(AND(AS5>=Inputs!$L$10,F5<Inputs!$D$29),'(Z+) Rent Roll'!$K$20*(1+Inputs!$L$7)^(('(Z+) Monthly CF'!F5-Inputs!$L$10)/12),IF(AS5>=Inputs!$D$29,AR11*((1+Inputs!$L$7)^(1/12)),'(Z+) Rent Roll'!$K$20)),0) -> 2289 | AT11: =+IFERROR(IF(AND(AT5>=Inputs!$L$10,F5<Inputs!$D$29),'(Z+) Rent Roll'!$K$20*(1+Inputs!$L$7)^(('(Z+) Monthly CF'!F5-Inputs!$L$10)/12),IF(AT5>=Inputs!$D$29,AS11*((1+Inputs!$L$7)^(1/12)),'(Z+) Rent Roll'!$K$20)),0) -> 2289 | AU11: =+IFERROR(IF(AND(AU5>=Inputs!$L$10,F5<Inputs!$D$29),'(Z+) Rent Roll'!$K$20*(1+Inputs!$L$7)^(('(Z+) Monthly CF'!F5-Inputs!$L$10)/12),IF(AU5>=Inputs!$D$29,AT11*((1+Inputs!$L$7)^(1/12)),'(Z+) Rent Roll'!$K$20)),0) -> 2289 | AV11: =+IFERROR(IF(AND(AV5>=Inputs!$L$10,F5<Inputs!$D$29),'(Z+) Rent Roll'!$K$20*(1+Inputs!$L$7)^(('(Z+) Monthly CF'!F5-Inputs!$L$10)/12),IF(AV5>=Inputs!$D$29,AU11*((1+Inputs!$L$7)^(1/12)),'(Z+) Rent Roll'!$K$20)),0) -> 2289 | AW11: =+IFERROR(IF(AND(AW5>=Inputs!$L$10,F5<Inputs!$D$29),'(Z+) Rent Roll'!$K$20*(1+Inputs!$L$7)^(('(Z+) Monthly CF'!F5-Inputs!$L$10)/12),IF(AW5>=Inputs!$D$29,AV11*((1+Inputs!$L$7)^(1/12)),'(Z+) Rent Roll'!$K$20)),0) -> 2289 | AX11: =+IFERROR(IF(AND(AX5>=Inputs!$L$10,F5<Inputs!$D$29),'(Z+) Rent Roll'!$K$20*(1+Inputs!$L$7)^(('(Z+) Monthly CF'!F5-Inputs!$L$10)/12),IF(AX5>=Inputs!$D$29,AW11*((1+Inputs!$L$7)^(1/12)),'(Z+) Rent Roll'!$K$20)),0) -> 2289 | AY11: =+IFERROR(IF(AND(AY5>=Inputs!$L$10,F5<Inputs!$D$29),'(Z+) Rent Roll'!$K$20*(1+Inputs!$L$7)^(('(Z+) Monthly CF'!F5-Inputs!$L$10)/12),IF(AY5>=Inputs!$D$29,AX11*((1+Inputs!$L$7)^(1/12)),'(Z+) Rent Roll'!$K$20)),0) -> 2289 | AZ11: =+IFERROR(IF(AND(AZ5>=Inputs!$L$10,F5<Inputs!$D$29),'(Z+) Rent Roll'!$K$20*(1+Inputs!$L$7)^(('(Z+) Monthly CF'!F5-Inputs!$L$10)/12),IF(AZ5>=Inputs!$D$29,AY11*((1+Inputs!$L$7)^(1/12)),'(Z+) Rent Roll'!$K$20)),0) -> 2289 | BA11: =+IFERROR(IF(AND(BA5>=Inputs!$L$10,F5<Inputs!$D$29),'(Z+) Rent Roll'!$K$20*(1+Inputs!$L$7)^(('(Z+) Monthly CF'!F5-Inputs!$L$10)/12),IF(BA5>=Inputs!$D$29,AZ11*((1+Inputs!$L$7)^(1/12)),'(Z+) Rent Roll'!$K$20)),0) -> 2289 | BB11: =+IFERROR(IF(AND(BB5>=Inputs!$L$10,F5<Inputs!$D$29),'(Z+) Rent Roll'!$K$20*(1+Inputs!$L$7)^(('(Z+) Monthly CF'!F5-Inputs!$L$10)/12),IF(BB5>=Inputs!$D$29,BA11*((1+Inputs!$L$7)^(1/12)),'(Z+) Rent Roll'!$K$20)),0) -> 2289 | BC11: =+IFERROR(IF(AND(BC5>=Inputs!$L$10,F5<Inputs!$D$29),'(Z+) Rent Roll'!$K$20*(1+Inputs!$L$7)^(('(Z+) Monthly CF'!F5-Inputs!$L$10)/12),IF(BC5>=Inputs!$D$29,BB11*((1+Inputs!$L$7)^(1/12)),'(Z+) Rent Roll'!$K$20)),0) -> 2289 | BD11: =+IFERROR(IF(AND(BD5>=Inputs!$L$10,F5<Inputs!$D$29),'(Z+) Rent Roll'!$K$20*(1+Inputs!$L$7)^(('(Z+) Monthly CF'!F5-Inputs!$L$10)/12),IF(BD5>=Inputs!$D$29,BC11*((1+Inputs!$L$7)^(1/12)),'(Z+) Rent Roll'!$K$20)),0) -> 2289 | BE11: =+IFERROR(IF(AND(BE5>=Inputs!$L$10,F5<Inputs!$D$29),'(Z+) Rent Roll'!$K$20*(1+Inputs!$L$7)^(('(Z+) Monthly CF'!F5-Inputs!$L$10)/12),IF(BE5>=Inputs!$D$29,BD11*((1+Inputs!$L$7)^(1/12)),'(Z+) Rent Roll'!$K$20)),0) -> 2289 | BF11: =+IFERROR(IF(AND(BF5>=Inputs!$L$10,F5<Inputs!$D$29),'(Z+) Rent Roll'!$K$20*(1+Inputs!$L$7)^(('(Z+) Monthly CF'!F5-Inputs!$L$10)/12),IF(BF5>=Inputs!$D$29,BE11*((1+Inputs!$L$7)^(1/12)),'(Z+) Rent Roll'!$K$20)),0) -> 2289 | BG11: =+IFERROR(IF(AND(BG5>=Inputs!$L$10,F5<Inputs!$D$29),'(Z+) Rent Roll'!$K$20*(1+Inputs!$L$7)^(('(Z+) Monthly CF'!F5-Inputs!$L$10)/12),IF(BG5>=Inputs!$D$29,BF11*((1+Inputs!$L$7)^(1/12)),'(Z+) Rent Roll'!$K$20)),0) -> 2289 | BH11: =+IFERROR(IF(AND(BH5>=Inputs!$L$10,F5<Inputs!$D$29),'(Z+) Rent Roll'!$K$20*(1+Inputs!$L$7)^(('(Z+) Monthly CF'!F5-Inputs!$L$10)/12),IF(BH5>=Inputs!$D$29,BG11*((1+Inputs!$L$7)^(1/12)),'(Z+) Rent Roll'!$K$20)),0) -> 2289 | BI11: =+IFERROR(IF(AND(BI5>=Inputs!$L$10,F5<Inputs!$D$29),'(Z+) Rent Roll'!$K$20*(1+Inputs!$L$7)^(('(Z+) Monthly CF'!F5-Inputs!$L$10)/12),IF(BI5>=Inputs!$D$29,BH11*((1+Inputs!$L$7)^(1/12)),'(Z+) Rent Roll'!$K$20)),0) -> 2289 | BJ11: =+IFERROR(IF(AND(BJ5>=Inputs!$L$10,F5<Inputs!$D$29),'(Z+) Rent Roll'!$K$20*(1+Inputs!$L$7)^(('(Z+) Monthly CF'!F5-Inputs!$L$10)/12),IF(BJ5>=Inputs!$D$29,BI11*((1+Inputs!$L$7)^(1/12)),'(Z+) Rent Roll'!$K$20)),0) -> 2289 | BK11: =+IFERROR(IF(AND(BK5>=Inputs!$L$10,F5<Inputs!$D$29),'(Z+) Rent Roll'!$K$20*(1+Inputs!$L$7)^(('(Z+) Monthly CF'!F5-Inputs!$L$10)/12),IF(BK5>=Inputs!$D$29,BJ11*((1+Inputs!$L$7)^(1/12)),'(Z+) Rent Roll'!$K$20)),0) -> 2289 | BL11: =+IFERROR(IF(AND(BL5>=Inputs!$L$10,F5<Inputs!$D$29),'(Z+) Rent Roll'!$K$20*(1+Inputs!$L$7)^(('(Z+) Monthly CF'!F5-Inputs!$L$10)/12),IF(BL5>=Inputs!$D$29,BK11*((1+Inputs!$L$7)^(1/12)),'(Z+) Rent Roll'!$K$20)),0) -> 2289 | BM11: =+IFERROR(IF(AND(BM5>=Inputs!$L$10,F5<Inputs!$D$29),'(Z+) Rent Roll'!$K$20*(1+Inputs!$L$7)^(('(Z+) Monthly CF'!F5-Inputs!$L$10)/12),IF(BM5>=Inputs!$D$29,BL11*((1+Inputs!$L$7)^(1/12)),'(Z+) Rent Roll'!$K$20)),0) -> 2289 | BN11: =+IFERROR(IF(AND(BN5>=Inputs!$L$10,F5<Inputs!$D$29),'(Z+) Rent Roll'!$K$20*(1+Inputs!$L$7)^(('(Z+) Monthly CF'!F5-Inputs!$L$10)/12),IF(BN5>=Inputs!$D$29,BM11*((1+Inputs!$L$7)^(1/12)),'(Z+) Rent Roll'!$K$20)),0) -> 2289 | BO11: =+IFERROR(IF(AND(BO5>=Inputs!$L$10,F5<Inputs!$D$29),'(Z+) Rent Roll'!$K$20*(1+Inputs!$L$7)^(('(Z+) Monthly CF'!F5-Inputs!$L$10)/12),IF(BO5>=Inputs!$D$29,BN11*((1+Inputs!$L$7)^(1/12)),'(Z+) Rent Roll'!$K$20)),0) -> 2289 | BP11: =+IFERROR(IF(AND(BP5>=Inputs!$L$10,F5<Inputs!$D$29),'(Z+) Rent Roll'!$K$20*(1+Inputs!$L$7)^(('(Z+) Monthly CF'!F5-Inputs!$L$10)/12),IF(BP5>=Inputs!$D$29,BO11*((1+Inputs!$L$7)^(1/12)),'(Z+) Rent Roll'!$K$20)),0) -> 2289 | BQ11: =+IFERROR(IF(AND(BQ5>=Inputs!$L$10,F5<Inputs!$D$29),'(Z+) Rent Roll'!$K$20*(1+Inputs!$L$7)^(('(Z+) Monthly CF'!F5-Inputs!$L$10)/12),IF(BQ5>=Inputs!$D$29,BP11*((1+Inputs!$L$7)^(1/12)),'(Z+) Rent Roll'!$K$20)),0) -> 2289 | BR11: =+IFERROR(IF(AND(BR5>=Inputs!$L$10,F5<Inputs!$D$29),'(Z+) Rent Roll'!$K$20*(1+Inputs!$L$7)^(('(Z+) Monthly CF'!F5-Inputs!$L$10)/12),IF(BR5>=Inputs!$D$29,BQ11*((1+Inputs!$L$7)^(1/12)),'(Z+) Rent Roll'!$K$20)),0) -> 2289 | BS11: =+IFERROR(IF(AND(BS5>=Inputs!$L$10,F5<Inputs!$D$29),'(Z+) Rent Roll'!$K$20*(1+Inputs!$L$7)^(('(Z+) Monthly CF'!F5-Inputs!$L$10)/12),IF(BS5>=Inputs!$D$29,BR11*((1+Inputs!$L$7)^(1/12)),'(Z+) Rent Roll'!$K$20)),0) -> 2289 | BT11: =+IFERROR(IF(AND(BT5>=Inputs!$L$10,F5<Inputs!$D$29),'(Z+) Rent Roll'!$K$20*(1+Inputs!$L$7)^(('(Z+) Monthly CF'!F5-Inputs!$L$10)/12),IF(BT5>=Inputs!$D$29,BS11*((1+Inputs!$L$7)^(1/12)),'(Z+) Rent Roll'!$K$20)),0) -> 2289 | BU11: =+IFERROR(IF(AND(BU5>=Inputs!$L$10,F5<Inputs!$D$29),'(Z+) Rent Roll'!$K$20*(1+Inputs!$L$7)^(('(Z+) Monthly CF'!F5-Inputs!$L$10)/12),IF(BU5>=Inputs!$D$29,BT11*((1+Inputs!$L$7)^(1/12)),'(Z+) Rent Roll'!$K$20)),0) -> 2289 | BV11: =+IFERROR(IF(AND(BV5>=Inputs!$L$10,F5<Inputs!$D$29),'(Z+) Rent Roll'!$K$20*(1+Inputs!$L$7)^(('(Z+) Monthly CF'!F5-Inputs!$L$10)/12),IF(BV5>=Inputs!$D$29,BU11*((1+Inputs!$L$7)^(1/12)),'(Z+) Rent Roll'!$K$20)),0) -> 2289 | BW11: =+IFERROR(IF(AND(BW5>=Inputs!$L$10,F5<Inputs!$D$29),'(Z+) Rent Roll'!$K$20*(1+Inputs!$L$7)^(('(Z+) Monthly CF'!F5-Inputs!$L$10)/12),IF(BW5>=Inputs!$D$29,BV11*((1+Inputs!$L$7)^(1/12)),'(Z+) Rent Roll'!$K$20)),0) -> 2289 | BX11: =+IFERROR(IF(AND(BX5>=Inputs!$L$10,F5<Inputs!$D$29),'(Z+) Rent Roll'!$K$20*(1+Inputs!$L$7)^(('(Z+) Monthly CF'!F5-Inputs!$L$10)/12),IF(BX5>=Inputs!$D$29,BW11*((1+Inputs!$L$7)^(1/12)),'(Z+) Rent Roll'!$K$20)),0) -> 2289 | BY11: =+IFERROR(IF(AND(BY5>=Inputs!$L$10,F5<Inputs!$D$29),'(Z+) Rent Roll'!$K$20*(1+Inputs!$L$7)^(('(Z+) Monthly CF'!F5-Inputs!$L$10)/12),IF(BY5>=Inputs!$D$29,BX11*((1+Inputs!$L$7)^(1/12)),'(Z+) Rent Roll'!$K$20)),0) -> 2289 | BZ11: =+IFERROR(IF(AND(BZ5>=Inputs!$L$10,F5<Inputs!$D$29),'(Z+) Rent Roll'!$K$20*(1+Inputs!$L$7)^(('(Z+) Monthly CF'!F5-Inputs!$L$10)/12),IF(BZ5>=Inputs!$D$29,BY11*((1+Inputs!$L$7)^(1/12)),'(Z+) Rent Roll'!$K$20)),0) -> 2289 | CA11: =+IFERROR(IF(AND(CA5>=Inputs!$L$10,F5<Inputs!$D$29),'(Z+) Rent Roll'!$K$20*(1+Inputs!$L$7)^(('(Z+) Monthly CF'!F5-Inputs!$L$10)/12),IF(CA5>=Inputs!$D$29,BZ11*((1+Inputs!$L$7)^(1/12)),'(Z+) Rent Roll'!$K$20)),0) -> 2289 | CB11: =+IFERROR(IF(AND(CB5>=Inputs!$L$10,F5<Inputs!$D$29),'(Z+) Rent Roll'!$K$20*(1+Inputs!$L$7)^(('(Z+) Monthly CF'!F5-Inputs!$L$10)/12),IF(CB5>=Inputs!$D$29,CA11*((1+Inputs!$L$7)^(1/12)),'(Z+) Rent Roll'!$K$20)),0) -> 2289 | CC11: =+IFERROR(IF(AND(CC5>=Inputs!$L$10,F5<Inputs!$D$29),'(Z+) Rent Roll'!$K$20*(1+Inputs!$L$7)^(('(Z+) Monthly CF'!F5-Inputs!$L$10)/12),IF(CC5>=Inputs!$D$29,CB11*((1+Inputs!$L$7)^(1/12)),'(Z+) Rent Roll'!$K$20)),0) -> 2289 | CD11: =+IFERROR(IF(AND(CD5>=Inputs!$L$10,F5<Inputs!$D$29),'(Z+) Rent Roll'!$K$20*(1+Inputs!$L$7)^(('(Z+) Monthly CF'!F5-Inputs!$L$10)/12),IF(CD5>=Inputs!$D$29,CC11*((1+Inputs!$L$7)^(1/12)),'(Z+) Rent Roll'!$K$20)),0) -> 2289 | CE11: =+IFERROR(IF(AND(CE5>=Inputs!$L$10,F5<Inputs!$D$29),'(Z+) Rent Roll'!$K$20*(1+Inputs!$L$7)^(('(Z+) Monthly CF'!F5-Inputs!$L$10)/12),IF(CE5>=Inputs!$D$29,CD11*((1+Inputs!$L$7)^(1/12)),'(Z+) Rent Roll'!$K$20)),0) -> 2289 | CF11: =+IFERROR(IF(AND(CF5>=Inputs!$L$10,F5<Inputs!$D$29),'(Z+) Rent Roll'!$K$20*(1+Inputs!$L$7)^(('(Z+) Monthly CF'!F5-Inputs!$L$10)/12),IF(CF5>=Inputs!$D$29,CE11*((1+Inputs!$L$7)^(1/12)),'(Z+) Rent Roll'!$K$20)),0) -> 2289 | CG11: =+IFERROR(IF(AND(CG5>=Inputs!$L$10,F5<Inputs!$D$29),'(Z+) Rent Roll'!$K$20*(1+Inputs!$L$7)^(('(Z+) Monthly CF'!F5-Inputs!$L$10)/12),IF(CG5>=Inputs!$D$29,CF11*((1+Inputs!$L$7)^(1/12)),'(Z+) Rent Roll'!$K$20)),0) -> 2289 | CH11: =+IFERROR(IF(AND(CH5>=Inputs!$L$10,F5<Inputs!$D$29),'(Z+) Rent Roll'!$K$20*(1+Inputs!$L$7)^(('(Z+) Monthly CF'!F5-Inputs!$L$10)/12),IF(CH5>=Inputs!$D$29,CG11*((1+Inputs!$L$7)^(1/12)),'(Z+) Rent Roll'!$K$20)),0) -> 2289 | CI11: =+IFERROR(IF(AND(CI5>=Inputs!$L$10,F5<Inputs!$D$29),'(Z+) Rent Roll'!$K$20*(1+Inputs!$L$7)^(('(Z+) Monthly CF'!F5-Inputs!$L$10)/12),IF(CI5>=Inputs!$D$29,CH11*((1+Inputs!$L$7)^(1/12)),'(Z+) Rent Roll'!$K$20)),0) -> 2289 | CJ11: =+IFERROR(IF(AND(CJ5>=Inputs!$L$10,F5<Inputs!$D$29),'(Z+) Rent Roll'!$K$20*(1+Inputs!$L$7)^(('(Z+) Monthly CF'!F5-Inputs!$L$10)/12),IF(CJ5>=Inputs!$D$29,CI11*((1+Inputs!$L$7)^(1/12)),'(Z+) Rent Roll'!$K$20)),0) -> 2289 | CK11: =+IFERROR(IF(AND(CK5>=Inputs!$L$10,F5<Inputs!$D$29),'(Z+) Rent Roll'!$K$20*(1+Inputs!$L$7)^(('(Z+) Monthly CF'!F5-Inputs!$L$10)/12),IF(CK5>=Inputs!$D$29,CJ11*((1+Inputs!$L$7)^(1/12)),'(Z+) Rent Roll'!$K$20)),0) -> 2289 | CL11: =+IFERROR(IF(AND(CL5>=Inputs!$L$10,F5<Inputs!$D$29),'(Z+) Rent Roll'!$K$20*(1+Inputs!$L$7)^(('(Z+) Monthly CF'!F5-Inputs!$L$10)/12),IF(CL5>=Inputs!$D$29,CK11*((1+Inputs!$L$7)^(1/12)),'(Z+) Rent Roll'!$K$20)),0) -> 2289 | CM11: =+IFERROR(IF(AND(CM5>=Inputs!$L$10,F5<Inputs!$D$29),'(Z+) Rent Roll'!$K$20*(1+Inputs!$L$7)^(('(Z+) Monthly CF'!F5-Inputs!$L$10)/12),IF(CM5>=Inputs!$D$29,CL11*((1+Inputs!$L$7)^(1/12)),'(Z+) Rent Roll'!$K$20)),0) -> 2289 | CN11: =+IFERROR(IF(AND(CN5>=Inputs!$L$10,F5<Inputs!$D$29),'(Z+) Rent Roll'!$K$20*(1+Inputs!$L$7)^(('(Z+) Monthly CF'!F5-Inputs!$L$10)/12),IF(CN5>=Inputs!$D$29,CM11*((1+Inputs!$L$7)^(1/12)),'(Z+) Rent Roll'!$K$20)),0) -> 2289 | CO11: =+IFERROR(IF(AND(CO5>=Inputs!$L$10,F5<Inputs!$D$29),'(Z+) Rent Roll'!$K$20*(1+Inputs!$L$7)^(('(Z+) Monthly CF'!F5-Inputs!$L$10)/12),IF(CO5>=Inputs!$D$29,CN11*((1+Inputs!$L$7)^(1/12)),'(Z+) Rent Roll'!$K$20)),0) -> 2289 | CP11: =+IFERROR(IF(AND(CP5>=Inputs!$L$10,F5<Inputs!$D$29),'(Z+) Rent Roll'!$K$20*(1+Inputs!$L$7)^(('(Z+) Monthly CF'!F5-Inputs!$L$10)/12),IF(CP5>=Inputs!$D$29,CO11*((1+Inputs!$L$7)^(1/12)),'(Z+) Rent Roll'!$K$20)),0) -> 2289 | CQ11: =+IFERROR(IF(AND(CQ5>=Inputs!$L$10,F5<Inputs!$D$29),'(Z+) Rent Roll'!$K$20*(1+Inputs!$L$7)^(('(Z+) Monthly CF'!F5-Inputs!$L$10)/12),IF(CQ5>=Inputs!$D$29,CP11*((1+Inputs!$L$7)^(1/12)),'(Z+) Rent Roll'!$K$20)),0) -> 2289 | CR11: =+IFERROR(IF(AND(CR5>=Inputs!$L$10,F5<Inputs!$D$29),'(Z+) Rent Roll'!$K$20*(1+Inputs!$L$7)^(('(Z+) Monthly CF'!F5-Inputs!$L$10)/12),IF(CR5>=Inputs!$D$29,CQ11*((1+Inputs!$L$7)^(1/12)),'(Z+) Rent Roll'!$K$20)),0) -> 2289 | CS11: =+IFERROR(IF(AND(CS5>=Inputs!$L$10,F5<Inputs!$D$29),'(Z+) Rent Roll'!$K$20*(1+Inputs!$L$7)^(('(Z+) Monthly CF'!F5-Inputs!$L$10)/12),IF(CS5>=Inputs!$D$29,CR11*((1+Inputs!$L$7)^(1/12)),'(Z+) Rent Roll'!$K$20)),0) -> 2289 | CT11: =+IFERROR(IF(AND(CT5>=Inputs!$L$10,F5<Inputs!$D$29),'(Z+) Rent Roll'!$K$20*(1+Inputs!$L$7)^(('(Z+) Monthly CF'!F5-Inputs!$L$10)/12),IF(CT5>=Inputs!$D$29,CS11*((1+Inputs!$L$7)^(1/12)),'(Z+) Rent Roll'!$K$20)),0) -> 2289 | CU11: =+IFERROR(IF(AND(CU5>=Inputs!$L$10,F5<Inputs!$D$29),'(Z+) Rent Roll'!$K$20*(1+Inputs!$L$7)^(('(Z+) Monthly CF'!F5-Inputs!$L$10)/12),IF(CU5>=Inputs!$D$29,CT11*((1+Inputs!$L$7)^(1/12)),'(Z+) Rent Roll'!$K$20)),0) -> 2289 | CV11: =+IFERROR(IF(AND(CV5>=Inputs!$L$10,F5<Inputs!$D$29),'(Z+) Rent Roll'!$K$20*(1+Inputs!$L$7)^(('(Z+) Monthly CF'!F5-Inputs!$L$10)/12),IF(CV5>=Inputs!$D$29,CU11*((1+Inputs!$L$7)^(1/12)),'(Z+) Rent Roll'!$K$20)),0) -> 2289 | CW11: =+IFERROR(IF(AND(CW5>=Inputs!$L$10,F5<Inputs!$D$29),'(Z+) Rent Roll'!$K$20*(1+Inputs!$L$7)^(('(Z+) Monthly CF'!F5-Inputs!$L$10)/12),IF(CW5>=Inputs!$D$29,CV11*((1+Inputs!$L$7)^(1/12)),'(Z+) Rent Roll'!$K$20)),0) -> 2289 | CX11: =+IFERROR(IF(AND(CX5>=Inputs!$L$10,F5<Inputs!$D$29),'(Z+) Rent Roll'!$K$20*(1+Inputs!$L$7)^(('(Z+) Monthly CF'!F5-Inputs!$L$10)/12),IF(CX5>=Inputs!$D$29,CW11*((1+Inputs!$L$7)^(1/12)),'(Z+) Rent Roll'!$K$20)),0) -> 2289 | CY11: =+IFERROR(IF(AND(CY5>=Inputs!$L$10,F5<Inputs!$D$29),'(Z+) Rent Roll'!$K$20*(1+Inputs!$L$7)^(('(Z+) Monthly CF'!F5-Inputs!$L$10)/12),IF(CY5>=Inputs!$D$29,CX11*((1+Inputs!$L$7)^(1/12)),'(Z+) Rent Roll'!$K$20)),0) -> 2289 | CZ11: =+IFERROR(IF(AND(CZ5>=Inputs!$L$10,F5<Inputs!$D$29),'(Z+) Rent Roll'!$K$20*(1+Inputs!$L$7)^(('(Z+) Monthly CF'!F5-Inputs!$L$10)/12),IF(CZ5>=Inputs!$D$29,CY11*((1+Inputs!$L$7)^(1/12)),'(Z+) Rent Roll'!$K$20)),0) -> 2289 | DA11: =+IFERROR(IF(AND(DA5>=Inputs!$L$10,F5<Inputs!$D$29),'(Z+) Rent Roll'!$K$20*(1+Inputs!$L$7)^(('(Z+) Monthly CF'!F5-Inputs!$L$10)/12),IF(DA5>=Inputs!$D$29,CZ11*((1+Inputs!$L$7)^(1/12)),'(Z+) Rent Roll'!$K$20)),0) -> 2289 | DB11: =+IFERROR(IF(AND(DB5>=Inputs!$L$10,F5<Inputs!$D$29),'(Z+) Rent Roll'!$K$20*(1+Inputs!$L$7)^(('(Z+) Monthly CF'!F5-Inputs!$L$10)/12),IF(DB5>=Inputs!$D$29,DA11*((1+Inputs!$L$7)^(1/12)),'(Z+) Rent Roll'!$K$20)),0) -> 2289 | DC11: =+IFERROR(IF(AND(DC5>=Inputs!$L$10,F5<Inputs!$D$29),'(Z+) Rent Roll'!$K$20*(1+Inputs!$L$7)^(('(Z+) Monthly CF'!F5-Inputs!$L$10)/12),IF(DC5>=Inputs!$D$29,DB11*((1+Inputs!$L$7)^(1/12)),'(Z+) Rent Roll'!$K$20)),0) -> 2289 | DD11: =+IFERROR(IF(AND(DD5>=Inputs!$L$10,F5<Inputs!$D$29),'(Z+) Rent Roll'!$K$20*(1+Inputs!$L$7)^(('(Z+) Monthly CF'!F5-Inputs!$L$10)/12),IF(DD5>=Inputs!$D$29,DC11*((1+Inputs!$L$7)^(1/12)),'(Z+) Rent Roll'!$K$20)),0) -> 2289 | DE11: =+IFERROR(IF(AND(DE5>=Inputs!$L$10,F5<Inputs!$D$29),'(Z+) Rent Roll'!$K$20*(1+Inputs!$L$7)^(('(Z+) Monthly CF'!F5-Inputs!$L$10)/12),IF(DE5>=Inputs!$D$29,DD11*((1+Inputs!$L$7)^(1/12)),'(Z+) Rent Roll'!$K$20)),0) -> 2289 | DF11: =+IFERROR(IF(AND(DF5>=Inputs!$L$10,F5<Inputs!$D$29),'(Z+) Rent Roll'!$K$20*(1+Inputs!$L$7)^(('(Z+) Monthly CF'!F5-Inputs!$L$10)/12),IF(DF5>=Inputs!$D$29,DE11*((1+Inputs!$L$7)^(1/12)),'(Z+) Rent Roll'!$K$20)),0) -> 2289 | DG11: =+IFERROR(IF(AND(DG5>=Inputs!$L$10,F5<Inputs!$D$29),'(Z+) Rent Roll'!$K$20*(1+Inputs!$L$7)^(('(Z+) Monthly CF'!F5-Inputs!$L$10)/12),IF(DG5>=Inputs!$D$29,DF11*((1+Inputs!$L$7)^(1/12)),'(Z+) Rent Roll'!$K$20)),0) -> 2289 | DH11: =+IFERROR(IF(AND(DH5>=Inputs!$L$10,F5<Inputs!$D$29),'(Z+) Rent Roll'!$K$20*(1+Inputs!$L$7)^(('(Z+) Monthly CF'!F5-Inputs!$L$10)/12),IF(DH5>=Inputs!$D$29,DG11*((1+Inputs!$L$7)^(1/12)),'(Z+) Rent Roll'!$K$20)),0) -> 2289 | DI11: =+IFERROR(IF(AND(DI5>=Inputs!$L$10,F5<Inputs!$D$29),'(Z+) Rent Roll'!$K$20*(1+Inputs!$L$7)^(('(Z+) Monthly CF'!F5-Inputs!$L$10)/12),IF(DI5>=Inputs!$D$29,DH11*((1+Inputs!$L$7)^(1/12)),'(Z+) Rent Roll'!$K$20)),0) -> 2289 | DJ11: =+IFERROR(IF(AND(DJ5>=Inputs!$L$10,F5<Inputs!$D$29),'(Z+) Rent Roll'!$K$20*(1+Inputs!$L$7)^(('(Z+) Monthly CF'!F5-Inputs!$L$10)/12),IF(DJ5>=Inputs!$D$29,DI11*((1+Inputs!$L$7)^(1/12)),'(Z+) Rent Roll'!$K$20)),0) -> 2289 | DK11: =+IFERROR(IF(AND(DK5>=Inputs!$L$10,F5<Inputs!$D$29),'(Z+) Rent Roll'!$K$20*(1+Inputs!$L$7)^(('(Z+) Monthly CF'!F5-Inputs!$L$10)/12),IF(DK5>=Inputs!$D$29,DJ11*((1+Inputs!$L$7)^(1/12)),'(Z+) Rent Roll'!$K$20)),0) -> 2289 | DL11: =+IFERROR(IF(AND(DL5>=Inputs!$L$10,F5<Inputs!$D$29),'(Z+) Rent Roll'!$K$20*(1+Inputs!$L$7)^(('(Z+) Monthly CF'!F5-Inputs!$L$10)/12),IF(DL5>=Inputs!$D$29,DK11*((1+Inputs!$L$7)^(1/12)),'(Z+) Rent Roll'!$K$20)),0) -> 2289 | DM11: =+IFERROR(IF(AND(DM5>=Inputs!$L$10,F5<Inputs!$D$29),'(Z+) Rent Roll'!$K$20*(1+Inputs!$L$7)^(('(Z+) Monthly CF'!F5-Inputs!$L$10)/12),IF(DM5>=Inputs!$D$29,DL11*((1+Inputs!$L$7)^(1/12)),'(Z+) Rent Roll'!$K$20)),0) -> 2289 | DN11: =+IFERROR(IF(AND(DN5>=Inputs!$L$10,G5<Inputs!$D$29),'(Z+) Rent Roll'!$K$20*(1+Inputs!$L$7)^(('(Z+) Monthly CF'!G5-Inputs!$L$10)/12),IF(DN5>=Inputs!$D$29,DM11*((1+Inputs!$L$7)^(1/12)),'(Z+) Rent Roll'!$K$20)),0) -> 2293.715 | DO11: =+IFERROR(IF(AND(DO5>=Inputs!$L$10,H5<Inputs!$D$29),'(Z+) Rent Roll'!$K$20*(1+Inputs!$L$7)^(('(Z+) Monthly CF'!H5-Inputs!$L$10)/12),IF(DO5>=Inputs!$D$29,DN11*((1+Inputs!$L$7)^(1/12)),'(Z+) Rent Roll'!$K$20)),0) -> 2298.4396 | DP11: =+IFERROR(IF(AND(DP5>=Inputs!$L$10,I5<Inputs!$D$29),'(Z+) Rent Roll'!$K$20*(1+Inputs!$L$7)^(('(Z+) Monthly CF'!I5-Inputs!$L$10)/12),IF(DP5>=Inputs!$D$29,DO11*((1+Inputs!$L$7)^(1/12)),'(Z+) Rent Roll'!$K$20)),0) -> 2303.1741 | DQ11: =+IFERROR(IF(AND(DQ5>=Inputs!$L$10,J5<Inputs!$D$29),'(Z+) Rent Roll'!$K$20*(1+Inputs!$L$7)^(('(Z+) Monthly CF'!J5-Inputs!$L$10)/12),IF(DQ5>=Inputs!$D$29,DP11*((1+Inputs!$L$7)^(1/12)),'(Z+) Rent Roll'!$K$20)),0) -> 2307.9182 | DR11: =+IFERROR(IF(AND(DR5>=Inputs!$L$10,K5<Inputs!$D$29),'(Z+) Rent Roll'!$K$20*(1+Inputs!$L$7)^(('(Z+) Monthly CF'!K5-Inputs!$L$10)/12),IF(DR5>=Inputs!$D$29,DQ11*((1+Inputs!$L$7)^(1/12)),'(Z+) Rent Roll'!$K$20)),0) -> 2312.6721 | DS11: =+IFERROR(IF(AND(DS5>=Inputs!$L$10,L5<Inputs!$D$29),'(Z+) Rent Roll'!$K$20*(1+Inputs!$L$7)^(('(Z+) Monthly CF'!L5-Inputs!$L$10)/12),IF(DS5>=Inputs!$D$29,DR11*((1+Inputs!$L$7)^(1/12)),'(Z+) Rent Roll'!$K$20)),0) -> 2317.4359 | DT11: =+IFERROR(IF(AND(DT5>=Inputs!$L$10,M5<Inputs!$D$29),'(Z+) Rent Roll'!$K$20*(1+Inputs!$L$7)^(('(Z+) Monthly CF'!M5-Inputs!$L$10)/12),IF(DT5>=Inputs!$D$29,DS11*((1+Inputs!$L$7)^(1/12)),'(Z+) Rent Roll'!$K$20)),0) -> 2322.2094 | DU11: =+IFERROR(IF(AND(DU5>=Inputs!$L$10,N5<Inputs!$D$29),'(Z+) Rent Roll'!$K$20*(1+Inputs!$L$7)^(('(Z+) Monthly CF'!N5-Inputs!$L$10)/12),IF(DU5>=Inputs!$D$29,DT11*((1+Inputs!$L$7)^(1/12)),'(Z+) Rent Roll'!$K$20)),0) -> 2326.9928
A12: Structural Occupancy | F12: =IFERROR(IF(F4>=Inputs!$E$29,MIN(1/(lease_up_period+1)*(DAYS360(Inputs!$E$29-30,F4)/30),1),0),0) -> 0 | G12: =IFERROR(IF(G4>=Inputs!$E$29,MIN(1/(lease_up_period+1)*(DAYS360(Inputs!$E$29-30,G4)/30),1),0),0) -> 0 | H12: =IFERROR(IF(H4>=Inputs!$E$29,MIN(1/(lease_up_period+1)*(DAYS360(Inputs!$E$29-30,H4)/30),1),0),0) -> 0 | I12: =IFERROR(IF(I4>=Inputs!$E$29,MIN(1/(lease_up_period+1)*(DAYS360(Inputs!$E$29-30,I4)/30),1),0),0) -> 0 | J12: =IFERROR(IF(J4>=Inputs!$E$29,MIN(1/(lease_up_period+1)*(DAYS360(Inputs!$E$29-30,J4)/30),1),0),0) -> 0 | K12: =IFERROR(IF(K4>=Inputs!$E$29,MIN(1/(lease_up_period+1)*(DAYS360(Inputs!$E$29-30,K4)/30),1),0),0) -> 0 | L12: =IFERROR(IF(L4>=Inputs!$E$29,MIN(1/(lease_up_period+1)*(DAYS360(Inputs!$E$29-30,L4)/30),1),0),0) -> 0 | M12: =IFERROR(IF(M4>=Inputs!$E$29,MIN(1/(lease_up_period+1)*(DAYS360(Inputs!$E$29-30,M4)/30),1),0),0) -> 0 | ... DU12: =IFERROR(IF(DU4>=Inputs!$E$29,MIN(1/(lease_up_period+1)*(DAYS360(Inputs!$E$29-30,DU4)/30),1),0),0) -> 1
A13: Commercial Rent | F13: =IFERROR(IF(F4>=Inputs!$E$29,-FV('(Z+) Rent Roll'!$G$24,ROUNDDOWN(DAYS360(Inputs!$E$29,F4)/30/12,0),0,'(Z+) Rent Roll'!$C$24*'(Z+) Rent Roll'!$D$24),0)*F12,0) -> 0 | G13: =IFERROR(IF(G4>=Inputs!$E$29,-FV('(Z+) Rent Roll'!$G$24,ROUNDDOWN(DAYS360(Inputs!$E$29,G4)/30/12,0),0,'(Z+) Rent Roll'!$C$24*'(Z+) Rent Roll'!$D$24),0)*G12,0) -> 0 | H13: =IFERROR(IF(H4>=Inputs!$E$29,-FV('(Z+) Rent Roll'!$G$24,ROUNDDOWN(DAYS360(Inputs!$E$29,H4)/30/12,0),0,'(Z+) Rent Roll'!$C$24*'(Z+) Rent Roll'!$D$24),0)*H12,0) -> 0 | I13: =IFERROR(IF(I4>=Inputs!$E$29,-FV('(Z+) Rent Roll'!$G$24,ROUNDDOWN(DAYS360(Inputs!$E$29,I4)/30/12,0),0,'(Z+) Rent Roll'!$C$24*'(Z+) Rent Roll'!$D$24),0)*I12,0) -> 0 | J13: =IFERROR(IF(J4>=Inputs!$E$29,-FV('(Z+) Rent Roll'!$G$24,ROUNDDOWN(DAYS360(Inputs!$E$29,J4)/30/12,0),0,'(Z+) Rent Roll'!$C$24*'(Z+) Rent Roll'!$D$24),0)*J12,0) -> 0 | K13: =IFERROR(IF(K4>=Inputs!$E$29,-FV('(Z+) Rent Roll'!$G$24,ROUNDDOWN(DAYS360(Inputs!$E$29,K4)/30/12,0),0,'(Z+) Rent Roll'!$C$24*'(Z+) Rent Roll'!$D$24),0)*K12,0) -> 0 | L13: =IFERROR(IF(L4>=Inputs!$E$29,-FV('(Z+) Rent Roll'!$G$24,ROUNDDOWN(DAYS360(Inputs!$E$29,L4)/30/12,0),0,'(Z+) Rent Roll'!$C$24*'(Z+) Rent Roll'!$D$24),0)*L12,0) -> 0 | M13: =IFERROR(IF(M4>=Inputs!$E$29,-FV('(Z+) Rent Roll'!$G$24,ROUNDDOWN(DAYS360(Inputs!$E$29,M4)/30/12,0),0,'(Z+) Rent Roll'!$C$24*'(Z+) Rent Roll'!$D$24),0)*M12,0) -> 0 | ... DU13: =IFERROR(IF(DU4>=Inputs!$E$29,-FV('(Z+) Rent Roll'!$G$24,ROUNDDOWN(DAYS360(Inputs!$E$29,DU4)/30/12,0),0,'(Z+) Rent Roll'!$C$24*'(Z+) Rent Roll'!$D$24),0)*DU12,0) -> 0
A14: Residential Rent | F14: =IFERROR(IF(F$4>=Inputs!$E$29,'(Z+) Rent Roll'!$L$20*'(Z+) Monthly CF'!F$9*F$12,0),0) -> 0 | G14: =IFERROR(IF(G$4>=Inputs!$E$29,'(Z+) Rent Roll'!$L$20*'(Z+) Monthly CF'!G$9*G$12,0),0) -> 0 | H14: =IFERROR(IF(H$4>=Inputs!$E$29,'(Z+) Rent Roll'!$L$20*'(Z+) Monthly CF'!H$9*H$12,0),0) -> 0 | I14: =IFERROR(IF(I$4>=Inputs!$E$29,'(Z+) Rent Roll'!$L$20*'(Z+) Monthly CF'!I$9*I$12,0),0) -> 0 | J14: =IFERROR(IF(J$4>=Inputs!$E$29,'(Z+) Rent Roll'!$L$20*'(Z+) Monthly CF'!J$9*J$12,0),0) -> 0 | K14: =IFERROR(IF(K$4>=Inputs!$E$29,'(Z+) Rent Roll'!$L$20*'(Z+) Monthly CF'!K$9*K$12,0),0) -> 0 | L14: =IFERROR(IF(L$4>=Inputs!$E$29,'(Z+) Rent Roll'!$L$20*'(Z+) Monthly CF'!L$9*L$12,0),0) -> 0 | M14: =IFERROR(IF(M$4>=Inputs!$E$29,'(Z+) Rent Roll'!$L$20*'(Z+) Monthly CF'!M$9*M$12,0),0) -> 0 | ... DU14: =IFERROR(IF(DU$4>=Inputs!$E$29,'(Z+) Rent Roll'!$L$20*'(Z+) Monthly CF'!DU$9*DU$12,0),0) -> 654996.24
A15: Other Income | F15: =IFERROR(IF(F4>=Inputs!$E$29,'(Z+) Rent Roll'!$H$36*F9*F12,0),0) -> 0 | G15: =IFERROR(IF(G4>=Inputs!$E$29,'(Z+) Rent Roll'!$H$36*G9*G12,0),0) -> 0 | H15: =IFERROR(IF(H4>=Inputs!$E$29,'(Z+) Rent Roll'!$H$36*H9*H12,0),0) -> 0 | I15: =IFERROR(IF(I4>=Inputs!$E$29,'(Z+) Rent Roll'!$H$36*I9*I12,0),0) -> 0 | J15: =IFERROR(IF(J4>=Inputs!$E$29,'(Z+) Rent Roll'!$H$36*J9*J12,0),0) -> 0 | K15: =IFERROR(IF(K4>=Inputs!$E$29,'(Z+) Rent Roll'!$H$36*K9*K12,0),0) -> 0 | L15: =IFERROR(IF(L4>=Inputs!$E$29,'(Z+) Rent Roll'!$H$36*L9*L12,0),0) -> 0 | M15: =IFERROR(IF(M4>=Inputs!$E$29,'(Z+) Rent Roll'!$H$36*M9*M12,0),0) -> 0 | ... DU15: =IFERROR(IF(DU4>=Inputs!$E$29,'(Z+) Rent Roll'!$H$36*DU9*DU12,0),0) -> 17902.801
A16: Total Rental Income | F16: =IFERROR(SUM(F13:F15),0) -> 0 | G16: =IFERROR(SUM(G13:G15),0) -> 0 | H16: =IFERROR(SUM(H13:H15),0) -> 0 | I16: =IFERROR(SUM(I13:I15),0) -> 0 | J16: =IFERROR(SUM(J13:J15),0) -> 0 | K16: =IFERROR(SUM(K13:K15),0) -> 0 | L16: =IFERROR(SUM(L13:L15),0) -> 0 | M16: =IFERROR(SUM(M13:M15),0) -> 0 | ... DU16: =IFERROR(SUM(DU13:DU15),0) -> 672899.05
A17: Residential Vacancy/Credit Loss | F17: =-IFERROR(F14*Inputs!$L$6,0) -> 0 | G17: =-IFERROR(G14*Inputs!$L$6,0) -> 0 | H17: =-IFERROR(H14*Inputs!$L$6,0) -> 0 | I17: =-IFERROR(I14*Inputs!$L$6,0) -> 0 | J17: =-IFERROR(J14*Inputs!$L$6,0) -> 0 | K17: =-IFERROR(K14*Inputs!$L$6,0) -> 0 | L17: =-IFERROR(L14*Inputs!$L$6,0) -> 0 | M17: =-IFERROR(M14*Inputs!$L$6,0) -> 0 | ... DU17: =-IFERROR(DU14*Inputs!$L$6,0) -> -19649.887
A18: Total Vacancy/Credit Loss | F18: =IFERROR(SUM(F17:F17),0) -> 0 | G18: =IFERROR(SUM(G17:G17),0) -> 0 | H18: =IFERROR(SUM(H17:H17),0) -> 0 | I18: =IFERROR(SUM(I17:I17),0) -> 0 | J18: =IFERROR(SUM(J17:J17),0) -> 0 | K18: =IFERROR(SUM(K17:K17),0) -> 0 | L18: =IFERROR(SUM(L17:L17),0) -> 0 | M18: =IFERROR(SUM(M17:M17),0) -> 0 | ... DU18: =IFERROR(SUM(DU17:DU17),0) -> -19649.887
A19: Effective Gross Income | F19: =IFERROR(SUM(F16,F18),0) -> 0 | G19: =IFERROR(SUM(G16,G18),0) -> 0 | H19: =IFERROR(SUM(H16,H18),0) -> 0 | I19: =IFERROR(SUM(I16,I18),0) -> 0 | J19: =IFERROR(SUM(J16,J18),0) -> 0 | K19: =IFERROR(SUM(K16,K18),0) -> 0 | L19: =IFERROR(SUM(L16,L18),0) -> 0 | M19: =IFERROR(SUM(M16,M18),0) -> 0 | ... DU19: =IFERROR(SUM(DU16,DU18),0) -> 653249.16
A21: Covenanted Exit
A22: Commercial Rent | F22: =0 -> 0 | G22: =0 -> 0 | H22: =0 -> 0 | I22: =0 -> 0 | J22: =0 -> 0 | K22: =0 -> 0 | L22: =0 -> 0 | M22: =0 -> 0 | ... DU22: =0 -> 0
A23: Residential Rent | F23: =IF(F4>=Inputs!$E$29,'(Z+) Rent Roll'!$H$20*F9*F12,0) -> 0 | G23: =IF(G4>=Inputs!$E$29,'(Z+) Rent Roll'!$H$20*G9*G12,0) -> 0 | H23: =IF(H4>=Inputs!$E$29,'(Z+) Rent Roll'!$H$20*H9*H12,0) -> 0 | I23: =IF(I4>=Inputs!$E$29,'(Z+) Rent Roll'!$H$20*I9*I12,0) -> 0 | J23: =IF(J4>=Inputs!$E$29,'(Z+) Rent Roll'!$H$20*J9*J12,0) -> 0 | K23: =IF(K4>=Inputs!$E$29,'(Z+) Rent Roll'!$H$20*K9*K12,0) -> 0 | L23: =IF(L4>=Inputs!$E$29,'(Z+) Rent Roll'!$H$20*L9*L12,0) -> 0 | M23: =IF(M4>=Inputs!$E$29,'(Z+) Rent Roll'!$H$20*M9*M12,0) -> 0 | ... DU23: =IF(DU4>=Inputs!$E$29,'(Z+) Rent Roll'!$H$20*DU9*DU12,0) -> 2924.0904
A24: Other Income | F24: =IF(F4>=Inputs!$E$29,'(Z+) Rent Roll'!$H$36*F9*F12,0) -> 0 | G24: =IF(G4>=Inputs!$E$29,'(Z+) Rent Roll'!$H$36*G9*G12,0) -> 0 | H24: =IF(H4>=Inputs!$E$29,'(Z+) Rent Roll'!$H$36*H9*H12,0) -> 0 | I24: =IF(I4>=Inputs!$E$29,'(Z+) Rent Roll'!$H$36*I9*I12,0) -> 0 | J24: =IF(J4>=Inputs!$E$29,'(Z+) Rent Roll'!$H$36*J9*J12,0) -> 0 | K24: =IF(K4>=Inputs!$E$29,'(Z+) Rent Roll'!$H$36*K9*K12,0) -> 0 | L24: =IF(L4>=Inputs!$E$29,'(Z+) Rent Roll'!$H$36*L9*L12,0) -> 0 | M24: =IF(M4>=Inputs!$E$29,'(Z+) Rent Roll'!$H$36*M9*M12,0) -> 0 | ... DU24: =IF(DU4>=Inputs!$E$29,'(Z+) Rent Roll'!$H$36*DU9*DU12,0) -> 17902.801
A25: Total Rental Income | F25: =SUM(F22:F24) -> 0 | G25: =SUM(G22:G24) -> 0 | H25: =SUM(H22:H24) -> 0 | I25: =SUM(I22:I24) -> 0 | J25: =SUM(J22:J24) -> 0 | K25: =SUM(K22:K24) -> 0 | L25: =SUM(L22:L24) -> 0 | M25: =SUM(M22:M24) -> 0 | ... DU25: =SUM(DU22:DU24) -> 20826.892
A26: Commercial Vacancy/Credit Loss
A27: Residential Vacancy/Credit Loss | F27: =-F23*'(Z+) Rent Roll'!$N$20 -> 0 | G27: =-G23*'(Z+) Rent Roll'!$N$20 -> 0 | H27: =-H23*'(Z+) Rent Roll'!$N$20 -> 0 | I27: =-I23*'(Z+) Rent Roll'!$N$20 -> 0 | J27: =-J23*'(Z+) Rent Roll'!$N$20 -> 0 | K27: =-K23*'(Z+) Rent Roll'!$N$20 -> 0 | L27: =-L23*'(Z+) Rent Roll'!$N$20 -> 0 | M27: =-M23*'(Z+) Rent Roll'!$N$20 -> 0 | ... DU27: =-DU23*'(Z+) Rent Roll'!$N$20 -> -87.722711
A28: Total Vacancy/Credit Loss | F28: =SUM(F26:F27) -> 0 | G28: =SUM(G26:G27) -> 0 | H28: =SUM(H26:H27) -> 0 | I28: =SUM(I26:I27) -> 0 | J28: =SUM(J26:J27) -> 0 | K28: =SUM(K26:K27) -> 0 | L28: =SUM(L26:L27) -> 0 | M28: =SUM(M26:M27) -> 0 | ... DU28: =SUM(DU26:DU27) -> -87.722711
A29: Effective Gross Income | F29: =SUM(F25,F28) -> 0 | G29: =SUM(G25,G28) -> 0 | H29: =SUM(H25,H28) -> 0 | I29: =SUM(I25,I28) -> 0 | J29: =SUM(J25,J28) -> 0 | K29: =SUM(K25,K28) -> 0 | L29: =SUM(L25,L28) -> 0 | M29: =SUM(M25,M28) -> 0 | ... DU29: =SUM(DU25,DU28) -> 20739.169
A31: =+'(Z+) OpEx'!C8 -> Prop. Taxes | C31: =+'(Z+) OpEx'!D8 -> 0 | F31: =IF(F$4>=Inputs!$E$29,-F$10*'(Z+) OpEx'!$E$8,0) -> 0 | G31: =IF(G$4>=Inputs!$E$29,-G$10*'(Z+) OpEx'!$E$8,0) -> 0 | H31: =IF(H$4>=Inputs!$E$29,-H$10*'(Z+) OpEx'!$E$8,0) -> 0 | I31: =IF(I$4>=Inputs!$E$29,-I$10*'(Z+) OpEx'!$E$8,0) -> 0 | J31: =IF(J$4>=Inputs!$E$29,-J$10*'(Z+) OpEx'!$E$8,0) -> 0 | K31: =IF(K$4>=Inputs!$E$29,-K$10*'(Z+) OpEx'!$E$8,0) -> 0 | L31: =IF(L$4>=Inputs!$E$29,-L$10*'(Z+) OpEx'!$E$8,0) -> 0 | M31: =IF(M$4>=Inputs!$E$29,-M$10*'(Z+) OpEx'!$E$8,0) -> 0 | ... DU31: =IF(DU$4>=Inputs!$E$29,-DU$10*'(Z+) OpEx'!$E$8,0) -> 0
A32: =+'(Z+) OpEx'!C9 -> Insurance | C32: =+'(Z+) OpEx'!D9 -> 69 | F32: =IF(F$4>=Inputs!$E$29,-F$10*'(Z+) OpEx'!$E$9,0) -> 0 | G32: =IF(G$4>=Inputs!$E$29,-G$10*'(Z+) OpEx'!$E$9,0) -> 0 | H32: =IF(H$4>=Inputs!$E$29,-H$10*'(Z+) OpEx'!$E$9,0) -> 0 | I32: =IF(I$4>=Inputs!$E$29,-I$10*'(Z+) OpEx'!$E$9,0) -> 0 | J32: =IF(J$4>=Inputs!$E$29,-J$10*'(Z+) OpEx'!$E$9,0) -> 0 | K32: =IF(K$4>=Inputs!$E$29,-K$10*'(Z+) OpEx'!$E$9,0) -> 0 | L32: =IF(L$4>=Inputs!$E$29,-L$10*'(Z+) OpEx'!$E$9,0) -> 0 | M32: =IF(M$4>=Inputs!$E$29,-M$10*'(Z+) OpEx'!$E$9,0) -> 0 | ... DU32: =IF(DU$4>=Inputs!$E$29,-DU$10*'(Z+) OpEx'!$E$9,0) -> -21026.293
A33: =+'(Z+) OpEx'!C10 -> Management | C33: =+'(Z+) OpEx'!D10 -> 0.05 | F33: =-$C$33*F$19 -> 0 | G33: =-$C$33*G$19 -> 0 | H33: =-$C$33*H$19 -> 0 | I33: =-$C$33*I$19 -> 0 | J33: =-$C$33*J$19 -> 0 | K33: =-$C$33*K$19 -> 0 | L33: =-$C$33*L$19 -> 0 | M33: =-$C$33*M$19 -> 0 | ... DU33: =-$C$33*DU$19 -> -32662.458
A34: =+'(Z+) OpEx'!C14 -> Electric | C34: =+'(Z+) OpEx'!D14 -> 30 | F34: =IF(F$4>=Inputs!$E$29,-F$10*'(Z+) OpEx'!$E$14*F$12,0) -> 0 | G34: =IF(G$4>=Inputs!$E$29,-G$10*'(Z+) OpEx'!$E$14*G$12,0) -> 0 | H34: =IF(H$4>=Inputs!$E$29,-H$10*'(Z+) OpEx'!$E$14*H$12,0) -> 0 | I34: =IF(I$4>=Inputs!$E$29,-I$10*'(Z+) OpEx'!$E$14*I$12,0) -> 0 | J34: =IF(J$4>=Inputs!$E$29,-J$10*'(Z+) OpEx'!$E$14*J$12,0) -> 0 | K34: =IF(K$4>=Inputs!$E$29,-K$10*'(Z+) OpEx'!$E$14*K$12,0) -> 0 | L34: =IF(L$4>=Inputs!$E$29,-L$10*'(Z+) OpEx'!$E$14*L$12,0) -> 0 | M34: =IF(M$4>=Inputs!$E$29,-M$10*'(Z+) OpEx'!$E$14*M$12,0) -> 0 | ... DU34: =IF(DU$4>=Inputs!$E$29,-DU$10*'(Z+) OpEx'!$E$14*DU$12,0) -> -9231.4928
A35: =+'(Z+) OpEx'!C15 -> Water/Sewer | C35: =+'(Z+) OpEx'!D15 -> 30 | F35: =IF(F$4>=Inputs!$E$29,-F$10*'(Z+) OpEx'!$E$15*F$12,0) -> 0 | G35: =IF(G$4>=Inputs!$E$29,-G$10*'(Z+) OpEx'!$E$15*G$12,0) -> 0 | H35: =IF(H$4>=Inputs!$E$29,-H$10*'(Z+) OpEx'!$E$15*H$12,0) -> 0 | I35: =IF(I$4>=Inputs!$E$29,-I$10*'(Z+) OpEx'!$E$15*I$12,0) -> 0 | J35: =IF(J$4>=Inputs!$E$29,-J$10*'(Z+) OpEx'!$E$15*J$12,0) -> 0 | K35: =IF(K$4>=Inputs!$E$29,-K$10*'(Z+) OpEx'!$E$15*K$12,0) -> 0 | L35: =IF(L$4>=Inputs!$E$29,-L$10*'(Z+) OpEx'!$E$15*L$12,0) -> 0 | M35: =IF(M$4>=Inputs!$E$29,-M$10*'(Z+) OpEx'!$E$15*M$12,0) -> 0 | ... DU35: =IF(DU$4>=Inputs!$E$29,-DU$10*'(Z+) OpEx'!$E$15*DU$12,0) -> -9231.4928
A36: =+'(Z+) OpEx'!C16 -> Gas | C36: =+'(Z+) OpEx'!D16 -> 20 | F36: =IF(F$4>=Inputs!$E$29,-F$10*'(Z+) OpEx'!$E$16*F$12,0) -> 0 | G36: =IF(G$4>=Inputs!$E$29,-G$10*'(Z+) OpEx'!$E$16*G$12,0) -> 0 | H36: =IF(H$4>=Inputs!$E$29,-H$10*'(Z+) OpEx'!$E$16*H$12,0) -> 0 | I36: =IF(I$4>=Inputs!$E$29,-I$10*'(Z+) OpEx'!$E$16*I$12,0) -> 0 | J36: =IF(J$4>=Inputs!$E$29,-J$10*'(Z+) OpEx'!$E$16*J$12,0) -> 0 | K36: =IF(K$4>=Inputs!$E$29,-K$10*'(Z+) OpEx'!$E$16*K$12,0) -> 0 | L36: =IF(L$4>=Inputs!$E$29,-L$10*'(Z+) OpEx'!$E$16*L$12,0) -> 0 | M36: =IF(M$4>=Inputs!$E$29,-M$10*'(Z+) OpEx'!$E$16*M$12,0) -> 0 | ... DU36: =IF(DU$4>=Inputs!$E$29,-DU$10*'(Z+) OpEx'!$E$16*DU$12,0) -> -6154.3285
A37: =+'(Z+) OpEx'!C17 -> Trash | C37: =+'(Z+) OpEx'!D17 -> 28 | F37: =IF(F$4>=Inputs!$E$29,-F$10*'(Z+) OpEx'!$E$17*F$12,0) -> 0 | G37: =IF(G$4>=Inputs!$E$29,-G$10*'(Z+) OpEx'!$E$17*G$12,0) -> 0 | H37: =IF(H$4>=Inputs!$E$29,-H$10*'(Z+) OpEx'!$E$17*H$12,0) -> 0 | I37: =IF(I$4>=Inputs!$E$29,-I$10*'(Z+) OpEx'!$E$17*I$12,0) -> 0 | J37: =IF(J$4>=Inputs!$E$29,-J$10*'(Z+) OpEx'!$E$17*J$12,0) -> 0 | K37: =IF(K$4>=Inputs!$E$29,-K$10*'(Z+) OpEx'!$E$17*K$12,0) -> 0 | L37: =IF(L$4>=Inputs!$E$29,-L$10*'(Z+) OpEx'!$E$17*L$12,0) -> 0 | M37: =IF(M$4>=Inputs!$E$29,-M$10*'(Z+) OpEx'!$E$17*M$12,0) -> 0 | ... DU37: =IF(DU$4>=Inputs!$E$29,-DU$10*'(Z+) OpEx'!$E$17*DU$12,0) -> -8616.0599
A38: =+'(Z+) OpEx'!C18 -> Landscape | C38: =+'(Z+) OpEx'!D18 -> 0 | F38: =IF(F$4>=Inputs!$E$29,-F$10*'(Z+) OpEx'!$E$18*F$12,0) -> 0 | G38: =IF(G$4>=Inputs!$E$29,-G$10*'(Z+) OpEx'!$E$18*G$12,0) -> 0 | H38: =IF(H$4>=Inputs!$E$29,-H$10*'(Z+) OpEx'!$E$18*H$12,0) -> 0 | I38: =IF(I$4>=Inputs!$E$29,-I$10*'(Z+) OpEx'!$E$18*I$12,0) -> 0 | J38: =IF(J$4>=Inputs!$E$29,-J$10*'(Z+) OpEx'!$E$18*J$12,0) -> 0 | K38: =IF(K$4>=Inputs!$E$29,-K$10*'(Z+) OpEx'!$E$18*K$12,0) -> 0 | L38: =IF(L$4>=Inputs!$E$29,-L$10*'(Z+) OpEx'!$E$18*L$12,0) -> 0 | M38: =IF(M$4>=Inputs!$E$29,-M$10*'(Z+) OpEx'!$E$18*M$12,0) -> 0 | ... DU38: =IF(DU$4>=Inputs!$E$29,-DU$10*'(Z+) OpEx'!$E$18*DU$12,0) -> -824.24043
A39: =+'(Z+) OpEx'!C19 -> M&R/Turnover | C39: =+'(Z+) OpEx'!D19 -> 50 | F39: =IF(F$4>=Inputs!$E$29,F$10*'(Z+) OpEx'!$E$19*F$12,0) -> 0 | G39: =IF(G$4>=Inputs!$E$29,G$10*'(Z+) OpEx'!$E$19*G$12,0) -> 0 | H39: =IF(H$4>=Inputs!$E$29,H$10*'(Z+) OpEx'!$E$19*H$12,0) -> 0 | I39: =IF(I$4>=Inputs!$E$29,I$10*'(Z+) OpEx'!$E$19*I$12,0) -> 0 | J39: =IF(J$4>=Inputs!$E$29,J$10*'(Z+) OpEx'!$E$19*J$12,0) -> 0 | K39: =IF(K$4>=Inputs!$E$29,K$10*'(Z+) OpEx'!$E$19*K$12,0) -> 0 | L39: =IF(L$4>=Inputs!$E$29,L$10*'(Z+) OpEx'!$E$19*L$12,0) -> 0 | M39: =IF(M$4>=Inputs!$E$29,M$10*'(Z+) OpEx'!$E$19*M$12,0) -> 0 | ... DU39: =IF(DU$4>=Inputs!$E$29,DU$10*'(Z+) OpEx'!$E$19*DU$12,0) -> 15385.821
A40: =+'(Z+) OpEx'!C20 -> Payroll/Security | C40: =+'(Z+) OpEx'!D20 -> 0 | F40: =IF(F$4>=Inputs!$E$29,-F$10*'(Z+) OpEx'!$E$20,0) -> 0 | G40: =IF(G$4>=Inputs!$E$29,-G$10*'(Z+) OpEx'!$E$20,0) -> 0 | H40: =IF(H$4>=Inputs!$E$29,-H$10*'(Z+) OpEx'!$E$20,0) -> 0 | I40: =IF(I$4>=Inputs!$E$29,-I$10*'(Z+) OpEx'!$E$20,0) -> 0 | J40: =IF(J$4>=Inputs!$E$29,-J$10*'(Z+) OpEx'!$E$20,0) -> 0 | K40: =IF(K$4>=Inputs!$E$29,-K$10*'(Z+) OpEx'!$E$20,0) -> 0 | L40: =IF(L$4>=Inputs!$E$29,-L$10*'(Z+) OpEx'!$E$20,0) -> 0 | M40: =IF(M$4>=Inputs!$E$29,-M$10*'(Z+) OpEx'!$E$20,0) -> 0 | ... DU40: =IF(DU$4>=Inputs!$E$29,-DU$10*'(Z+) OpEx'!$E$20,0) -> -38845.962
A41: =+'(Z+) OpEx'!C21 -> HCID Fee | C41: =+'(Z+) OpEx'!D21 -> 22 | F41: =IF(F$4>=Inputs!$E$29,-F$10*'(Z+) OpEx'!$E$21,0) -> 0 | G41: =IF(G$4>=Inputs!$E$29,-G$10*'(Z+) OpEx'!$E$21,0) -> 0 | H41: =IF(H$4>=Inputs!$E$29,-H$10*'(Z+) OpEx'!$E$21,0) -> 0 | I41: =IF(I$4>=Inputs!$E$29,-I$10*'(Z+) OpEx'!$E$21,0) -> 0 | J41: =IF(J$4>=Inputs!$E$29,-J$10*'(Z+) OpEx'!$E$21,0) -> 0 | K41: =IF(K$4>=Inputs!$E$29,-K$10*'(Z+) OpEx'!$E$21,0) -> 0 | L41: =IF(L$4>=Inputs!$E$29,-L$10*'(Z+) OpEx'!$E$21,0) -> 0 | M41: =IF(M$4>=Inputs!$E$29,-M$10*'(Z+) OpEx'!$E$21,0) -> 0 | ... DU41: =IF(DU$4>=Inputs!$E$29,-DU$10*'(Z+) OpEx'!$E$21,0) -> -6769.7614
A42: =+'(Z+) OpEx'!C22 -> Elevator Maint. | C42: =+'(Z+) OpEx'!D22 -> 5 | F42: =IF(F$4>=Inputs!$E$29,-F$10*'(Z+) OpEx'!$E$22,0) -> 0 | G42: =IF(G$4>=Inputs!$E$29,-G$10*'(Z+) OpEx'!$E$22,0) -> 0 | H42: =IF(H$4>=Inputs!$E$29,-H$10*'(Z+) OpEx'!$E$22,0) -> 0 | I42: =IF(I$4>=Inputs!$E$29,-I$10*'(Z+) OpEx'!$E$22,0) -> 0 | J42: =IF(J$4>=Inputs!$E$29,-J$10*'(Z+) OpEx'!$E$22,0) -> 0 | K42: =IF(K$4>=Inputs!$E$29,-K$10*'(Z+) OpEx'!$E$22,0) -> 0 | L42: =IF(L$4>=Inputs!$E$29,-L$10*'(Z+) OpEx'!$E$22,0) -> 0 | M42: =IF(M$4>=Inputs!$E$29,-M$10*'(Z+) OpEx'!$E$22,0) -> 0 | ... DU42: =IF(DU$4>=Inputs!$E$29,-DU$10*'(Z+) OpEx'!$E$22,0) -> -1373.734
A43: =+'(Z+) OpEx'!C23 -> Legal | C43: =+'(Z+) OpEx'!D23 -> 5 | F43: =IF(F$4>=Inputs!$E$29,-F$10*'(Z+) OpEx'!$E$23*F$12,0) -> 0 | G43: =IF(G$4>=Inputs!$E$29,-G$10*'(Z+) OpEx'!$E$23*G$12,0) -> 0 | H43: =IF(H$4>=Inputs!$E$29,-H$10*'(Z+) OpEx'!$E$23*H$12,0) -> 0 | I43: =IF(I$4>=Inputs!$E$29,-I$10*'(Z+) OpEx'!$E$23*I$12,0) -> 0 | J43: =IF(J$4>=Inputs!$E$29,-J$10*'(Z+) OpEx'!$E$23*J$12,0) -> 0 | K43: =IF(K$4>=Inputs!$E$29,-K$10*'(Z+) OpEx'!$E$23*K$12,0) -> 0 | L43: =IF(L$4>=Inputs!$E$29,-L$10*'(Z+) OpEx'!$E$23*L$12,0) -> 0 | M43: =IF(M$4>=Inputs!$E$29,-M$10*'(Z+) OpEx'!$E$23*M$12,0) -> 0 | ... DU43: =IF(DU$4>=Inputs!$E$29,-DU$10*'(Z+) OpEx'!$E$23*DU$12,0) -> -1538.5821
A44: =+'(Z+) OpEx'!C24 -> Misc. | C44: =+'(Z+) OpEx'!D24 -> 180 | F44: =IF(F$4>=Inputs!$E$29,-F$10*'(Z+) OpEx'!$E$24,0) -> 0 | G44: =IF(G$4>=Inputs!$E$29,-G$10*'(Z+) OpEx'!$E$24,0) -> 0 | H44: =IF(H$4>=Inputs!$E$29,-H$10*'(Z+) OpEx'!$E$24,0) -> 0 | I44: =IF(I$4>=Inputs!$E$29,-I$10*'(Z+) OpEx'!$E$24,0) -> 0 | J44: =IF(J$4>=Inputs!$E$29,-J$10*'(Z+) OpEx'!$E$24,0) -> 0 | K44: =IF(K$4>=Inputs!$E$29,-K$10*'(Z+) OpEx'!$E$24,0) -> 0 | L44: =IF(L$4>=Inputs!$E$29,-L$10*'(Z+) OpEx'!$E$24,0) -> 0 | M44: =IF(M$4>=Inputs!$E$29,-M$10*'(Z+) OpEx'!$E$24,0) -> 0 | ... DU44: =IF(DU$4>=Inputs!$E$29,-DU$10*'(Z+) OpEx'!$E$24,0) -> -55388.957
A45: =+'(Z+) OpEx'!C25 -> Mgr's Rent Credit | F45: =IF(F$4>=Inputs!$E$29,-F$10*'(Z+) OpEx'!$E$25,0) -> 0 | G45: =IF(G$4>=Inputs!$E$29,-G$10*'(Z+) OpEx'!$E$25,0) -> 0 | H45: =IF(H$4>=Inputs!$E$29,-H$10*'(Z+) OpEx'!$E$25,0) -> 0 | I45: =IF(I$4>=Inputs!$E$29,-I$10*'(Z+) OpEx'!$E$25,0) -> 0 | J45: =IF(J$4>=Inputs!$E$29,-J$10*'(Z+) OpEx'!$E$25,0) -> 0 | K45: =IF(K$4>=Inputs!$E$29,-K$10*'(Z+) OpEx'!$E$25,0) -> 0 | L45: =IF(L$4>=Inputs!$E$29,-L$10*'(Z+) OpEx'!$E$25,0) -> 0 | M45: =IF(M$4>=Inputs!$E$29,-M$10*'(Z+) OpEx'!$E$25,0) -> 0 | ... DU45: =IF(DU$4>=Inputs!$E$29,-DU$10*'(Z+) OpEx'!$E$25,0) -> 0
A46: =+'(Z+) OpEx'!C26 -> Reserves | C46: =+'(Z+) OpEx'!D26 -> 1 | F46: =IF(F$4>=Inputs!$E$29,-F$10*'(Z+) OpEx'!$E$26,0) -> 0 | G46: =IF(G$4>=Inputs!$E$29,-G$10*'(Z+) OpEx'!$E$26,0) -> 0 | H46: =IF(H$4>=Inputs!$E$29,-H$10*'(Z+) OpEx'!$E$26,0) -> 0 | I46: =IF(I$4>=Inputs!$E$29,-I$10*'(Z+) OpEx'!$E$26,0) -> 0 | J46: =IF(J$4>=Inputs!$E$29,-J$10*'(Z+) OpEx'!$E$26,0) -> 0 | K46: =IF(K$4>=Inputs!$E$29,-K$10*'(Z+) OpEx'!$E$26,0) -> 0 | L46: =IF(L$4>=Inputs!$E$29,-L$10*'(Z+) OpEx'!$E$26,0) -> 0 | M46: =IF(M$4>=Inputs!$E$29,-M$10*'(Z+) OpEx'!$E$26,0) -> 0 | ... DU46: =IF(DU$4>=Inputs!$E$29,-DU$10*'(Z+) OpEx'!$E$26,0) -> -307.71643
A47: Operating Expense | F47: =SUM(F$31:F$46) -> 0 | G47: =SUM(G$31:G$46) -> 0 | H47: =SUM(H$31:H$46) -> 0 | I47: =SUM(I$31:I$46) -> 0 | J47: =SUM(J$31:J$46) -> 0 | K47: =SUM(K$31:K$46) -> 0 | L47: =SUM(L$31:L$46) -> 0 | M47: =SUM(M$31:M$46) -> 0 | ... DU47: =SUM(DU$31:DU$46) -> -176585.26
A48: Net Operating Income | F48: =+SUM(F$19,F$47) -> 0 | G48: =+SUM(G$19,G$47) -> 0 | H48: =+SUM(H$19,H$47) -> 0 | I48: =+SUM(I$19,I$47) -> 0 | J48: =+SUM(J$19,J$47) -> 0 | K48: =+SUM(K$19,K$47) -> 0 | L48: =+SUM(L$19,L$47) -> 0 | M48: =+SUM(M$19,M$47) -> 0 | ... DU48: =+SUM(DU$19,DU$47) -> 476663.9
A49: Operating Ratio | F49: =IF(F$19>0,-F$47/F$19,"") | G49: =IF(G$19>0,-G$47/G$19,"") | H49: =IF(H$19>0,-H$47/H$19,"") | I49: =IF(I$19>0,-I$47/I$19,"") | J49: =IF(J$19>0,-J$47/J$19,"") | K49: =IF(K$19>0,-K$47/K$19,"") | L49: =IF(L$19>0,-L$47/L$19,"") | M49: =IF(M$19>0,-M$47/M$19,"") | ... DU49: =IF(DU$19>0,-DU$47/DU$19,"") -> 0.27031839
A50: Covenanted Net Operating Income | F50: =SUM(F$29,F$47) -> 0 | G50: =SUM(G$29,G$47) -> 0 | H50: =SUM(H$29,H$47) -> 0 | I50: =SUM(I$29,I$47) -> 0 | J50: =SUM(J$29,J$47) -> 0 | K50: =SUM(K$29,K$47) -> 0 | L50: =SUM(L$29,L$47) -> 0 | M50: =SUM(M$29,M$47) -> 0 | ... DU50: =SUM(DU$29,DU$47) -> -155846.09
A51: Covenanted Operating Ratio | F51: =IF(F$29>0,-F47/F$29,"") | G51: =IF(G$29>0,-G47/G$29,"") | H51: =IF(H$29>0,-H47/H$29,"") | I51: =IF(I$29>0,-I47/I$29,"") | J51: =IF(J$29>0,-J47/J$29,"") | K51: =IF(K$29>0,-K47/K$29,"") | L51: =IF(L$29>0,-L47/L$29,"") | M51: =IF(M$29>0,-M47/M$29,"") | ... DU51: =IF(DU$29>0,-DU47/DU$29,"") -> 8.5145772
A53: Release of Operating Shortfall Reserve | F53: =-MIN(F48,0) -> 0 | G53: =-MIN(G48,0) -> 0 | H53: =-MIN(H48,0) -> 0 | I53: =-MIN(I48,0) -> 0 | J53: =-MIN(J48,0) -> 0 | K53: =-MIN(K48,0) -> 0 | L53: =-MIN(L48,0) -> 0 | M53: =-MIN(M48,0) -> 0 | ... DU53: =-MIN(DU48,0) -> 0
A54: Sales Proceeds | F54: =IFERROR((F4=Inputs!$E$38)*'(Z+) Financing'!$H$40, 0) -> 0 | G54: =IFERROR((G4=Inputs!$E$38)*'(Z+) Financing'!$H$40, 0) -> 0 | H54: =IFERROR((H4=Inputs!$E$38)*'(Z+) Financing'!$H$40, 0) -> 0 | I54: =IFERROR((I4=Inputs!$E$38)*'(Z+) Financing'!$H$40, 0) -> 0 | J54: =IFERROR((J4=Inputs!$E$38)*'(Z+) Financing'!$H$40, 0) -> 0 | K54: =IFERROR((K4=Inputs!$E$38)*'(Z+) Financing'!$H$40, 0) -> 0 | L54: =IFERROR((L4=Inputs!$E$38)*'(Z+) Financing'!$H$40, 0) -> 0 | M54: =IFERROR((M4=Inputs!$E$38)*'(Z+) Financing'!$H$40, 0) -> 0 | ... DU54: =IFERROR((DU4=Inputs!$E$38)*'(Z+) Financing'!$H$40, 0) -> 0
A56: Total Unlevered Income | D56: =IFERROR(SUM(F56:GB56),0) -> 85939507 | F56: =+IFERROR((F$4<=Inputs!$E$38)*(F54+F48+F53),0) -> 0 | G56: =+IFERROR((G$4<=Inputs!$E$38)*(G54+G48+G53),0) -> 0 | H56: =+IFERROR((H$4<=Inputs!$E$38)*(H54+H48+H53),0) -> 0 | I56: =+IFERROR((I$4<=Inputs!$E$38)*(I54+I48+I53),0) -> 0 | J56: =+IFERROR((J$4<=Inputs!$E$38)*(J54+J48+J53),0) -> 0 | K56: =+IFERROR((K$4<=Inputs!$E$38)*(K54+K48+K53),0) -> 0 | L56: =+IFERROR((L$4<=Inputs!$E$38)*(L54+L48+L53),0) -> 0 | M56: =+IFERROR((M$4<=Inputs!$E$38)*(M54+M48+M53),0) -> 0 | ... DU56: =+IFERROR((DU$4<=Inputs!$E$38)*(DU54+DU48+DU53),0) -> 0
A58: % Hard Costs | D58: =IFERROR(SUM(F58:CM58),0) -> 1 | F58: =IFERROR(IF(AND(F$4>Construction_Start_Date,F$4<=Inputs!$E$27),(NORMDIST(F$5-Inputs!$D$25,Inputs!$E$26/2,'(Z+) Dev Budget'!$D$80,TRUE())- NORMDIST(F$5-Inputs!$D$25-1,Inputs!$E$26/2,'(Z+) Dev Budget'!$D$80,TRUE()))/(1-2* NORMDIST(0,Inputs!$E$26/2,'(Z+) Dev Budget'!$D$80,TRUE())),0),0) -> 0 | G58: =IFERROR(IF(AND(G$4>Construction_Start_Date,G$4<=Inputs!$E$27),(NORMDIST(G$5-Inputs!$D$25,Inputs!$E$26/2,'(Z+) Dev Budget'!$D$80,TRUE())- NORMDIST(G$5-Inputs!$D$25-1,Inputs!$E$26/2,'(Z+) Dev Budget'!$D$80,TRUE()))/(1-2* NORMDIST(0,Inputs!$E$26/2,'(Z+) Dev Budget'!$D$80,TRUE())),0),0) -> 0 | H58: =IFERROR(IF(AND(H$4>Construction_Start_Date,H$4<=Inputs!$E$27),(NORMDIST(H$5-Inputs!$D$25,Inputs!$E$26/2,'(Z+) Dev Budget'!$D$80,TRUE())- NORMDIST(H$5-Inputs!$D$25-1,Inputs!$E$26/2,'(Z+) Dev Budget'!$D$80,TRUE()))/(1-2* NORMDIST(0,Inputs!$E$26/2,'(Z+) Dev Budget'!$D$80,TRUE())),0),0) -> 0 | I58: =IFERROR(IF(AND(I$4>Construction_Start_Date,I$4<=Inputs!$E$27),(NORMDIST(I$5-Inputs!$D$25,Inputs!$E$26/2,'(Z+) Dev Budget'!$D$80,TRUE())- NORMDIST(I$5-Inputs!$D$25-1,Inputs!$E$26/2,'(Z+) Dev Budget'!$D$80,TRUE()))/(1-2* NORMDIST(0,Inputs!$E$26/2,'(Z+) Dev Budget'!$D$80,TRUE())),0),0) -> 0 | J58: =IFERROR(IF(AND(J$4>Construction_Start_Date,J$4<=Inputs!$E$27),(NORMDIST(J$5-Inputs!$D$25,Inputs!$E$26/2,'(Z+) Dev Budget'!$D$80,TRUE())- NORMDIST(J$5-Inputs!$D$25-1,Inputs!$E$26/2,'(Z+) Dev Budget'!$D$80,TRUE()))/(1-2* NORMDIST(0,Inputs!$E$26/2,'(Z+) Dev Budget'!$D$80,TRUE())),0),0) -> 0 | K58: =IFERROR(IF(AND(K$4>Construction_Start_Date,K$4<=Inputs!$E$27),(NORMDIST(K$5-Inputs!$D$25,Inputs!$E$26/2,'(Z+) Dev Budget'!$D$80,TRUE())- NORMDIST(K$5-Inputs!$D$25-1,Inputs!$E$26/2,'(Z+) Dev Budget'!$D$80,TRUE()))/(1-2* NORMDIST(0,Inputs!$E$26/2,'(Z+) Dev Budget'!$D$80,TRUE())),0),0) -> 0 | L58: =IFERROR(IF(AND(L$4>Construction_Start_Date,L$4<=Inputs!$E$27),(NORMDIST(L$5-Inputs!$D$25,Inputs!$E$26/2,'(Z+) Dev Budget'!$D$80,TRUE())- NORMDIST(L$5-Inputs!$D$25-1,Inputs!$E$26/2,'(Z+) Dev Budget'!$D$80,TRUE()))/(1-2* NORMDIST(0,Inputs!$E$26/2,'(Z+) Dev Budget'!$D$80,TRUE())),0),0) -> 0 | M58: =IFERROR(IF(AND(M$4>Construction_Start_Date,M$4<=Inputs!$E$27),(NORMDIST(M$5-Inputs!$D$25,Inputs!$E$26/2,'(Z+) Dev Budget'!$D$80,TRUE())- NORMDIST(M$5-Inputs!$D$25-1,Inputs!$E$26/2,'(Z+) Dev Budget'!$D$80,TRUE()))/(1-2* NORMDIST(0,Inputs!$E$26/2,'(Z+) Dev Budget'!$D$80,TRUE())),0),0) -> 0 | ... DU58: =IFERROR(IF(AND(DU$4>Construction_Start_Date,DU$4<=Inputs!$E$27),(NORMDIST(DU$5-Inputs!$D$25,Inputs!$E$26/2,'(Z+) Dev Budget'!$D$80,TRUE())- NORMDIST(DU$5-Inputs!$D$25-1,Inputs!$E$26/2,'(Z+) Dev Budget'!$D$80,TRUE()))/(1-2* NORMDIST(0,Inputs!$E$26/2,'(Z+) Dev Budget'!$D$80,TRUE())),0),0) -> 0
A59: % Soft Costs - Preconstruction Period | D59: =IFERROR(SUM(F59:HB59),0) -> 1 | F59: =IFERROR(IF(AND(F$4>Greenlight_Date,F$4<=Construction_Start_Date),(NORMDIST(F$5-Greenlight_Mo,(Inputs!$D$25-Greenlight_Mo)/2,'(Z+) Dev Budget'!$D$80,TRUE())-NORMDIST(F$5-Greenlight_Mo-1,(Inputs!$D$25-Greenlight_Mo)/2,'(Z+) Dev Budget'!$D$80,TRUE()))/(1-2*NORMDIST(0,(Inputs!$D$25-Greenlight_Mo)/2,'(Z+) Dev Budget'!$D$80,TRUE())),0),0) -> 0 | G59: =IFERROR(IF(AND(G$4>Greenlight_Date,G$4<=Construction_Start_Date),(NORMDIST(G$5-Greenlight_Mo,(Inputs!$D$25-Greenlight_Mo)/2,'(Z+) Dev Budget'!$D$80,TRUE())-NORMDIST(G$5-Greenlight_Mo-1,(Inputs!$D$25-Greenlight_Mo)/2,'(Z+) Dev Budget'!$D$80,TRUE()))/(1-2*NORMDIST(0,(Inputs!$D$25-Greenlight_Mo)/2,'(Z+) Dev Budget'!$D$80,TRUE())),0),0) -> 0 | H59: =IFERROR(IF(AND(H$4>Greenlight_Date,H$4<=Construction_Start_Date),(NORMDIST(H$5-Greenlight_Mo,(Inputs!$D$25-Greenlight_Mo)/2,'(Z+) Dev Budget'!$D$80,TRUE())-NORMDIST(H$5-Greenlight_Mo-1,(Inputs!$D$25-Greenlight_Mo)/2,'(Z+) Dev Budget'!$D$80,TRUE()))/(1-2*NORMDIST(0,(Inputs!$D$25-Greenlight_Mo)/2,'(Z+) Dev Budget'!$D$80,TRUE())),0),0) -> 0 | I59: =IFERROR(IF(AND(I$4>Greenlight_Date,I$4<=Construction_Start_Date),(NORMDIST(I$5-Greenlight_Mo,(Inputs!$D$25-Greenlight_Mo)/2,'(Z+) Dev Budget'!$D$80,TRUE())-NORMDIST(I$5-Greenlight_Mo-1,(Inputs!$D$25-Greenlight_Mo)/2,'(Z+) Dev Budget'!$D$80,TRUE()))/(1-2*NORMDIST(0,(Inputs!$D$25-Greenlight_Mo)/2,'(Z+) Dev Budget'!$D$80,TRUE())),0),0) -> 0 | J59: =IFERROR(IF(AND(J$4>Greenlight_Date,J$4<=Construction_Start_Date),(NORMDIST(J$5-Greenlight_Mo,(Inputs!$D$25-Greenlight_Mo)/2,'(Z+) Dev Budget'!$D$80,TRUE())-NORMDIST(J$5-Greenlight_Mo-1,(Inputs!$D$25-Greenlight_Mo)/2,'(Z+) Dev Budget'!$D$80,TRUE()))/(1-2*NORMDIST(0,(Inputs!$D$25-Greenlight_Mo)/2,'(Z+) Dev Budget'!$D$80,TRUE())),0),0) -> 0.15576105 | K59: =IFERROR(IF(AND(K$4>Greenlight_Date,K$4<=Construction_Start_Date),(NORMDIST(K$5-Greenlight_Mo,(Inputs!$D$25-Greenlight_Mo)/2,'(Z+) Dev Budget'!$D$80,TRUE())-NORMDIST(K$5-Greenlight_Mo-1,(Inputs!$D$25-Greenlight_Mo)/2,'(Z+) Dev Budget'!$D$80,TRUE()))/(1-2*NORMDIST(0,(Inputs!$D$25-Greenlight_Mo)/2,'(Z+) Dev Budget'!$D$80,TRUE())),0),0) -> 0.168689 | L59: =IFERROR(IF(AND(L$4>Greenlight_Date,L$4<=Construction_Start_Date),(NORMDIST(L$5-Greenlight_Mo,(Inputs!$D$25-Greenlight_Mo)/2,'(Z+) Dev Budget'!$D$80,TRUE())-NORMDIST(L$5-Greenlight_Mo-1,(Inputs!$D$25-Greenlight_Mo)/2,'(Z+) Dev Budget'!$D$80,TRUE()))/(1-2*NORMDIST(0,(Inputs!$D$25-Greenlight_Mo)/2,'(Z+) Dev Budget'!$D$80,TRUE())),0),0) -> 0.17554995 | M59: =IFERROR(IF(AND(M$4>Greenlight_Date,M$4<=Construction_Start_Date),(NORMDIST(M$5-Greenlight_Mo,(Inputs!$D$25-Greenlight_Mo)/2,'(Z+) Dev Budget'!$D$80,TRUE())-NORMDIST(M$5-Greenlight_Mo-1,(Inputs!$D$25-Greenlight_Mo)/2,'(Z+) Dev Budget'!$D$80,TRUE()))/(1-2*NORMDIST(0,(Inputs!$D$25-Greenlight_Mo)/2,'(Z+) Dev Budget'!$D$80,TRUE())),0),0) -> 0.17554995 | ... DU59: =IFERROR(IF(AND(DU$4>Greenlight_Date,DU$4<=Construction_Start_Date),(NORMDIST(DU$5-Greenlight_Mo,(Inputs!$D$25-Greenlight_Mo)/2,'(Z+) Dev Budget'!$D$80,TRUE())-NORMDIST(DU$5-Greenlight_Mo-1,(Inputs!$D$25-Greenlight_Mo)/2,'(Z+) Dev Budget'!$D$80,TRUE()))/(1-2*NORMDIST(0,(Inputs!$D$25-Greenlight_Mo)/2,'(Z+) Dev Budget'!$D$80,TRUE())),0),0) -> 0
A60: % Soft Costs - Construction Period | D60: =IFERROR(SUM(F60:HB60),0) -> 1 | F60: =IFERROR(IF(AND(F4<=Inputs!$E$27,F4>Construction_Start_Date),1/Inputs!$E$26,0),0) -> 0 | G60: =IFERROR(IF(AND(G4<=Inputs!$E$27,G4>Construction_Start_Date),1/Inputs!$E$26,0),0) -> 0 | H60: =IFERROR(IF(AND(H4<=Inputs!$E$27,H4>Construction_Start_Date),1/Inputs!$E$26,0),0) -> 0 | I60: =IFERROR(IF(AND(I4<=Inputs!$E$27,I4>Construction_Start_Date),1/Inputs!$E$26,0),0) -> 0 | J60: =IFERROR(IF(AND(J4<=Inputs!$E$27,J4>Construction_Start_Date),1/Inputs!$E$26,0),0) -> 0 | K60: =IFERROR(IF(AND(K4<=Inputs!$E$27,K4>Construction_Start_Date),1/Inputs!$E$26,0),0) -> 0 | L60: =IFERROR(IF(AND(L4<=Inputs!$E$27,L4>Construction_Start_Date),1/Inputs!$E$26,0),0) -> 0 | M60: =IFERROR(IF(AND(M4<=Inputs!$E$27,M4>Construction_Start_Date),1/Inputs!$E$26,0),0) -> 0 | ... DU60: =IFERROR(IF(AND(DU4<=Inputs!$E$27,DU4>Construction_Start_Date),1/Inputs!$E$26,0),0) -> 0
A62: Land/Acquisition Costs | D62: =SUM(F62:HB62) -> -1601600 | F62: =IFERROR(IF(Inputs!$E$22='(Z+) Monthly CF'!F4,-'(Z+) Dev Budget'!$G$10,0),0) -> 0 | G62: =IFERROR(IF(Inputs!$E$22='(Z+) Monthly CF'!G4,-'(Z+) Dev Budget'!$G$10,0),0) -> 0 | H62: =IFERROR(IF(Inputs!$E$22='(Z+) Monthly CF'!H4,-'(Z+) Dev Budget'!$G$10,0),0) -> 0 | I62: =IFERROR(IF(Inputs!$E$22='(Z+) Monthly CF'!I4,-'(Z+) Dev Budget'!$G$10,0),0) -> -1601600 | J62: =IFERROR(IF(Inputs!$E$22='(Z+) Monthly CF'!J4,-'(Z+) Dev Budget'!$G$10,0),0) -> 0 | K62: =IFERROR(IF(Inputs!$E$22='(Z+) Monthly CF'!K4,-'(Z+) Dev Budget'!$G$10,0),0) -> 0 | L62: =IFERROR(IF(Inputs!$E$22='(Z+) Monthly CF'!L4,-'(Z+) Dev Budget'!$G$10,0),0) -> 0 | M62: =IFERROR(IF(Inputs!$E$22='(Z+) Monthly CF'!M4,-'(Z+) Dev Budget'!$G$10,0),0) -> 0 | ... DU62: =IFERROR(IF(Inputs!$E$22='(Z+) Monthly CF'!DU4,-'(Z+) Dev Budget'!$G$10,0),0) -> 0
A63: Hard Costs | D63: =IFERROR(SUM(F63:HC63),0) -> -23567340 | F63: =-IFERROR(('(Z+) Dev Budget'!$G$30-'(Z+) Dev Budget'!$G$14-'(Z+) Dev Budget'!$G$21)*F58,0) -> 0 | G63: =-IFERROR(('(Z+) Dev Budget'!$G$30-'(Z+) Dev Budget'!$G$14-'(Z+) Dev Budget'!$G$21)*G58,0) -> 0 | H63: =-IFERROR(('(Z+) Dev Budget'!$G$30-'(Z+) Dev Budget'!$G$14-'(Z+) Dev Budget'!$G$21)*H58,0) -> 0 | I63: =-IFERROR(('(Z+) Dev Budget'!$G$30-'(Z+) Dev Budget'!$G$14-'(Z+) Dev Budget'!$G$21)*I58,0) -> 0 | J63: =-IFERROR(('(Z+) Dev Budget'!$G$30-'(Z+) Dev Budget'!$G$14-'(Z+) Dev Budget'!$G$21)*J58,0) -> 0 | K63: =-IFERROR(('(Z+) Dev Budget'!$G$30-'(Z+) Dev Budget'!$G$14-'(Z+) Dev Budget'!$G$21)*K58,0) -> 0 | L63: =-IFERROR(('(Z+) Dev Budget'!$G$30-'(Z+) Dev Budget'!$G$14-'(Z+) Dev Budget'!$G$21)*L58,0) -> 0 | M63: =-IFERROR(('(Z+) Dev Budget'!$G$30-'(Z+) Dev Budget'!$G$14-'(Z+) Dev Budget'!$G$21)*M58,0) -> 0 | ... DU63: =-IFERROR(('(Z+) Dev Budget'!$G$30-'(Z+) Dev Budget'!$G$14-'(Z+) Dev Budget'!$G$21)*DU58,0) -> 0
A64: Modular Factory Costs | D64: ='(Z+) Dev Budget'!G14 -> 20160000 | F64: =-IF(OR(F5=(const_start+2),F5=(const_start+3)), mod_costs*0.1, IF(F5=(const_start-2),mod_costs*0.5,IF(F5=const_start+1, mod_costs*0.3, 0))) -> 0 | G64: =-IF(OR(G5=(const_start+2),G5=(const_start+3)), mod_costs*0.1, IF(G5=(const_start-2),mod_costs*0.5,IF(G5=const_start+1, mod_costs*0.3, 0))) -> 0 | H64: =-IF(OR(H5=(const_start+2),H5=(const_start+3)), mod_costs*0.1, IF(H5=(const_start-2),mod_costs*0.5,IF(H5=const_start+1, mod_costs*0.3, 0))) -> 0 | I64: =-IF(OR(I5=(const_start+2),I5=(const_start+3)), mod_costs*0.1, IF(I5=(const_start-2),mod_costs*0.5,IF(I5=const_start+1, mod_costs*0.3, 0))) -> 0 | J64: =-IF(OR(J5=(const_start+2),J5=(const_start+3)), mod_costs*0.1, IF(J5=(const_start-2),mod_costs*0.5,IF(J5=const_start+1, mod_costs*0.3, 0))) -> 0 | K64: =-IF(OR(K5=(const_start+2),K5=(const_start+3)), mod_costs*0.1, IF(K5=(const_start-2),mod_costs*0.5,IF(K5=const_start+1, mod_costs*0.3, 0))) -> 0 | L64: =-IF(OR(L5=(const_start+2),L5=(const_start+3)), mod_costs*0.1, IF(L5=(const_start-2),mod_costs*0.5,IF(L5=const_start+1, mod_costs*0.3, 0))) -> 0 | M64: =-IF(OR(M5=(const_start+2),M5=(const_start+3)), mod_costs*0.1, IF(M5=(const_start-2),mod_costs*0.5,IF(M5=const_start+1, mod_costs*0.3, 0))) -> -10080000 | ... DU64: =-IF(OR(DU5=(const_start+2),DU5=(const_start+3)), mod_costs*0.1, IF(DU5=(const_start-2),mod_costs*0.5,IF(DU5=const_start+1, mod_costs*0.3, 0))) -> 0
A65: Modular Logistics Costs | D65: ='(Z+) Dev Budget'!G21 -> 336000 | F65: =-IF(OR((const_start+1)=F5, F5=(const_start+2), F5=(const_start+3)),logistics_cost*0.28,IF(OR((const_start+4)=F5,(const_start+5)=F5,(const_start+6)=F5),logistics_cost*0.06,0)) -> 0 | G65: =-IF(OR((const_start+1)=G5, G5=(const_start+2), G5=(const_start+3)),logistics_cost*0.28,IF(OR((const_start+4)=G5,(const_start+5)=G5,(const_start+6)=G5),logistics_cost*0.06,0)) -> 0 | H65: =-IF(OR((const_start+1)=H5, H5=(const_start+2), H5=(const_start+3)),logistics_cost*0.28,IF(OR((const_start+4)=H5,(const_start+5)=H5,(const_start+6)=H5),logistics_cost*0.06,0)) -> 0 | I65: =-IF(OR((const_start+1)=I5, I5=(const_start+2), I5=(const_start+3)),logistics_cost*0.28,IF(OR((const_start+4)=I5,(const_start+5)=I5,(const_start+6)=I5),logistics_cost*0.06,0)) -> 0 | J65: =-IF(OR((const_start+1)=J5, J5=(const_start+2), J5=(const_start+3)),logistics_cost*0.28,IF(OR((const_start+4)=J5,(const_start+5)=J5,(const_start+6)=J5),logistics_cost*0.06,0)) -> 0 | K65: =-IF(OR((const_start+1)=K5, K5=(const_start+2), K5=(const_start+3)),logistics_cost*0.28,IF(OR((const_start+4)=K5,(const_start+5)=K5,(const_start+6)=K5),logistics_cost*0.06,0)) -> 0 | L65: =-IF(OR((const_start+1)=L5, L5=(const_start+2), L5=(const_start+3)),logistics_cost*0.28,IF(OR((const_start+4)=L5,(const_start+5)=L5,(const_start+6)=L5),logistics_cost*0.06,0)) -> 0 | M65: =-IF(OR((const_start+1)=M5, M5=(const_start+2), M5=(const_start+3)),logistics_cost*0.28,IF(OR((const_start+4)=M5,(const_start+5)=M5,(const_start+6)=M5),logistics_cost*0.06,0)) -> 0 | ... DU65: =-IF(OR((const_start+1)=DU5, DU5=(const_start+2), DU5=(const_start+3)),logistics_cost*0.28,IF(OR((const_start+4)=DU5,(const_start+5)=DU5,(const_start+6)=DU5),logistics_cost*0.06,0)) -> 0
A66: Admin Costs | D66: =IFERROR(SUM(F66:HC66),0) -> -2609303.2 | F66: =+IFERROR(('(Z+) Dev Budget'!$G$115/SUM('(Z+) Dev Budget'!$G$109,'(Z+) Dev Budget'!$G$30))*SUM(F63,F67:F69,F64,F65),0) -> -820.44215 | G66: =+IFERROR(('(Z+) Dev Budget'!$G$115/SUM('(Z+) Dev Budget'!$G$109,'(Z+) Dev Budget'!$G$30))*SUM(G63,G67:G69,G64,G65),0) -> 0 | H66: =+IFERROR(('(Z+) Dev Budget'!$G$115/SUM('(Z+) Dev Budget'!$G$109,'(Z+) Dev Budget'!$G$30))*SUM(H63,H67:H69,H64,H65),0) -> 0 | I66: =+IFERROR(('(Z+) Dev Budget'!$G$115/SUM('(Z+) Dev Budget'!$G$109,'(Z+) Dev Budget'!$G$30))*SUM(I63,I67:I69,I64,I65),0) -> 0 | J66: =+IFERROR(('(Z+) Dev Budget'!$G$115/SUM('(Z+) Dev Budget'!$G$109,'(Z+) Dev Budget'!$G$30))*SUM(J63,J67:J69,J64,J65),0) -> -18506.323 | K66: =+IFERROR(('(Z+) Dev Budget'!$G$115/SUM('(Z+) Dev Budget'!$G$109,'(Z+) Dev Budget'!$G$30))*SUM(K63,K67:K69,K64,K65),0) -> -20042.322 | L66: =+IFERROR(('(Z+) Dev Budget'!$G$115/SUM('(Z+) Dev Budget'!$G$109,'(Z+) Dev Budget'!$G$30))*SUM(L63,L67:L69,L64,L65),0) -> -20857.488 | M66: =+IFERROR(('(Z+) Dev Budget'!$G$115/SUM('(Z+) Dev Budget'!$G$109,'(Z+) Dev Budget'!$G$30))*SUM(M63,M67:M69,M64,M65),0) -> -572194.61 | ... DU66: =+IFERROR(('(Z+) Dev Budget'!$G$115/SUM('(Z+) Dev Budget'!$G$109,'(Z+) Dev Budget'!$G$30))*SUM(DU63,DU67:DU69,DU64,DU65),0) -> 0
A67: Due Diligence Costs | D67: =IFERROR(SUM(F67:HC67),0) -> -15000 | F67: =-IFERROR('(Z+) Dev Budget'!$G$46,0) -> -15000 | G67: 0 | H67: 0 | I67: 0 | J67: 0 | K67: 0 | L67: 0 | M67: 0 | N67: 0 | O67: 0 | P67: 0 | Q67: 0 | R67: 0 | S67: 0 | T67: 0 | U67: 0 | V67: 0 | W67: 0 | X67: 0 | Y67: 0 | Z67: 0 | AA67: 0 | AB67: 0 | AC67: 0 | AD67: 0 | AE67: 0 | AF67: 0 | AG67: 0 | AH67: 0 | AI67: 0 | AJ67: 0 | AK67: 0 | AL67: 0 | AM67: 0 | AN67: 0 | AO67: 0 | AP67: 0 | AQ67: 0 | AR67: 0 | AS67: 0 | AT67: 0 | AU67: 0 | AV67: 0 | AW67: 0 | AX67: 0 | AY67: 0 | AZ67: 0 | BA67: 0 | BB67: 0 | BC67: 0 | BD67: 0 | BE67: 0 | BF67: 0 | BG67: 0 | BH67: 0 | BI67: 0 | BJ67: 0 | BK67: 0 | BL67: 0 | BM67: 0 | BN67: 0 | BO67: 0 | BP67: 0 | BQ67: 0 | BR67: 0 | BS67: 0 | BT67: 0 | BU67: 0 | BV67: 0 | BW67: 0 | BX67: 0 | BY67: 0 | BZ67: 0 | CA67: 0 | CB67: 0 | CC67: 0 | CD67: 0 | CE67: 0 | CF67: 0 | CG67: 0 | CH67: 0 | CI67: 0 | CJ67: 0 | CK67: 0 | CL67: 0 | CM67: 0 | CN67: 0 | CO67: 0 | CP67: 0 | CQ67: 0 | CR67: 0 | CS67: 0 | CT67: 0 | CU67: 0 | CV67: 0 | CW67: 0 | CX67: 0 | CY67: 0 | CZ67: 0 | DA67: 0 | DB67: 0 | DC67: 0 | DD67: 0 | DE67: 0 | DF67: 0 | DG67: 0 | DH67: 0 | DI67: 0 | DJ67: 0 | DK67: 0 | DL67: 0 | DM67: 0 | DN67: 0 | DO67: 0 | DP67: 0 | DQ67: 0 | DR67: 0 | DS67: 0 | DT67: 0 | DU67: 0
A68: Soft Costs - Preconstruction Period | D68: =IFERROR(SUM(F68:HC68),0) -> -2172223.8 | F68: =-IFERROR(F$59*('(Z+) Dev Budget'!$G$109-'(Z+) Dev Budget'!$G$46)*Inputs!$L$11,0) -> 0 | G68: =-IFERROR(G$59*('(Z+) Dev Budget'!$G$109-'(Z+) Dev Budget'!$G$46)*Inputs!$L$11,0) -> 0 | H68: =-IFERROR(H$59*('(Z+) Dev Budget'!$G$109-'(Z+) Dev Budget'!$G$46)*Inputs!$L$11,0) -> 0 | I68: =-IFERROR(I$59*('(Z+) Dev Budget'!$G$109-'(Z+) Dev Budget'!$G$46)*Inputs!$L$11,0) -> 0 | J68: =-IFERROR(J$59*('(Z+) Dev Budget'!$G$109-'(Z+) Dev Budget'!$G$46)*Inputs!$L$11,0) -> -338347.85 | K68: =-IFERROR(K$59*('(Z+) Dev Budget'!$G$109-'(Z+) Dev Budget'!$G$46)*Inputs!$L$11,0) -> -366430.26 | L68: =-IFERROR(L$59*('(Z+) Dev Budget'!$G$109-'(Z+) Dev Budget'!$G$46)*Inputs!$L$11,0) -> -381333.79 | M68: =-IFERROR(M$59*('(Z+) Dev Budget'!$G$109-'(Z+) Dev Budget'!$G$46)*Inputs!$L$11,0) -> -381333.79 | ... DU68: =-IFERROR(DU$59*('(Z+) Dev Budget'!$G$109-'(Z+) Dev Budget'!$G$46)*Inputs!$L$11,0) -> 0
A69: Soft Costs - Construction Period | D69: =IFERROR(SUM(F69:HC69),0) -> -1448149.2 | F69: =-IFERROR(F$60*('(Z+) Dev Budget'!$G$109-'(Z+) Dev Budget'!$G$46)*(1-Inputs!$L$11),0) -> 0 | G69: =-IFERROR(G$60*('(Z+) Dev Budget'!$G$109-'(Z+) Dev Budget'!$G$46)*(1-Inputs!$L$11),0) -> 0 | H69: =-IFERROR(H$60*('(Z+) Dev Budget'!$G$109-'(Z+) Dev Budget'!$G$46)*(1-Inputs!$L$11),0) -> 0 | I69: =-IFERROR(I$60*('(Z+) Dev Budget'!$G$109-'(Z+) Dev Budget'!$G$46)*(1-Inputs!$L$11),0) -> 0 | J69: =-IFERROR(J$60*('(Z+) Dev Budget'!$G$109-'(Z+) Dev Budget'!$G$46)*(1-Inputs!$L$11),0) -> 0 | K69: =-IFERROR(K$60*('(Z+) Dev Budget'!$G$109-'(Z+) Dev Budget'!$G$46)*(1-Inputs!$L$11),0) -> 0 | L69: =-IFERROR(L$60*('(Z+) Dev Budget'!$G$109-'(Z+) Dev Budget'!$G$46)*(1-Inputs!$L$11),0) -> 0 | M69: =-IFERROR(M$60*('(Z+) Dev Budget'!$G$109-'(Z+) Dev Budget'!$G$46)*(1-Inputs!$L$11),0) -> 0 | ... DU69: =-IFERROR(DU$60*('(Z+) Dev Budget'!$G$109-'(Z+) Dev Budget'!$G$46)*(1-Inputs!$L$11),0) -> 0
A70: Total Unlevered Costs | D70: =IFERROR(SUM(F70:HC70),0) -> -51916336 | F70: =IFERROR(SUM(F62:F69),0) -> -15820.442 | G70: =IFERROR(SUM(G62:G69),0) -> 0 | H70: =IFERROR(SUM(H62:H69),0) -> 0 | I70: =IFERROR(SUM(I62:I69),0) -> -1601600 | J70: =IFERROR(SUM(J62:J69),0) -> -356854.17 | K70: =IFERROR(SUM(K62:K69),0) -> -386472.59 | L70: =IFERROR(SUM(L62:L69),0) -> -402191.27 | M70: =IFERROR(SUM(M62:M69),0) -> -11033528 | ... DU70: =IFERROR(SUM(DU62:DU69),0) -> 0
A71: Cumulative Unlevered Costs | F71: =IFERROR(F70,0) -> -15820.442 | G71: =F71-G70 -> -15820.442 | H71: =G71-H70 -> -15820.442 | I71: =H71-I70 -> 1585779.6 | J71: =I71-J70 -> 1942633.7 | K71: =J71-K70 -> 2329106.3 | L71: =K71-L70 -> 2731297.6 | M71: =L71-M70 -> 13764826 | N71: =M71-N70 -> 14151299 | ... DU71: =DT71-DU70 -> 51884695
A73: Unlevered Project Cash Flow | D73: =IFERROR(SUM(F73:HB73),0) -> 34023171 | F73: =IFERROR(F56+F70,0) -> -15820.442 | G73: =IFERROR(G56+G70,0) -> 0 | H73: =IFERROR(H56+H70,0) -> 0 | I73: =IFERROR(I56+I70,0) -> -1601600 | J73: =IFERROR(J56+J70,0) -> -356854.17 | K73: =IFERROR(K56+K70,0) -> -386472.59 | L73: =IFERROR(L56+L70,0) -> -402191.27 | M73: =IFERROR(M56+M70,0) -> -11033528 | ... DU73: =IFERROR(DU56+DU70,0) -> 0
C74: Unlevered IIR | D74: =XIRR(F73:HB73,F4:HB4) -> 0.097391468
A75: LEVERED PRO FORMA
A77: Interest | D77: =IFERROR(SUM(F77:HC77),0) -> 3886817.2 | F77: =F91 -> 0 | G77: =G91 -> 0 | H77: =H91 -> 0 | I77: =I91 -> 0 | J77: =J91 -> 0 | K77: =K91 -> 0 | L77: =L91 -> 0 | M77: =M91 -> 0 | ... DU77: =DU91 -> 0
A78: Loan Closing Costs | D78: =IFERROR(SUM(F78:HC78),0) -> 365176.8 | F78: =IFERROR(F88+F90,0) -> 0 | G78: =IFERROR(G88+G90,0) -> 0 | H78: =IFERROR(H88+H90,0) -> 0 | I78: =IFERROR(I88+I90,0) -> 0 | J78: =IFERROR(J88+J90,0) -> 0 | K78: =IFERROR(K88+K90,0) -> 0 | L78: =IFERROR(L88+L90,0) -> 0 | M78: =IFERROR(M88+M90,0) -> 0 | ... DU78: =IFERROR(DU88+DU90,0) -> 0
A79: Total Levered Costs | F79: =IFERROR(F70+F77+F78, 0) -> -15820.442 | G79: =IFERROR(G70+G77+G78, 0) -> 0 | H79: =IFERROR(H70+H77+H78, 0) -> 0 | I79: =IFERROR(I70+I77+I78, 0) -> -1601600 | J79: =IFERROR(J70+J77+J78, 0) -> -356854.17 | K79: =IFERROR(K70+K77+K78, 0) -> -386472.59 | L79: =IFERROR(L70+L77+L78, 0) -> -402191.27 | M79: =IFERROR(M70+M77+M78, 0) -> -11033528 | ... DU79: =IFERROR(DU70+DU77+DU78, 0) -> 0
A81: Equity Contributions | F81: =IFERROR(MAX(0,MIN(-F70,(F83-E82))),0) -> 15820.442 | G81: =IFERROR(MAX(0,MIN(-G70,(G83-F82))),0) -> 0 | H81: =IFERROR(MAX(0,MIN(-H70,(H83-G82))),0) -> 0 | I81: =IFERROR(MAX(0,MIN(-I70,(I83-H82))),0) -> 1601600 | J81: =IFERROR(MAX(0,MIN(-J70,(J83-I82))),0) -> 356854.17 | K81: =IFERROR(MAX(0,MIN(-K70,(K83-J82))),0) -> 386472.59 | L81: =IFERROR(MAX(0,MIN(-L70,(L83-K82))),0) -> 402191.27 | M81: =IFERROR(MAX(0,MIN(-M70,(M83-L82))),0) -> 11033528 | ... DU81: =IFERROR(MAX(0,MIN(-DU70,(DU83-DT82))),0) -> 0
A82: Cumulative Equity Contributions | F82: =IFERROR(F81+E82, 0) -> 15820.442 | G82: =IFERROR(G81+F82, 0) -> 15820.442 | H82: =IFERROR(H81+G82, 0) -> 15820.442 | I82: =IFERROR(I81+H82, 0) -> 1617420.4 | J82: =IFERROR(J81+I82, 0) -> 1974274.6 | K82: =IFERROR(K81+J82, 0) -> 2360747.2 | L82: =IFERROR(L81+K82, 0) -> 2762938.5 | M82: =IFERROR(M81+L82, 0) -> 13796467 | ... DU82: =IFERROR(DU81+DT82, 0) -> 23841608
A83: Max Equity Committed | F83: =IFERROR(IF(F4<Construction_Start_Date,Inputs!$L$15,Inputs!$L$19),0) -> 15572775 | G83: =IFERROR(IF(G4<Construction_Start_Date,Inputs!$L$15,Inputs!$L$19),0) -> 15572775 | H83: =IFERROR(IF(H4<Construction_Start_Date,Inputs!$L$15,Inputs!$L$19),0) -> 15572775 | I83: =IFERROR(IF(I4<Construction_Start_Date,Inputs!$L$15,Inputs!$L$19),0) -> 15572775 | J83: =IFERROR(IF(J4<Construction_Start_Date,Inputs!$L$15,Inputs!$L$19),0) -> 15572775 | K83: =IFERROR(IF(K4<Construction_Start_Date,Inputs!$L$15,Inputs!$L$19),0) -> 15572775 | L83: =IFERROR(IF(L4<Construction_Start_Date,Inputs!$L$15,Inputs!$L$19),0) -> 15572775 | M83: =IFERROR(IF(M4<Construction_Start_Date,Inputs!$L$15,Inputs!$L$19),0) -> 15572775 | ... DU83: =IFERROR(IF(DU4<Construction_Start_Date,Inputs!$L$15,Inputs!$L$19),0) -> 23841608
A85: Bridge Financing Rate | F85: =IF(F4<Construction_Start_Date,'(Z+) Financing'!$D$7*365.25/360/12,'(Z+) Financing'!$D$36*365.25/360/12) -> 0.0070767187 | G85: =IF(G4<Construction_Start_Date,'(Z+) Financing'!$D$7*365.25/360/12,'(Z+) Financing'!$D$36*365.25/360/12) -> 0.0070767187 | H85: =IF(H4<Construction_Start_Date,'(Z+) Financing'!$D$7*365.25/360/12,'(Z+) Financing'!$D$36*365.25/360/12) -> 0.0070767187 | I85: =IF(I4<Construction_Start_Date,'(Z+) Financing'!$D$7*365.25/360/12,'(Z+) Financing'!$D$36*365.25/360/12) -> 0.0070767187 | J85: =IF(J4<Construction_Start_Date,'(Z+) Financing'!$D$7*365.25/360/12,'(Z+) Financing'!$D$36*365.25/360/12) -> 0.0070767187 | K85: =IF(K4<Construction_Start_Date,'(Z+) Financing'!$D$7*365.25/360/12,'(Z+) Financing'!$D$36*365.25/360/12) -> 0.0070767187 | L85: =IF(L4<Construction_Start_Date,'(Z+) Financing'!$D$7*365.25/360/12,'(Z+) Financing'!$D$36*365.25/360/12) -> 0.0070767187 | M85: =IF(M4<Construction_Start_Date,'(Z+) Financing'!$D$7*365.25/360/12,'(Z+) Financing'!$D$36*365.25/360/12) -> 0.0070767187 | ... DU85: =IF(DU4<Construction_Start_Date,'(Z+) Financing'!$D$7*365.25/360/12,'(Z+) Financing'!$D$36*365.25/360/12) -> 0.007609375
A86: Beginning Balance | F86: =E93 -> 0 | G86: =F93 -> 0 | H86: =G93 -> 0 | I86: =H93 -> 0 | J86: =I93 -> 0 | K86: =J93 -> 0 | L86: =K93 -> 0 | M86: =L93 -> 0 | ... DU86: =DT93 -> 0
A87: Loan Draw - Acquisition Loan | D87: =IFERROR(SUM(F87:HC87), 0) -> 0 | F87: =(F4<Construction_Start_Date)*(-F70-F81) -> 0 | G87: =(G4<Construction_Start_Date)*(-G70-G81) -> 0 | H87: =(H4<Construction_Start_Date)*(-H70-H81) -> 0 | I87: =(I4<Construction_Start_Date)*(-I70-I81) -> 0 | J87: =(J4<Construction_Start_Date)*(-J70-J81) -> 0 | K87: =(K4<Construction_Start_Date)*(-K70-K81) -> 0 | L87: =(L4<Construction_Start_Date)*(-L70-L81) -> 0 | M87: =(M4<Construction_Start_Date)*(-M70-M81) -> 0 | ... DU87: =(DU4<Construction_Start_Date)*(-DU70-DU81) -> 0
A88: Financing Closing Cost - Acquisition Loan | D88: =IFERROR(SUM(F88:HC88), 0) -> 0 | F88: =(F4=Inputs!$E$21)*('(Z+) Financing'!$D$9) -> 0 | G88: =(G4=Inputs!$E$21)*('(Z+) Financing'!$D$9) -> 0 | H88: =(H4=Inputs!$E$21)*('(Z+) Financing'!$D$9) -> 0 | I88: =(I4=Inputs!$E$21)*('(Z+) Financing'!$D$9) -> 0 | J88: =(J4=Inputs!$E$21)*('(Z+) Financing'!$D$9) -> 0 | K88: =(K4=Inputs!$E$21)*('(Z+) Financing'!$D$9) -> 0 | L88: =(L4=Inputs!$E$21)*('(Z+) Financing'!$D$9) -> 0 | M88: =(M4=Inputs!$E$21)*('(Z+) Financing'!$D$9) -> 0 | ... DU88: =(DU4=Inputs!$E$21)*('(Z+) Financing'!$D$9) -> 0
A89: Loan Draw - Construction Loan | D89: =IFERROR(SUM(F89:HC89), 0) -> 28074728 | F89: =(F4>=Construction_Start_Date)*(-F70-F81) -> 0 | G89: =(G4>=Construction_Start_Date)*(-G70-G81) -> 0 | H89: =(H4>=Construction_Start_Date)*(-H70-H81) -> 0 | I89: =(I4>=Construction_Start_Date)*(-I70-I81) -> 0 | J89: =(J4>=Construction_Start_Date)*(-J70-J81) -> 0 | K89: =(K4>=Construction_Start_Date)*(-K70-K81) -> 0 | L89: =(L4>=Construction_Start_Date)*(-L70-L81) -> 0 | M89: =(M4>=Construction_Start_Date)*(-M70-M81) -> 0 | ... DU89: =(DU4>=Construction_Start_Date)*(-DU70-DU81) -> 0
A90: Financing Closing Cost - Construction Loan | D90: =IFERROR(SUM(F90:HC90), 0) -> 365176.8 | F90: =(F4=Construction_Start_Date)*('(Z+) Financing'!$D$40) -> 0 | G90: =(G4=Construction_Start_Date)*('(Z+) Financing'!$D$40) -> 0 | H90: =(H4=Construction_Start_Date)*('(Z+) Financing'!$D$40) -> 0 | I90: =(I4=Construction_Start_Date)*('(Z+) Financing'!$D$40) -> 0 | J90: =(J4=Construction_Start_Date)*('(Z+) Financing'!$D$40) -> 0 | K90: =(K4=Construction_Start_Date)*('(Z+) Financing'!$D$40) -> 0 | L90: =(L4=Construction_Start_Date)*('(Z+) Financing'!$D$40) -> 0 | M90: =(M4=Construction_Start_Date)*('(Z+) Financing'!$D$40) -> 0 | ... DU90: =(DU4=Construction_Start_Date)*('(Z+) Financing'!$D$40) -> 0
A91: Interest Reserve | D91: =IFERROR(SUM(F91:HC91), 0) -> 3886817.2 | F91: =F85*F86 -> 0 | G91: =G85*G86 -> 0 | H91: =H85*H86 -> 0 | I91: =I85*I86 -> 0 | J91: =J85*J86 -> 0 | K91: =K85*K86 -> 0 | L91: =L85*L86 -> 0 | M91: =M85*M86 -> 0 | ... DU91: =DU85*DU86 -> 0
A92: Paydown | D92: =IFERROR(SUM(F92:HC92), 0) -> -32326722 | F92: =-MAX(0,MIN(F56+F95,SUM(F86:F91))) -> 0 | G92: =-MAX(0,MIN(G56+G95,SUM(G86:G91))) -> 0 | H92: =-MAX(0,MIN(H56+H95,SUM(H86:H91))) -> 0 | I92: =-MAX(0,MIN(I56+I95,SUM(I86:I91))) -> 0 | J92: =-MAX(0,MIN(J56+J95,SUM(J86:J91))) -> 0 | K92: =-MAX(0,MIN(K56+K95,SUM(K86:K91))) -> 0 | L92: =-MAX(0,MIN(L56+L95,SUM(L86:L91))) -> 0 | M92: =-MAX(0,MIN(M56+M95,SUM(M86:M91))) -> 0 | ... DU92: =-MAX(0,MIN(DU56+DU95,SUM(DU86:DU91))) -> 0
A93: Ending Balance | F93: =SUM(F86:F92) -> 0 | G93: =SUM(G86:G92) -> 0 | H93: =SUM(H86:H92) -> 0 | I93: =SUM(I86:I92) -> 0 | J93: =SUM(J86:J92) -> 0 | K93: =SUM(K86:K92) -> 0 | L93: =SUM(L86:L92) -> 0 | M93: =SUM(M86:M92) -> 0 | ... DU93: =SUM(DU86:DU92) -> 0
A95: Permanent Loan Proceeds | F95: =(F4=refinance_date)*(perm_proceeds)*(100-perm_fees)*0.01 -> 0 | G95: =(G4=refinance_date)*(perm_proceeds)*(100-perm_fees)*0.01 -> 0 | H95: =(H4=refinance_date)*(perm_proceeds)*(100-perm_fees)*0.01 -> 0 | I95: =(I4=refinance_date)*(perm_proceeds)*(100-perm_fees)*0.01 -> 0 | J95: =(J4=refinance_date)*(perm_proceeds)*(100-perm_fees)*0.01 -> 0 | K95: =(K4=refinance_date)*(perm_proceeds)*(100-perm_fees)*0.01 -> 0 | L95: =(L4=refinance_date)*(perm_proceeds)*(100-perm_fees)*0.01 -> 0 | M95: =(M4=refinance_date)*(perm_proceeds)*(100-perm_fees)*0.01 -> 0 | ... DU95: =(DU4=refinance_date)*(perm_proceeds)*(100-perm_fees)*0.01 -> 0
A96: Interest | F96: =IF(AND(F4>refinance_date,F4<=sale_month),IPMT('(Z+) Financing'!$H$18*365.25/360/12,ROUND(DAYS360(refinance_date,F4)/30,0),'(Z+) Financing'!$H$21*12,perm_proceeds),0) -> 0 | G96: =IF(AND(G4>refinance_date,G4<=sale_month),IPMT('(Z+) Financing'!$H$18*365.25/360/12,ROUND(DAYS360(refinance_date,G4)/30,0),'(Z+) Financing'!$H$21*12,perm_proceeds),0) -> 0 | H96: =IF(AND(H4>refinance_date,H4<=sale_month),IPMT('(Z+) Financing'!$H$18*365.25/360/12,ROUND(DAYS360(refinance_date,H4)/30,0),'(Z+) Financing'!$H$21*12,perm_proceeds),0) -> 0 | I96: =IF(AND(I4>refinance_date,I4<=sale_month),IPMT('(Z+) Financing'!$H$18*365.25/360/12,ROUND(DAYS360(refinance_date,I4)/30,0),'(Z+) Financing'!$H$21*12,perm_proceeds),0) -> 0 | J96: =IF(AND(J4>refinance_date,J4<=sale_month),IPMT('(Z+) Financing'!$H$18*365.25/360/12,ROUND(DAYS360(refinance_date,J4)/30,0),'(Z+) Financing'!$H$21*12,perm_proceeds),0) -> 0 | K96: =IF(AND(K4>refinance_date,K4<=sale_month),IPMT('(Z+) Financing'!$H$18*365.25/360/12,ROUND(DAYS360(refinance_date,K4)/30,0),'(Z+) Financing'!$H$21*12,perm_proceeds),0) -> 0 | L96: =IF(AND(L4>refinance_date,L4<=sale_month),IPMT('(Z+) Financing'!$H$18*365.25/360/12,ROUND(DAYS360(refinance_date,L4)/30,0),'(Z+) Financing'!$H$21*12,perm_proceeds),0) -> 0 | M96: =IF(AND(M4>refinance_date,M4<=sale_month),IPMT('(Z+) Financing'!$H$18*365.25/360/12,ROUND(DAYS360(refinance_date,M4)/30,0),'(Z+) Financing'!$H$21*12,perm_proceeds),0) -> 0 | ... DU96: =IF(AND(DU4>refinance_date,DU4<=sale_month),IPMT('(Z+) Financing'!$H$18*365.25/360/12,ROUND(DAYS360(refinance_date,DU4)/30,0),'(Z+) Financing'!$H$21*12,perm_proceeds),0) -> 0
A97: Loan Amortization | F97: =IF(AND(F4>refinance_date,F4<=sale_month),PMT('(Z+) Financing'!$H$18*365.25/360/12,'(Z+) Financing'!$H$21*12,perm_proceeds),0)-F96 -> 0 | G97: =IF(AND(G4>refinance_date,G4<=sale_month),PMT('(Z+) Financing'!$H$18*365.25/360/12,'(Z+) Financing'!$H$21*12,perm_proceeds),0)-G96 -> 0 | H97: =IF(AND(H4>refinance_date,H4<=sale_month),PMT('(Z+) Financing'!$H$18*365.25/360/12,'(Z+) Financing'!$H$21*12,perm_proceeds),0)-H96 -> 0 | I97: =IF(AND(I4>refinance_date,I4<=sale_month),PMT('(Z+) Financing'!$H$18*365.25/360/12,'(Z+) Financing'!$H$21*12,perm_proceeds),0)-I96 -> 0 | J97: =IF(AND(J4>refinance_date,J4<=sale_month),PMT('(Z+) Financing'!$H$18*365.25/360/12,'(Z+) Financing'!$H$21*12,perm_proceeds),0)-J96 -> 0 | K97: =IF(AND(K4>refinance_date,K4<=sale_month),PMT('(Z+) Financing'!$H$18*365.25/360/12,'(Z+) Financing'!$H$21*12,perm_proceeds),0)-K96 -> 0 | L97: =IF(AND(L4>refinance_date,L4<=sale_month),PMT('(Z+) Financing'!$H$18*365.25/360/12,'(Z+) Financing'!$H$21*12,perm_proceeds),0)-L96 -> 0 | M97: =IF(AND(M4>refinance_date,M4<=sale_month),PMT('(Z+) Financing'!$H$18*365.25/360/12,'(Z+) Financing'!$H$21*12,perm_proceeds),0)-M96 -> 0 | ... DU97: =IF(AND(DU4>refinance_date,DU4<=sale_month),PMT('(Z+) Financing'!$H$18*365.25/360/12,'(Z+) Financing'!$H$21*12,perm_proceeds),0)-DU96 -> 0
A98: Paydown | F98: =(F4=sale_month)*(-perm_proceeds-SUM($F$97:F97)) -> 0 | G98: =(G4=sale_month)*(-perm_proceeds-SUM($F$97:G97)) -> 0 | H98: =(H4=sale_month)*(-perm_proceeds-SUM($F$97:H97)) -> 0 | I98: =(I4=sale_month)*(-perm_proceeds-SUM($F$97:I97)) -> 0 | J98: =(J4=sale_month)*(-perm_proceeds-SUM($F$97:J97)) -> 0 | K98: =(K4=sale_month)*(-perm_proceeds-SUM($F$97:K97)) -> 0 | L98: =(L4=sale_month)*(-perm_proceeds-SUM($F$97:L97)) -> 0 | M98: =(M4=sale_month)*(-perm_proceeds-SUM($F$97:M97)) -> 0 | ... DU98: =(DU4=sale_month)*(-perm_proceeds-SUM($F$97:DU97)) -> 0
A100: Levered Project Cash Flow | D100: =SUM(F100:HB100) -> 17170572 | F100: =-F81+F56+F95+F96+F97+F98+F92+F106+F107+F108+F109 -> -15820.442 | G100: =-G81+G56+G95+G96+G97+G98+G92+G106+G107+G108+G109 -> 0 | H100: =-H81+H56+H95+H96+H97+H98+H92+H106+H107+H108+H109 -> 0 | I100: =-I81+I56+I95+I96+I97+I98+I92+I106+I107+I108+I109 -> -1601600 | J100: =-J81+J56+J95+J96+J97+J98+J92+J106+J107+J108+J109 -> -356854.17 | K100: =-K81+K56+K95+K96+K97+K98+K92+K106+K107+K108+K109 -> -386472.59 | L100: =-L81+L56+L95+L96+L97+L98+L92+L106+L107+L108+L109 -> -402191.27 | M100: =-M81+M56+M95+M96+M97+M98+M92+M106+M107+M108+M109 -> -11033528 | ... DU100: =-DU81+DU56+DU95+DU96+DU97+DU98+DU92+DU106+DU107+DU108+DU109 -> 0
B102: Gross Unlevered IRR | F102: =XIRR(F73:DM73,F4:DM4) -> 0.097391468
B103: Gross Levered IRR | F103: =XIRR(F100:DM100,F4:DM4) -> 0.15538478
B104: Equity Multiple (Project-Level) | F104: =SUMIF(F100:DM100,">0")/-SUMIF(F100:DM100,"<0") -> 1.7201935
D106: Sub Loan Proceeds | F106: =(F4=refinance_date)*('(Z+) Financing'!$D$43) -> 0 | G106: =(G4=refinance_date)*('(Z+) Financing'!$D$43) -> 0 | H106: =(H4=refinance_date)*('(Z+) Financing'!$D$43) -> 0 | I106: =(I4=refinance_date)*('(Z+) Financing'!$D$43) -> 0 | J106: =(J4=refinance_date)*('(Z+) Financing'!$D$43) -> 0 | K106: =(K4=refinance_date)*('(Z+) Financing'!$D$43) -> 0 | L106: =(L4=refinance_date)*('(Z+) Financing'!$D$43) -> 0 | M106: =(M4=refinance_date)*('(Z+) Financing'!$D$43) -> 0 | ... DU106: =(DU4=refinance_date)*('(Z+) Financing'!$D$43) -> 0
D107: Sub Interest | F107: =IF(AND(F4>refinance_date,F4<=sale_month),IF('(Z+) Financing'!$D$45>0,IPMT('(Z+) Financing'!$D$44*365.25/360/12,ROUND(DAYS360(refinance_date,F4)/30,0),'(Z+) Financing'!$D$45*12,'(Z+) Financing'!$D$43),-'(Z+) Financing'!$D$43*'(Z+) Financing'!$D$44*365.25/360/12),0) -> 0 | G107: =IF(AND(G4>refinance_date,G4<=sale_month),IF('(Z+) Financing'!$D$45>0,IPMT('(Z+) Financing'!$D$44*365.25/360/12,ROUND(DAYS360(refinance_date,G4)/30,0),'(Z+) Financing'!$D$45*12,'(Z+) Financing'!$D$43),-'(Z+) Financing'!$D$43*'(Z+) Financing'!$D$44*365.25/360/12),0) -> 0 | H107: =IF(AND(H4>refinance_date,H4<=sale_month),IF('(Z+) Financing'!$D$45>0,IPMT('(Z+) Financing'!$D$44*365.25/360/12,ROUND(DAYS360(refinance_date,H4)/30,0),'(Z+) Financing'!$D$45*12,'(Z+) Financing'!$D$43),-'(Z+) Financing'!$D$43*'(Z+) Financing'!$D$44*365.25/360/12),0) -> 0 | I107: =IF(AND(I4>refinance_date,I4<=sale_month),IF('(Z+) Financing'!$D$45>0,IPMT('(Z+) Financing'!$D$44*365.25/360/12,ROUND(DAYS360(refinance_date,I4)/30,0),'(Z+) Financing'!$D$45*12,'(Z+) Financing'!$D$43),-'(Z+) Financing'!$D$43*'(Z+) Financing'!$D$44*365.25/360/12),0) -> 0 | J107: =IF(AND(J4>refinance_date,J4<=sale_month),IF('(Z+) Financing'!$D$45>0,IPMT('(Z+) Financing'!$D$44*365.25/360/12,ROUND(DAYS360(refinance_date,J4)/30,0),'(Z+) Financing'!$D$45*12,'(Z+) Financing'!$D$43),-'(Z+) Financing'!$D$43*'(Z+) Financing'!$D$44*365.25/360/12),0) -> 0 | K107: =IF(AND(K4>refinance_date,K4<=sale_month),IF('(Z+) Financing'!$D$45>0,IPMT('(Z+) Financing'!$D$44*365.25/360/12,ROUND(DAYS360(refinance_date,K4)/30,0),'(Z+) Financing'!$D$45*12,'(Z+) Financing'!$D$43),-'(Z+) Financing'!$D$43*'(Z+) Financing'!$D$44*365.25/360/12),0) -> 0 | L107: =IF(AND(L4>refinance_date,L4<=sale_month),IF('(Z+) Financing'!$D$45>0,IPMT('(Z+) Financing'!$D$44*365.25/360/12,ROUND(DAYS360(refinance_date,L4)/30,0),'(Z+) Financing'!$D$45*12,'(Z+) Financing'!$D$43),-'(Z+) Financing'!$D$43*'(Z+) Financing'!$D$44*365.25/360/12),0) -> 0 | M107: =IF(AND(M4>refinance_date,M4<=sale_month),IF('(Z+) Financing'!$D$45>0,IPMT('(Z+) Financing'!$D$44*365.25/360/12,ROUND(DAYS360(refinance_date,M4)/30,0),'(Z+) Financing'!$D$45*12,'(Z+) Financing'!$D$43),-'(Z+) Financing'!$D$43*'(Z+) Financing'!$D$44*365.25/360/12),0) -> 0 | ... DU107: =IF(AND(DU4>refinance_date,DU4<=sale_month),IF('(Z+) Financing'!$D$45>0,IPMT('(Z+) Financing'!$D$44*365.25/360/12,ROUND(DAYS360(refinance_date,DU4)/30,0),'(Z+) Financing'!$D$45*12,'(Z+) Financing'!$D$43),-'(Z+) Financing'!$D$43*'(Z+) Financing'!$D$44*365.25/360/12),0) -> 0
D108: Sub Principal | F108: =IF(AND(F4>refinance_date,F4<=sale_month),IF('(Z+) Financing'!$D$45>0,PMT('(Z+) Financing'!$D$44*365.25/360/12,'(Z+) Financing'!$D$45*12,'(Z+) Financing'!$D$43)-F107,0),0) -> 0 | G108: =IF(AND(G4>refinance_date,G4<=sale_month),IF('(Z+) Financing'!$D$45>0,PMT('(Z+) Financing'!$D$44*365.25/360/12,'(Z+) Financing'!$D$45*12,'(Z+) Financing'!$D$43)-G107,0),0) -> 0 | H108: =IF(AND(H4>refinance_date,H4<=sale_month),IF('(Z+) Financing'!$D$45>0,PMT('(Z+) Financing'!$D$44*365.25/360/12,'(Z+) Financing'!$D$45*12,'(Z+) Financing'!$D$43)-H107,0),0) -> 0 | I108: =IF(AND(I4>refinance_date,I4<=sale_month),IF('(Z+) Financing'!$D$45>0,PMT('(Z+) Financing'!$D$44*365.25/360/12,'(Z+) Financing'!$D$45*12,'(Z+) Financing'!$D$43)-I107,0),0) -> 0 | J108: =IF(AND(J4>refinance_date,J4<=sale_month),IF('(Z+) Financing'!$D$45>0,PMT('(Z+) Financing'!$D$44*365.25/360/12,'(Z+) Financing'!$D$45*12,'(Z+) Financing'!$D$43)-J107,0),0) -> 0 | K108: =IF(AND(K4>refinance_date,K4<=sale_month),IF('(Z+) Financing'!$D$45>0,PMT('(Z+) Financing'!$D$44*365.25/360/12,'(Z+) Financing'!$D$45*12,'(Z+) Financing'!$D$43)-K107,0),0) -> 0 | L108: =IF(AND(L4>refinance_date,L4<=sale_month),IF('(Z+) Financing'!$D$45>0,PMT('(Z+) Financing'!$D$44*365.25/360/12,'(Z+) Financing'!$D$45*12,'(Z+) Financing'!$D$43)-L107,0),0) -> 0 | M108: =IF(AND(M4>refinance_date,M4<=sale_month),IF('(Z+) Financing'!$D$45>0,PMT('(Z+) Financing'!$D$44*365.25/360/12,'(Z+) Financing'!$D$45*12,'(Z+) Financing'!$D$43)-M107,0),0) -> 0 | ... DU108: =IF(AND(DU4>refinance_date,DU4<=sale_month),IF('(Z+) Financing'!$D$45>0,PMT('(Z+) Financing'!$D$44*365.25/360/12,'(Z+) Financing'!$D$45*12,'(Z+) Financing'!$D$43)-DU107,0),0) -> 0
D109: Sub Payoff | F109: =(F4=sale_month)*(-'(Z+) Financing'!$D$43-SUM($F$108:F108)) -> 0 | G109: =(G4=sale_month)*(-'(Z+) Financing'!$D$43-SUM($F$108:G108)) -> 0 | H109: =(H4=sale_month)*(-'(Z+) Financing'!$D$43-SUM($F$108:H108)) -> 0 | I109: =(I4=sale_month)*(-'(Z+) Financing'!$D$43-SUM($F$108:I108)) -> 0 | J109: =(J4=sale_month)*(-'(Z+) Financing'!$D$43-SUM($F$108:J108)) -> 0 | K109: =(K4=sale_month)*(-'(Z+) Financing'!$D$43-SUM($F$108:K108)) -> 0 | L109: =(L4=sale_month)*(-'(Z+) Financing'!$D$43-SUM($F$108:L108)) -> 0 | M109: =(M4=sale_month)*(-'(Z+) Financing'!$D$43-SUM($F$108:M108)) -> 0 | ... DU109: =(DU4=sale_month)*(-'(Z+) Financing'!$D$43-SUM($F$108:DU108)) -> 0
